Workbook

Sheet Inputs
A1: Variable | B1: Description | C1: Units | D1: Value | E1: Experimental Value | F1: Value Used
A2: PLANT
A3: otp | B3: Operating Time | C3: hr/yr | D3: 8000 | F3: =IF(ISBLANK(E3),D3,E3) -> 8000
A4: qcow | B4: manure produced by cows on average | C4: kg/d-cow | D4: 53.8 | F4: =IF(ISBLANK(E4),D4,E4) -> 53.8
A5: dcow | B5: distance to travel for manure collection | C5: mi | D5: 60 | F5: =IF(ISBLANK(E5),D5,E5) -> 60
A6: dfw | B6: distance to travel for food waste collection | C6: mi | D6: 60 | F6: =IF(ISBLANK(E6),D6,E6) -> 60
A7: tmpg | B7: transportation fuel consumption | C7: mi/gal | D7: 0.45 | F7: =IF(ISBLANK(E7),D7,E7) -> 0.45
A8: tspd | B8: speed of transportation vehicle | C8: mi/hr | D8: 60 | F8: =IF(ISBLANK(E8),D8,E8) -> 60
A9: pump_efficiency | B9: effeciency of the pumps | C9: %/100 | D9: 0.7 | F9: =IF(ISBLANK(E9),D9,E9) -> 0.7
F10: =IF(ISBLANK(E10),D10,E10) -> 0
F11: =IF(ISBLANK(E11),D11,E11) -> 0
A12: Feedstock Characteristics | F12: =IF(ISBLANK(E12),D12,E12) -> 0 | H12: Total Plant Flow Rates
A13: qow | B13: organic waste feedstock flow rate | C13: kg/hr | D13: 150000 | E13: 25000 | F13: =IF(ISBLANK(E13),D13,E13) -> 25000 | H13: m3/hr | J13: ton/hr | L13: ton/yr | N13: ton/d
A14: pfw | B14: percentage of food waste in feedstock | C14: %/100 | D14: 0.1 | F14: =IF(ISBLANK(E14),D14,E14) -> 0.1 | H14: Path A | I14: Path AB | J14: Path A | K14: Path AB | L14: Path A | M14: Path AB | N14: Path A | O14: Path AB
A15: ppoo | B15: percentage of manure in feedstock | C15: %/100 | D15: 0.9 | F15: =IF(ISBLANK(E15),D15,E15) -> 0.9 | H15: =F13/1050 -> 23.809524 | I15: =F13/(1050)*2 -> 47.619048 | J15: =Inputs!F13/Units!C45 -> 27.557775 | K15: =Inputs!F13/(Units!C45)*2 -> 55.11555 | L15: =J15*Units!C55*Units!C52 -> 241406.11 | M15: =K15*Units!C55*Units!C52 -> 482812.22 | N15: =J15*Units!C55 -> 661.3866 | O15: =N15*2 -> 1322.7732
A16: pcow | B16: percentage of manure from cattle in feedstock | C16: %/100 | D16: 0.6 | F16: =IF(ISBLANK(E16),D16,E16) -> 0.6
A17: ppig | B17: percentage of manure from pigs in feedstock | C17: %/100 | D17: 0.4 | F17: =IF(ISBLANK(E17),D17,E17) -> 0.4
F18: =IF(ISBLANK(E18),D18,E18) -> 0
F19: =IF(ISBLANK(E19),D19,E19) -> 0
F20: =IF(ISBLANK(E20),D20,E20) -> 0
A21: Raw Food Waste Characteristics | F21: =IF(ISBLANK(E21),D21,E21) -> 0
A22: fw_tss | B22: total suspended solids in mixed food waste | C22: g TS / g FW | D22: 0.4052 | F22: =IF(ISBLANK(E22),D22,E22) -> 0.4052
A23: fw_vss | B23: total volatile suspended solids in mixed food waste | C23: g VS / g FW | D23: 0.3996 | F23: =IF(ISBLANK(E23),D23,E23) -> 0.3996
A24: fw_tcod | B24: total chemical oxygen demand in mixed food waste | C24: mg/L | D24: 1500 | F24: =IF(ISBLANK(E24),D24,E24) -> 1500
A25: fw_scod | B25: soluble chemical oxygen demand in mixed food waste | C25: mg/L | D25: 670 | F25: =IF(ISBLANK(E25),D25,E25) -> 670
A26: fw_pcod | B26: particulate chemical oxygen demand in mixed food waste | C26: mg/L | D26: 870 | F26: =IF(ISBLANK(E26),D26,E26) -> 870
A27: fw_tbod | B27: total biological oxygen demand in mixed food waste | C27: mg/L | D27: 580 | F27: =IF(ISBLANK(E27),D27,E27) -> 580
A28: fw_sbod | B28: soluble biological oxygen demand in mixed food waste | C28: mg/L | D28: 190 | F28: =IF(ISBLANK(E28),D28,E28) -> 190
A29: fw_pbod | B29: particulate biological oxygen demand in mixed food waste | C29: mg/L | D29: 380 | F29: =IF(ISBLANK(E29),D29,E29) -> 380
A30: fw_tn | B30: total nitrogen in mixed food waste | C30: g/g DM | D30: 0.025 | F30: =IF(ISBLANK(E30),D30,E30) -> 0.025
A31: fw_son | B31: soluble organic nitrogen in mixed food waste | C31: g/g TN | D31: 0.29 | F31: =IF(ISBLANK(E31),D31,E31) -> 0.29
A32: fw_pn | B32: particulate nitrogen in mixed food waste | C32: g/g TN | D32: 0.69 | F32: =IF(ISBLANK(E32),D32,E32) -> 0.69
A33: fw_nh3_n | B33: amount of nitrogen present as ammonia in mixed food waste | C33: g/g TN | D33: 0.02 | F33: =IF(ISBLANK(E33),D33,E33) -> 0.02
... A39: fw_C | B39: the percentage of carbon in food waste (m:m) | C39: %/100 | D39: 0.5 | F39: =IF(ISBLANK(E39),D39,E39) -> 0.5
F40: =IF(ISBLANK(E40),D40,E40) -> 0
F41: =IF(ISBLANK(E41),D41,E41) -> 0
A42: Digested Cattle Manure Characteristics | F42: =IF(ISBLANK(E42),D42,E42) -> 0
A43: cow_tss | B43: total suspended solids in manure | C43: g TS / g M | D43: 0.229 | F43: =IF(ISBLANK(E43),D43,E43) -> 0.229
A44: cow_vss | B44: volatile suspended solids in manure | C44: g VS / g M | D44: 0.1793 | F44: =IF(ISBLANK(E44),D44,E44) -> 0.1793
A45: cow_pH | B45: aqueous pH of cattle manure | D45: 7.4 | F45: =IF(ISBLANK(E45),D45,E45) -> 7.4
A46: cow_ash | B46: ash content of cattle manure | C46: mg/g DM | D46: 19.3 | F46: =IF(ISBLANK(E46),D46,E46) -> 19.3
A47: cow_oc | B47: organic carbon content of ash free cattle manure | C47: mg/g DM | D47: 500.4 | F47: =IF(ISBLANK(E47),D47,E47) -> 500.4
A48: cow_on | B48: organic nitrogen content of ash free cattle manure | C48: mg/g DM | D48: 25.2 | F48: =IF(ISBLANK(E48),D48,E48) -> 25.2
A49: cow_wsc | B49: water soluble carbon content of ash free cattle manure | C49: mg/g DM | D49: 3.7 | F49: =IF(ISBLANK(E49),D49,E49) -> 3.7
A50: cow_wsn | B50: water soluble nitrogen content of ash free cattle manure | C50: mg/g DM | D50: 27.3 | F50: =IF(ISBLANK(E50),D50,E50) -> 27.3
A51: cow_p | B51: phosphorus content of cattle manure | C51: mg/g DM | D51: 9 | F51: =IF(ISBLANK(E51),D51,E51) -> 9
A52: cow_k | B52: pottassium content of cattle manure | C52: mg/g DM | D52: 7.3 | F52: =IF(ISBLANK(E52),D52,E52) -> 7.3
A53: cow_ca | B53: calcium content of cattle manure | C53: mg/g DM | D53: 19.6 | F53: =IF(ISBLANK(E53),D53,E53) -> 19.6
A54: cow_mg | B54: magnesium content of cattle manure | C54: mg/g DM | D54: 6 | F54: =IF(ISBLANK(E54),D54,E54) -> 6
A55: cow_s | B55: sulfur content of cattle manure | C55: mg/g DM | D55: 3.6 | F55: =IF(ISBLANK(E55),D55,E55) -> 3.6
A56: cow_cod | B56: chemical oxygen demand in cattle manure | C56: mg COD/L | D56: 60000 | F56: =IF(ISBLANK(E56),D56,E56) -> 60000
F57: =IF(ISBLANK(E57),D57,E57) -> 0
F58: =IF(ISBLANK(E58),D58,E58) -> 0
A59: Digested Pig Manure Characteristics | F59: =IF(ISBLANK(E59),D59,E59) -> 0
A60: pig_tss | B60: total suspended solids in manure | C60: g TS / g M | D60: 0.229 | F60: =IF(ISBLANK(E60),D60,E60) -> 0.229
A61: pig_vss | B61: volatile suspended solids in manure | C61: g VS / g M | D61: 0.1793 | F61: =IF(ISBLANK(E61),D61,E61) -> 0.1793
A62: pig_pH | B62: aqueous pH of pig manure | D62: 6.5 | F62: =IF(ISBLANK(E62),D62,E62) -> 6.5
A63: pig_ash | B63: ash content of pig manure | C63: mg/g DM | D63: 19.4 | F63: =IF(ISBLANK(E63),D63,E63) -> 19.4
A64: pig_oc | B64: organic carbon content of ash free pig manure | C64: mg/g DM | D64: 550.8 | F64: =IF(ISBLANK(E64),D64,E64) -> 550.8
A65: pig_on | B65: organic nitrogen content of ash free pig manure | C65: mg/g DM | D65: 25.9 | F65: =IF(ISBLANK(E65),D65,E65) -> 25.9
A66: pig_wsc | B66: water soluble carbon content of ash free pig manure | C66: mg/g DM | D66: 36.7 | F66: =IF(ISBLANK(E66),D66,E66) -> 36.7
A67: pig_wsn | B67: water soluble nitrogen content of ash free pig manure | C67: mg/g DM | D67: 26.3 | F67: =IF(ISBLANK(E67),D67,E67) -> 26.3
A68: pig_p | B68: phosphorus content of pig manure | C68: mg/g DM | D68: 29 | F68: =IF(ISBLANK(E68),D68,E68) -> 29
A69: pig_k | B69: pottassium content of pig manure | C69: mg/g DM | D69: 11.4 | F69: =IF(ISBLANK(E69),D69,E69) -> 11.4
A70: pig_ca | B70: calcium content of pig manure | C70: mg/g DM | D70: 26.4 | F70: =IF(ISBLANK(E70),D70,E70) -> 26.4
A71: pig_mg | B71: magnesium content of pig manure | C71: mg/g DM | D71: 9.8 | F71: =IF(ISBLANK(E71),D71,E71) -> 9.8
A72: pig_s | B72: sulfur content of pig manure | C72: mg/g DM | D72: 4.3 | F72: =IF(ISBLANK(E72),D72,E72) -> 4.3
A73: pig_cod | B73: chemical oxygen demand in pig manure | C73: mg COD/L | D73: 50000 | F73: =IF(ISBLANK(E73),D73,E73) -> 50000
F74: =IF(ISBLANK(E74),D74,E74) -> 0
F75: =IF(ISBLANK(E75),D75,E75) -> 0
A76: Ocean Water Characteristics | F76: =IF(ISBLANK(E76),D76,E76) -> 0
A77: oc_na | B77: sodium ion concentration in the ocean (+1) | C77: ppm | D77: 10500 | F77: =IF(ISBLANK(E77),D77,E77) -> 10500
A78: oc_k | B78: potassium ion concentration in the ocean (+1) | C78: ppm | D78: 380 | F78: =IF(ISBLANK(E78),D78,E78) -> 380
A79: oc_mg | B79: magnesium ion concentration in the ocean (+2) | C79: ppm | D79: 1250 | F79: =IF(ISBLANK(E79),D79,E79) -> 1250
A80: oc_ca | B80: calcium ion concentration in the ocean (+2) | C80: ppm | D80: 400 | F80: =IF(ISBLANK(E80),D80,E80) -> 400
A81: oc_cl | B81: chloride ion concentration in the ocean (-1) | C81: ppm | D81: 16535.44 | F81: =IF(ISBLANK(E81),D81,E81) -> 16535.44
A82: oc_so4 | B82: sulfate ion concentration in the ocean (-2) | C82: ppm | D82: 5899.07 | F82: =IF(ISBLANK(E82),D82,E82) -> 5899.07
F83: =IF(ISBLANK(E83),D83,E83) -> 0
F84: =IF(ISBLANK(E84),D84,E84) -> 0
A85: Ocean Water Processing | F85: =IF(ISBLANK(E85),D85,E85) -> 0
A86: ed_hrt | B86: electrodialysis operating time | C86: hr | D86: 6 | F86: =IF(ISBLANK(E86),D86,E86) -> 6
A87: ed_temp | B87: electrodialysis operating temperature | C87: K | D87: 298.15 | F87: =IF(ISBLANK(E87),D87,E87) -> 298.15
A88: ed_flow | B88: electrodialysis flow rate within the compartments | C88: L/hr | D88: 18 | F88: =IF(ISBLANK(E88),D88,E88) -> 18
A89: vconst | B89: is the volatage applied constant? 1=yes 0=no | D89: 1 | F89: =IF(ISBLANK(E89),D89,E89) -> 1
A90: vap | B90: constant applied voltage per membrane pair, if yes | C90: V/mp | D90: 2 | F90: =IF(ISBLANK(E90),D90,E90) -> 2
A91: imax | B91: maximum applied current per membrane pair, if yes | C91: A/mp | D91: 0.6 | F91: =IF(ISBLANK(E91),D91,E91) -> 0.6
A92: imin | B92: minimum applied current per membrane pair, if yes | C92: A/mp | D92: 0.3 | F92: =IF(ISBLANK(E92),D92,E92) -> 0.3
A93: iap | B93: constant applied current per membrane pair, if no | C93: A/mp | D93: 0.3 | F93: =IF(ISBLANK(E93),D93,E93) -> 0.3
A94: vmax | B94: maximum applied voltage per membrane pair, if no | C94: V/mp | D94: 2 | F94: =IF(ISBLANK(E94),D94,E94) -> 2
A95: vmin | B95: minimum applied volate per membrane pair, if no | C95: V/mp | D95: 1 | F95: =IF(ISBLANK(E95),D95,E95) -> 1
A96: celec | B96: electrolyte concentration | C96: g/L | D96: 10 | F96: =IF(ISBLANK(E96),D96,E96) -> 10
A97: ldtc | B97: diluate to concentrate volume ratio | C97: L/L | D97: 5 | F97: =IF(ISBLANK(E97),D97,E97) -> 5
A98: ldte | B98: dilute to electrolyte volume ratio | C98: L/L | D98: 5 | F98: =IF(ISBLANK(E98),D98,E98) -> 5
A99: msa | B99: membrane surface area | C99: m2 | D99: 1 | F99: =IF(ISBLANK(E99),D99,E99) -> 1
A100: mth | B100: membrane thickness | C100: m | D100: 0.01 | F100: =IF(ISBLANK(E100),D100,E100) -> 0.01
A101: mstack | B101: scenario 1, 2, 3, or 4 for membrane stack design | C101: scenario | D101: 1 | F101: =IF(ISBLANK(E101),D101,E101) -> 1
... A115: ed_wvol | B115: maximum working volume of electrodialysis tanks | C115: % | D115: 80 | F115: =IF(ISBLANK(E115),D115,E115) -> 80
F116: =IF(ISBLANK(E116),D116,E116) -> 0
F117: =IF(ISBLANK(E117),D117,E117) -> 0
A118: Cheese Whey Processing | F118: =IF(ISBLANK(E118),D118,E118) -> 0
...

Sheet Units
A1: Unit Conversions
A2: Volume | G2: kg COD/m3 sludge to g/L liquid digestate
A3: 1 | B3: gal | C3: 3.785 | D3: L | G3: kg COD | H3: 1000 g | I3: mol | J3: g | K3: m3 | L3: L sludge
A4: 1 | B4: gal | C4: 3.9 | D4: kg - sludge | G4: m3 | H4: 1kg | I4: g COD | J4: mol | K4: 1050 L sludge | L4: L digestate
A5: 1 | B5: gal | C5: 3.785 | D5: kg - water
A6: 1 | B6: yd3 | C6: 0.76455 | D6: m3 | G6: mol/L to kg/m3
A7: 1 | B7: ft3 | C7: 0.028168 | D7: m3 | G7: mol | H7: g | I7: 1000 L | J7: kg
A8: 1 | B8: oz | C8: 0.0295735 | D8: L | G8: L | H8: mol | I8: m3 | J8: 1000 g
A9: 1 | B9: m3 | C9: 6.29 | D9: barrels
A10: 1 | B10: gal | C10: 3.03 | D10: kg - jet fuel | G10: sludge to ld
G11: g | H11: L sludge | I11: hr
A12: Density at STP | G12: L sludge | H12: hr | I12: L digest
A13: 1 | B13: L water | C13: 1 | D13: kg
A14: 1 | B14: m3 water | C14: 1000 | D14: L
A15: 1 | B15: m3 water | C15: 1000 | D15: kg
A16: 1 | B16: L sludge | C16: 1.5 | D16: kg
A17: 1 | B17: m3 sludge | C17: 1050 | D17: L
A18: 1 | B18: m3 sludge | C18: 1050 | D18: kg
A19: 1 | B19: L acetone | C19: 749.4 | D19: g
A20: 1 | B20: L butanol | C20: 810 | D20: g
A21: 1 | B21: L ethanol | C21: 0.789 | D21: kg
A22: 1 | B22: m3 ethanol | C22: 789 | D22: kg
A23: 1 | B23: L acetic acid | C23: 1049 | D23: g
A24: 1 | B24: L butyric acid | C24: 964 | D24: g
A25: 1 | B25: mL Amb-37 | C25: 1.2 | D25: g
A26: =A25/(C81*C14) -> 1 | B26: m3 Amb-37 | C26: =C25*C84 -> 1200 | D26: kg
A27: 1 | B27: cm3 Pd/C | C27: 3.71 | D27: g
A28: =A27/C82 -> 100 | B28: m3 Pd/C | C28: =C27*C84 -> 3710 | D28: kg
A29: 1 | B29: m3 CH4 gas | C29: 0.657 | D29: kg
A30: 1 | B30: m3 CO2 | C30: 1.98 | D30: kg
A31: 1 | B31: m3 H2 | C31: 0.09 | D31: kg
A32: 1 | B32: m3 N2 gas | C32: 1.25 | D32: kg
A33: 1 | B33: m3 H2S | C33: 1.36 | D33: kg
A34: 1 | B34: m3 Biosolids | C34: =1.78*(C85/C84) -> 1780 | D34: kg
A35: 1 | B35: m3 Glucose | C35: 1560 | D35: kg
A36: Cheese Whey | B36: 1 m3 | C36: 400 | D36: kg
A37: 1 | B37: L Ideal Gas STP | C37: =1/22.414 -> 0.044614973 | D37: mol
A39: Length
A40: 1 | B40: acre | C40: 4047 | D40: m2
A41: 1 | B41: ft | C41: 12 | D41: in
A42: 1 | B42: ft | C42: 0.3048 | D42: m
A44: Mass
A45: 1 | B45: ton | C45: 907.185 | D45: kg
A46: 1 | B46: lb | C46: 0.4535923 | D46: kg
A47: 1 | B47: g | C47: 1000 | D47: kg
A48: 641 | B48: kg graphite | C48: 1 | D48: m3
A51: Time
A52: 1 | B52: year | C52: 365 | D52: days
A53: 1 | B53: year | C53: 12 | D53: months
A54: 1 | B54: month | C54: 30 | D54: days
A55: 1 | B55: day | C55: 24 | D55: hr
A56: 1 | B56: hr | C56: 60 | D56: min
A57: 1 | B57: min | C57: 60 | D57: sec
A59: Pressure
A60: 1 | B60: psi | C60: 0.0689476 | D60: bar
A62: Energy
A63: 1 | B63: kWp | C63: 1000 | D63: kWh/yr
A64: 1 | B64: BTU | C64: 1.05506 | D64: kJ
A65: 1 | B65: hp | C65: 745.7 | D65: W
A66: 1 | B66: kJ | C66: 0.239006 | D66: kcal
A67: Water Specific Heat | B67: Cp | C67: 4.186 | D67: kJ/kg*K
A68: Ideal Gas Constant | B68: R | C68: 0.0821 | D68: L-atm/mol-k
B69: R | C69: 0.008314 | D69: kJ/mo-L-K
A70: 1 | B70: kWh | C70: =3600000 -> 3600000 | D70: J
A71: Gravitational acceleration | B71: m/s2 | C71: 9.81
A74: Temperature
A75: Celcius to Kelvin | B75: 273.15
A78: Math
C79: 3.141592 | D79: pi
A80: 1 | B80: base | C80: 1e-06 | D80: micro(u)
A81: 1 | B81: base | C81: 0.001 | D81: milli(m)
A82: 1 | B82: base | C82: 0.01 | D82: centi(c)
A83: 1 | B83: base | C83: 0.01 | D83: deci(d)
A84: 1 | B84: base | C84: 1000 | D84: kilo(k)
A85: 1 | B85: base | C85: 1000000 | D85: mega(M)
A86: 1 | B86: base | C86: 1000000000 | D86: giga(G)
A88: Money
A89: 1 | B89: USD | C89: =Inputs!F885 -> 0.112 | D89: kWh
A90: 1 | B90: 2018 euro | C90: 1.2 | D90: 2018 $
A92: Molar Mass
A93: Lactate | B93: g/mol | C93: 89.07
A94: Acetate | B94: g/mol | C94: 59.04
A95: Propionate | B95: g/mol | C95: 73.07
A96: Butyrate | B96: g/mol | C96: 87.1
A97: Isobutyrate | B97: g/mol | C97: 87.1
A98: Valerate | B98: g/mol | C98: 101.12
A99: Isovalerate | B99: g/mol | C99: 101.12
A100: Hexanoate | B100: g/mol | C100: 115.15
A101: Heptanoate | B101: g/mol | C101: 129.17
A102: Lactic Acid | B102: g/mol | C102: 90.08
A103: Acetic Acid | B103: g/mol | C103: 60.05
A104: Propionic Acid | B104: g/mol | C104: 74.08
... A122: Ammonium NH4+ | B122: g/mol | C122: 18.04
A123: NH4Cl | B123: g/mol | C123: =C122+C140 -> 53.49
A124: H3PO4 | B124: g/mol | C124: 97.994
A125: H2PO4 | B125: g/mol | C125: 96.99
A126: HPO4 | B126: g/mol | C126: 95.98
A127: PO4 | B127: g/mol | C127: 94.97
A128: H2SO4 | B128: g/mol | C128: 98.079
A129: HSO4 | B129: g/mol | C129: 97.064
...

Sheet ExpBase
A1: SEA WATER BIPOLAR MEMBRANE ELECTRODIALYSIS
A2: Operating Conditions
A3: Parameter | B3: Unit | C3: Value
A4: electrodialysis operating time | B4: hr | C4: 6
A5: electrodialysis operating temperature | B5: K | C5: 298.15
A6: electrodialysis flow rate within the compartments | B6: L/hr | C6: 18
A7: constant applied current per membrane pair | B7: A/mp | C7: 0.3
A8: maximum applied voltage per membrane pair | B8: V/mp | C8: 2
A9: minimum applied volate per membrane pair | B9: V/mp | C9: 1
A10: electrolyte concentration | B10: g/L | C10: 10
A11: diluate to concentrate volume ratio | B11: L/L | C11: 5
A12: dilute to electrolyte volume ratio | B12: L/L | C12: 5
A13: membrane surface area | B13: m2 | C13: 1
A14: membrane thickness | B14: m | C14: 0.01
A15: distance between electrodes | B15: m | C15: 4.5
... A27: ratio of tank height to diameter | B27: m:m | C27: 1.2
A30: Species by Compartment
A31: Parameter | B31: Unit | C31: Value
A32: LD_sodium | B32: %/100 | C32: 0.12
A33: LD_chlorine | B33: %/100 | C33: 0.08
A34: LD_sulfur | B34: %/100 | C34: 0.11
A35: LD_magnesium | B35: %/100 | C35: 0.06
A36: LD_calcium | B36: %/100 | C36: 0.04
A37: LD_potassium | B37: %/100 | C37: 0.02
A38: LD_pH | C38: =C4 -> 6
A39: A1_sodium | B39: %/100 | C39: 0.08
A40: A1_chlorine | B40: %/100 | C40: 0.85
A41: A1_sulfur | B41: %/100 | C41: =0.70005+0.2 -> 0.90005
A42: A1_magnesium | B42: %/100 | C42: 0.05
A43: A1_calcium | B43: %/100 | C43: 0.02
A44: A1_potassium | B44: %/100 | C44: 0.01
A45: A1_pH | C45: 1
A46: B1_sodium | B46: %/100 | C46: 0.76
A47: B1_chlorine | B47: %/100 | C47: 0.08
A48: B1_sulfur | B48: %/100 | C48: 0.03
A49: B1_magnesium | B49: %/100 | C49: 0.87
A50: B1_calcium | B50: %/100 | C50: 0.93
A51: B1_potassium | B51: %/100 | C51: 0.95
A52: B1_pH | C52: 13
A53: EL_sodium | B53: %/100 | C53: =1-SUM(C32,C39,C46) -> 0.04
A54: EL_chlorine | B54: %/100 | C54: 0.0911392
A55: EL_sulfur | B55: %/100 | C55: 0.108535
A56: EL_magnesium | B56: %/100 | C56: =1-SUM(C35,C42,C49) -> 0.02
A57: EL_calcium | B57: %/100 | C57: =1-SUM(C36,C43,C50) -> 0.01
A58: EL_potassium | B58: %/100 | C58: =1-SUM(C37,C44,C51) -> 0.02
A59: EL_pH | C59: 6.5
A62: Initial Values
A63: Parameter | B63: Unit | C63: Value
A64: C_Na | B64: g/L | C64: =Inputs!F77/1000 -> 10.5
A65: C_Cl | B65: g/L | C65: =Inputs!F81/1000 -> 16.53544
A66: C_SO4 | B66: g/L | C66: =Inputs!F82/1000 -> 5.89907
A67: C_Mg | B67: g/L | C67: =Inputs!F79/1000 -> 1.25
A68: C_Ca | B68: g/L | C68: =Inputs!F80/1000 -> 0.4
A69: C_K | B69: g/L | C69: =Inputs!F78/1000 -> 0.38
A70: C_H | B70: mol/L | C70: =10^(-C45) -> 0.1
A71: C_OH | B71: mol/L | C71: =10^(-(14-C52)) -> 0.1
A74: Electrodialysis Effluent
B75: Ocean Water | D75: Base 1 | E75: Acid 1 | F75: Electrolyte | G75: Ocean Water | I75: Base 1 | J75: Acid 1 | K75: Electrolyte
A76: Parameter | B76: Unit | C76: Value | D76: Value | E76: Value | F76: Value | G76: Unit | H76: Value | I76: Value | J76: Value | K76: Value
A77: C_Na | B77: g/L | C77: =C64*C32 -> 1.26 | D77: =(C64*C46)*C$11 -> 39.9 | E77: =(C64*C39)*C$11 -> 4.2 | F77: =(C64*C53)*C$12 -> 2.1 | G77: mol/L | H77: =C77/Units!$C232 -> 0.054806988 | I77: =D77/Units!$C232 -> 1.7355546 | J77: =E77/Units!$C232 -> 0.18268996 | K77: =F77/Units!$C232 -> 0.09134498
A78: C_Cl | B78: g/L | C78: =C65*C33 -> 1.3228352 | D78: =(C65*C47)*C$11 -> 6.614176 | E78: =(C65*C40)*C$11 -> 70.27562 | F78: =(C65*C54)*C$12 -> 7.5351339 | G78: mol/L | H78: =C78/Units!$C233 -> 0.03731552 | I78: =D78/Units!$C233 -> 0.1865776 | J78: =E78/Units!$C233 -> 1.982387 | K78: =F78/Units!$C233 -> 0.21255667
A79: C_SO4 | B79: g/L | C79: =C66*C34 -> 0.6488977 | D79: =(C66*C48)*C$11 -> 0.8848605 | E79: =(C66*C41)*C$11 -> 26.54729 | F79: =(C66*C55)*C$12 -> 3.2012778 | G79: mol/L | H79: =C79/Units!$C234 -> 0.0067551291 | I79: =D79/Units!$C234 -> 0.0092115397 | J79: =E79/Units!$C234 -> 0.27636154 | K79: =F79/Units!$C234 -> 0.033325815
A80: C_Mg | B80: g/L | C80: =C67*C35 -> 0.075 | D80: =(C67*C49)*C$11 -> 5.4375 | E80: =(C67*C42)*C$11 -> 0.3125 | F80: =(C67*C56)*C$12 -> 0.125 | G80: mol/L | H80: =C80/Units!$C235 -> 0.0030857848 | I80: =D80/Units!$C235 -> 0.2237194 | J80: =E80/Units!$C235 -> 0.012857437 | K80: =F80/Units!$C235 -> 0.0051429747
A81: C_Ca | B81: g/L | C81: =C68*C36 -> 0.016 | D81: =(C68*C50)*C$11 -> 1.86 | E81: =(C68*C43)*C$11 -> 0.04 | F81: =(C68*C57)*C$12 -> 0.02 | G81: mol/L | H81: =C81/Units!$C236 -> 0.00039922152 | I81: =D81/Units!$C236 -> 0.046409501 | J81: =E81/Units!$C236 -> 0.0009980538 | K81: =F81/Units!$C236 -> 0.0004990269
A82: C_K | B82: g/L | C82: =C69*C37 -> 0.0076 | D82: =(C69*C51)*C$11 -> 1.805 | E82: =(C69*C44)*C$11 -> 0.019 | F82: =(C69*C58)*C$12 -> 0.038 | G82: mol/L | H82: =C82/Units!$C237 -> 0.00019438185 | I82: =D82/Units!$C237 -> 0.04616569 | J82: =E82/Units!$C237 -> 0.00048595463 | K82: =F82/Units!$C237 -> 0.00097190926
A87: Crystallizer
D88: Initial | F88: MgSO4 | H88: CaSO4 | I88: KCl | J88: NaCl | M88: Ocean Water Figure
A89: Parameter | B89: Unit | C89: Value | D89: Unit | E89: Value | F89: Unit | G89: Value | H89: Value | I89: Value | J89: Value | M89: Species | N89: Acid | O89: Base | P89: Electrolyte | Q89: Water
A90: C_Na | B90: g/L | C90: =C64 -> 10.5 | D90: mol/L | E90: =C90/Units!C232 -> 0.4567249 | F90: mol/L | G90: =E90 -> 0.4567249 | H90: =G90 -> 0.4567249 | I90: =H90 -> 0.4567249 | J90: =I90-I91 -> -1.0714245e-08 | L90: (g/L) | M90: Na+ | N90: =E77 -> 4.2 | O90: =D77 -> 39.9 | Q90: =C77 -> 1.26
A91: C_Cl | B91: g/L | C91: =C65 -> 16.53544 | D91: mol/L | E91: =C91/Units!C233 -> 0.46644401 | F91: mol/L | G91: =E91 -> 0.46644401 | H91: =G91-G93 -> 0.46644401 | I91: =H91-H95 -> 0.45672491 | J91: =I91-I91 -> 0 | L91: (g/L) | M91: Cl- | N91: =E78 -> 70.27562 | O91: =D78 -> 6.614176 | Q91: =C78 -> 1.3228352
A92: C_SO4 | B92: g/L | C92: =C66 -> 5.89907 | D92: mol/L | E92: =C92/Units!C234 -> 0.061410264 | F92: mol/L | G92: =E92-E93 -> 0.0099805175 | H92: =G92-G92 -> 0 | I92: =H92 -> 0 | L92: (g/L) | M92: SO4-- | N92: =E79 -> 26.54729 | O92: =D79 -> 0.8848605 | Q92: =C79 -> 0.6488977
A93: C_Mg | B93: g/L | C93: =C67 -> 1.25 | D93: mol/L | E93: =C93/Units!C235 -> 0.051429747 | F93: mol/L | G93: =E93-E93 -> 0 | H93: =G93-G93 -> 0 | I93: =H93 -> 0 | L93: (g/L) | M93: Mg++ | N93: =E80 -> 0.3125 | O93: =D80 -> 5.4375 | Q93: =C80 -> 0.075
A94: C_Ca | B94: g/L | C94: =C68 -> 0.4 | D94: mol/L | E94: =C94/Units!C236 -> 0.009980538 | F94: mol/L | G94: =E94 -> 0.009980538 | H94: =G94-G92 -> 2.0498568e-08 | I94: =H94-H94 -> 0 | L94: (g/L) | M94: Ca++ | N94: =E81 -> 0.04 | O94: =D81 -> 1.86 | Q94: =C81 -> 0.016
A95: C_K | B95: g/L | C95: =C69 -> 0.38 | D95: mol/L | E95: =C95/Units!C237 -> 0.0097190926 | F95: mol/L | G95: =E95 -> 0.0097190926 | H95: =G95 -> 0.0097190926 | I95: =H95-H95 -> 0 | L95: (g/L) | M95: K+ | N95: =E82 -> 0.019 | O95: =D82 -> 1.805
A96: q_Na | B96: e | C96: 1 | L96: (g/L) | M96: H+ | N96: =(J78+(2*J79))*Units!C142 -> 2.555391 | O96: =D83 -> 0
A97: q_Cl | B97: e | C97: -1 | F97: mol/L | G97: g/L | H97: ppm | L97: (g/L) | M97: OH- | O97: =SUM(I77,I80,I81,I82)*Units!C143 -> 34.897852
A98: q_SO4 | B98: e | C98: -2 | E98: so4 | F98: =E93+E94 -> 0.061410285 | G98: =F98*Units!C234 -> 5.899072 | H98: =G98*1000 -> 5899.072 | L98: (g/L) | M98: MgSO4*7H2O | P98: =E103 -> 3.0955565
A99: q_Mg | B99: e | C99: 2 | E99: cl | F99: =E90+E95 -> 0.46644399 | G99: =F99*Units!C233 -> 16.53544 | H99: =G99*1000 -> 16535.44 | L99: (g/L) | M99: CaSO4*10H2O | P99: =E104 -> 0.63875443
A100: q_Ca | B100: e | C100: 2 | L100: (g/L) | M100: KCl | P100: =E105 -> 0.72455836
A101: q_K | B101: e | C101: 1 | L101: (g/L) | M101: NaCl | P101: =E106 -> 26.691004
A102: Crystals Formed | L102: (m3/hr) | M102: Flow Rate | N102: =C552/Units!C14 -> 6.7911897 | O102: =N102 -> 6.7911897 | P102: =B115/1000 -> 0 | Q102: =O102*5 -> 33.955948
A103: MgSO4*7H2O | B103: mol/L | C103: =E93*0.5 -> 0.025714873 | D103: g/L | E103: =C103*Units!C238 -> 3.0955565
A104: CaSO4*2H2O | B104: mol/L | C104: =G94 -> 0.009980538 | D104: g/L | E104: =C104*Units!C239 -> 0.63875443
A105: KCl | B105: mol/L | C105: =H95 -> 0.0097190926 | D105: g/L | E105: =C105*Units!C240 -> 0.72455836
A106: NaCl | B106: mol/L | C106: =I91 -> 0.45672491 | D106: g/L | E106: =C106*Units!C241 -> 26.691004
A108: Amount of Electrolyte Required
A109: Ocean Water Electrodialysis | B109: =N102*C10 -> 67.911897 | C109: kg/hr
A110: Path A Electrodialysis | B110: =A917 -> 96.187769 | C110: kg/hr
A111: Path B Electrodialysis | B111: =A1460 -> 192.37554 | C111: kg/hr
A112: Total | B112: =SUM(B109:B111) -> 356.4752 | C112: kg/hr
A113: Total Sodium Sulfate Decahydrate | B113: =B635 -> 386.11611 | C113: kg/hr
A114: Ocean Water Crystal Flow | B114: =IF((B112-B113)>0,(B112-B113),0) -> 0 | C114: kg/hr
A115: Volume of Water Flow | B115: =B114/(E106/1000) -> 0 | C115: L/hr
A120: Chesse Whey Fermentation
A122: Enzymatic Hydrolysis
A123: Parameter | B123: Unit | C123: Value | D123: Unit | E123: Value | F123: Unit | G123: Value
A124: Substrate (Cheese Whey Powder) Concentration | B124: % w/v | C124: 25 | D124: g/L | E124: =(C124/100)*Units!C84 -> 250 | F124: m3 CW / L H2O | G124: =E124/(Units!C36*Units!C47) -> 0.000625
A125: Lactose Concentration in Substrate | B125: % w/v | C125: 70 | D125: g/L | E125: =E124*(C125/100) -> 175 | F125: m3 CW/hr | G125: =G124*C143 -> 7.5446155
A126: Beta-galactosidase (Lactase) | B126: U/g CW | C126: 15 | D126: U/L | E126: =C126*E124 -> 3750 | F126: kg CW/hr | G126: =G125*Units!C36 -> 3017.8462
A127: Yield (Glucose / Lactose) | B127: g:g | C127: 0.47
...

Sheet Carbon
A1: CARBON FLOW RATES
A3: Chesse Whey Fermentation
A4: Parameter | B4: Unit | C4: Value | D4: Unit | E4: Carbon | F4: Unit | G4: Carbon Flow Rate | H4: Unit | I4: Total Carbon Flow | J4: TYPE
A5: Fermentation
A6: IN
A7: Lactose in Substrate | B7: g/hr | C7: =ExpBase!E125*ExpBase!C143 -> 2112492.3 | D7: g/hr | E7: =C7*Units!D493 -> 889505.54 | F7: MT/hr | G7: =E7/(Units!C$85) -> 0.88950554 | H7: =F7 -> MT/hr | I7: =G7 -> 0.88950554 | J7: CHEESE WHEY
A8: OUT
A9: Glucose Flow Rate | B9: g/hr | C9: =ExpBase!C139*ExpBase!C143 -> 89358.426 | D9: g/hr | E9: =C9*Units!D491 -> 35745.156 | F9: MT/hr | G9: =E9/(Units!C$85) -> 0.035745156
A10: Galactose Flow Rate | B10: g/hr | C10: =ExpBase!C140*ExpBase!C143 -> 204066.76 | D10: g/hr | E10: =C10*Units!D492 -> 81630.782 | F10: MT/hr | G10: =E10/(Units!C$85) -> 0.081630782
A11: Lactose Flow Rate | B11: g/hr | C11: =ExpBase!C141*ExpBase!C143 -> 147874.46 | D11: g/hr | E11: =C11*Units!D493 -> 62265.388 | F11: MT/hr | G11: =E11/(Units!C$85) -> 0.062265388
A12: Lactic Acid Flow Rate | B12: g/hr | C12: =ExpBase!C138*ExpBase!C143 -> 1671192.7 | D12: g/hr | E12: =C12*Units!D494 -> 668495.63 | F12: MT/hr | G12: =E12/(Units!C$85) -> 0.66849563 | H12: =F12 -> MT/hr | I12: =SUM(G9:G12) -> 0.84813696 | J12: FERMENTATION BROTH
A13: WASTE | H13: MT/hr | I13: =I7-I12 -> 0.041368585 | J13: WASTE WHEY
A14: Separation
A15: IN | H15: =H12 -> MT/hr | I15: =I12 -> 0.84813696 | J15: FERMENTATION BROTH
A16: OUT
A17: Lactic Acid Flow Rate | B17: g/hr | C17: =C12*ExpBase!C174 -> 1654480.8 | D17: g/hr | E17: =C17*Units!D494 -> 661810.67 | F17: MT/hr | G17: =E17/Units!C$85 -> 0.66181067
A18: Glucose Flow Rate | B18: g/hr | C18: =C9*ExpBase!C174 -> 88464.842 | D18: g/hr | E18: =C18*Units!D491 -> 35387.705 | F18: MT/hr | G18: =E18/Units!C$85 -> 0.035387705
A19: Galactose Flow Rate | B19: g/hr | C19: =C10*ExpBase!C174 -> 202026.09 | D19: g/hr | E19: =C19*Units!D492 -> 80814.474 | F19: MT/hr | G19: =E19/Units!C$85 -> 0.080814474
A20: Lactose Flow Rate | B20: g/hr | C20: =C11*ExpBase!C174 -> 146395.72 | D20: g/hr | E20: =C20*Units!D493 -> 61642.734 | F20: MT/hr | G20: =E20/Units!C$85 -> 0.061642734 | H20: MT/hr | I20: =SUM(G17:G20) -> 0.83965559 | J20: CONCENTRATED LACTATE
A21: WASTE | H21: MT/hr | I21: =I15-I20 -> 0.0084813696 | J21: WASTE WATER
A24: Anaerobic Digestion
A25: Parameter | B25: Unit | C25: Value | D25: Unit | E25: Carbon | F25: Unit | G25: Carbon Flow Rate | H25: Unit | I25: Total Carbon Flow | J25: TYPE
A26: Manure Digestion
A27: IN
A28: Manure | B28: kg/hr | C28: =Inputs!F13*Inputs!F15 -> 22500 | D28: mg/hr | E28: =C28*ExpBase!C310*Inputs!D47 -> 1.476673e+09 | F28: MT/hr | G28: =E28/Units!C$86 -> 1.476673 | H28: MT/hr | I28: =SUM(G28) -> 1.476673 | J28: FEED
A29: Biosolid Recycle | D29: mg/hr | E29: =E28*0.2 -> 2.9533459e+08 | F29: MT/hr | G29: =E29/Units!C$86 -> 0.29533459 | H29: MT/hr | I29: =G29 -> 0.29533459 | J29: BIOSOLID RECYCLE
A30: BIOGAS
A31: Methane | B31: L/hr | C31: =ExpBase!G363 -> 11697.475 | D31: g/hr | E31: =C31*Units!D495*0.72 -> 6306.66 | F31: MT/hr | G31: =E31/Units!C85 -> 0.00630666 | H31: MT/hr | I31: =SUM(G31:G32) -> 0.10433521 | J31: BIOGAS
A32: Carbon Dioxide | B32: L/hr | C32: =ExpBase!G364 -> 183260.44 | D32: g/hr | E32: =C32*Units!D496*1.96 -> 98028.553 | F32: MT/hr | G32: =E32/Units!C85 -> 0.098028553 | N32: =I28+I46 -> 2.726673
A33: ACIDS | K33: =I34/SUM(I28:I29) -> 0.052366783 | N33: =0.8783/N32 -> 0.32211417
A34: Lactate Produced | B34: kg/hr | C34: =ExpBase!G251 -> 0.99389647 | D34: kg/hr | E34: =C34*Units!D494 -> 0.39756962 | F34: MT/hr | G34: =E34/1000 -> 0.00039756962 | H34: MT/hr | I34: =SUM(G34:G42) -> 0.092794335 | J34: VFAS | N34: =0.27/N32 -> 0.099021776
A35: Acetate Produced | B35: kg/hr | C35: =ExpBase!G252 -> 61.817073 | D35: kg/hr | E35: =C35*Units!D498 -> 25.151926 | F35: MT/hr | G35: =E35/1000 -> 0.025151926
A36: Propionic Production | B36: kg/hr | C36: =ExpBase!G253 -> 0 | D36: kg/hr | E36: =C36*Units!D499 -> 0 | F36: MT/hr | G36: =E36/1000 -> 0 | K36: 0.05093481
A37: Butyric Production | B37: kg/hr | C37: =ExpBase!G254 -> 63.607112 | D37: kg/hr | E37: =C37*Units!D500 -> 35.08542 | F37: MT/hr | G37: =E37/1000 -> 0.03508542 | K37: 0.058879666
A38: Isobutyric Production | B38: kg/hr | C38: =ExpBase!G255 -> 2.9168895 | D38: kg/hr | E38: =C38*Units!D501 -> 1.6089442 | F38: MT/hr | G38: =E38/1000 -> 0.0016089442
A39: Valerate Production | B39: kg/hr | C39: =ExpBase!G256 -> 37.531416 | D39: kg/hr | E39: =C39*Units!D502 -> 22.289846 | F39: MT/hr | G39: =E39/1000 -> 0.022289846
A40: Isovaleric Production | B40: kg/hr | C40: =ExpBase!G257 -> 0 | D40: kg/hr | E40: =C40*Units!D503 -> 0 | F40: MT/hr | G40: =E40/1000 -> 0
A41: Caproic Production | B41: kg/hr | C41: =ExpBase!G258 -> 13.19917 | D41: kg/hr | E41: =C41*Units!D504 -> 8.2606287 | F41: MT/hr | G41: =E41/1000 -> 0.0082606287
A42: Heptanoate Production | B42: kg/hr | C42: =ExpBase!G259 -> 0 | D42: kg/hr | E42: =C42*Units!D505 -> 0 | F42: MT/hr | G42: =E42/1000 -> 0
A44: Food Waste Digestion
A45: IN
A46: Food Waste | B46: kg/hr | C46: =ExpBase!C243 -> 2500 | D46: kg/hr | E46: =C46*Inputs!D39 -> 1250 | F46: MT/hr | G46: =E46/1000 -> 1.25 | H46: MT/hr | I46: =G46 -> 1.25 | J46: FEED | K46: =I51/I46 -> 0.070024554
A47: BIOGAS
A48: Methane | B48: L/hr | C48: =ExpBase!C363 -> 3354.672 | D48: g/hr | E48: =C48*Units!D495*0.72 -> 1808.6618 | F48: MT/hr | G48: =E48/1000000 -> 0.0018086618 | H48: MT/hr | I48: =SUM(G48:G49) -> 0.029921879 | J48: BIOGAS | K48: =I48/I46 -> 0.023937503
A49: Carbon Dioxide | B49: L/hr | C49: =ExpBase!C364 -> 52556.528 | D49: g/hr | E49: =C49*Units!D496*1.96 -> 28113.217 | F49: MT/hr | G49: =E49/1000000 -> 0.028113217 | H49: MT/hr
A50: ACIDS
A51: Lactate Produced | B51: kg/hr | C51: =ExpBase!C251 -> 0 | D51: kg/hr | E51: =C51*Units!D494 -> 0 | F51: MT/hr | G51: =E51/1000 -> 0 | H51: MT/hr | I51: =SUM(G51:G59) -> 0.087530692 | J51: VFAs
A52: Acetate Produced | B52: kg/hr | C52: =ExpBase!C252 -> 22.410997 | D52: kg/hr | E52: =C52*Units!D498 -> 9.1185124 | F52: MT/hr | G52: =E52/1000 -> 0.0091185124
A53: Propionic Production | B53: kg/hr | C53: =ExpBase!C253 -> 19.026615 | D53: kg/hr | E53: =C53*Units!D499 -> 9.3825921 | F53: MT/hr | G53: =E53/1000 -> 0.0093825921
A54: Butyric Production | B54: kg/hr | C54: =ExpBase!C254 -> 57.798418 | D54: kg/hr | E54: =C54*Units!D500 -> 31.881368 | F54: MT/hr | G54: =E54/1000 -> 0.031881368
A55: Isobutyric Production | B55: kg/hr | C55: =ExpBase!C255 -> 0 | D55: kg/hr | E55: =C55*Units!D501 -> 0 | F55: MT/hr | G55: =E55/1000 -> 0
A56: Valerate Production | B56: kg/hr | C56: =ExpBase!C256 -> 36.161019 | D56: kg/hr | E56: =C56*Units!D502 -> 21.475969 | F56: MT/hr | G56: =E56/1000 -> 0.021475969
A57: Isovaleric Production | B57: kg/hr | C57: =ExpBase!C257 -> 3.4198477 | D57: kg/hr | E57: =C57*Units!D503 -> 2.0310419 | F57: MT/hr | G57: =E57/1000 -> 0.0020310419
A58: Caproic Production | B58: kg/hr | C58: =ExpBase!C258 -> 21.79648 | D58: kg/hr | E58: =C58*Units!D504 -> 13.641208 | F58: MT/hr | G58: =E58/1000 -> 0.013641208
A59: Heptanoate Production | B59: kg/hr | C59: =ExpBase!C259 -> 0 | D59: kg/hr | E59: =C59*Units!D505 -> 0 | F59: MT/hr | G59: =E59/1000 -> 0
A62: NITROGEN REMOVAL
A63: Parameter | B63: Unit | C63: Value | D63: Unit | E63: Carbon | F63: Unit | G63: Carbon Flow Rate | H63: Unit | I63: Total Carbon Flow | J63: TYPE
A64: Manure Filtration
A65: IN
A66: Sludge | H66: =H29 -> MT/hr | I66: =SUM(I28:I29)-(I31*2) -> 1.5633371 | J66: SLUDGE
A67: OUT
A68: Liquid Digestate | H68: MT/hr | I68: =I34 -> 0.092794335 | J68: LIQUID VFAs
A69: Biosolid Waste | H69: MT/hr | I69: =I66-I68-I29 -> 1.1752082 | J69: BIOSOLID WASTE
H70: MT/hr | I70: =I29 -> 0.29533459 | J70: BIOSOLID RECYCLE
A71: Nitrogen Removal
A72: Treated Liquid Digestate | H72: MT/hr | I72: =SUM(G73:G81) -> 0.090185342 | J72: TREATED LIQUID VFAs
A73: Lactate Produced | B73: kg/hr | C73: =C34 -> 0.99389647 | D73: kg/hr | E73: =C73*Units!D494 -> 0.39756962 | F73: MT/hr | G73: =E73/1000 -> 0.00039756962 | H73: MT/hr | I73: =I68-I72 -> 0.0026089928 | J73: VFA LOSS
A74: Acetate Produced | B74: kg/hr | C74: =C35-ExpBase!G585 -> 59.192264 | D74: kg/hr | E74: =C74*Units!D498 -> 24.083953 | F74: MT/hr | G74: =E74/1000 -> 0.024083953
A75: Propionic Production | B75: kg/hr | C75: =C36-ExpBase!G586 -> -8.7641156e-08 | D75: kg/hr | E75: =C75*Units!D499 -> -4.3218473e-08 | F75: MT/hr | G75: =E75/1000 -> -4.3218473e-11
A76: Butyric Production | B76: kg/hr | C76: =C37-ExpBase!G587 -> 62.126039 | D76: kg/hr | E76: =C76*Units!D500 -> 34.268466 | F76: MT/hr | G76: =E76/1000 -> 0.034268466
A77: Isobutyric Production | B77: kg/hr | C77: =C38-ExpBase!G588 -> 2.8489706 | D77: kg/hr | E77: =C77*Units!D501 -> 1.5714804 | F77: MT/hr | G77: =E77/1000 -> 0.0015714804
A78: Valerate Production | B78: kg/hr | C78: =C39-ExpBase!G589 -> 36.682742 | D78: kg/hr | E78: =C78*Units!D502 -> 21.78582 | F78: MT/hr | G78: =E78/1000 -> 0.02178582
A79: Isovaleric Production | B79: kg/hr | C79: =C40-ExpBase!G590 -> -1.5564055e-08 | D79: kg/hr | E79: =C79*Units!D503 -> -9.2434666e-09 | F79: MT/hr | G79: =E79/1000 -> -9.2434666e-12
A80: Caproic Production | B80: kg/hr | C80: =C41-ExpBase!G591 -> 12.907444 | D80: kg/hr | E80: =C80*Units!D504 -> 8.0780534 | F80: MT/hr | G80: =E80/1000 -> 0.0080780534
A81: Heptanoate Production | B81: kg/hr | C81: =C42-ExpBase!G592 -> -2.1356536e-08 | D81: kg/hr | E81: =C81*Units!D505 -> -1.390101e-08 | F81: MT/hr | G81: =E81/1000 -> -1.390101e-11
A84: CHAIN-ELONGATION
A85: Parameter | B85: Unit | C85: Value | D85: Unit | E85: Carbon | F85: Unit | G85: Carbon Flow Rate | H85: Unit | I85: Total Carbon Flow | J85: TYPE
A86: IN
A87: Food Waste | H87: MT/hr | I87: =I51 -> 0.087530692 | J87: FOOD WASTE
A88: Treated Manure LD | H88: MT/hr | I88: =I72 -> 0.090185342 | J88: TREATED LIQUID
A89: Cheese Whey Lactate | H89: MT/hr | I89: =I20 -> 0.83965559 | J89: CONCENTRATED LACTATE
A90: Biosolid Recycle | H90: MT/hr | I90: =(SUM(I87:I89)-I104)*0.1 -> 0.011633359 | J90: BIOSOLID RECYCLE
A91: Extraction Recycle | H91: MT/hr | I91: =(I123-I127)*0.1 -> 0.0039721944 | J91: EXTRACTION RECYCLE
A92: OUT
A93: Liquid Digestate Acids
A94: total acetate | B94: kg/hr | C94: =Inputs!F$13*ExpBase!E681/1000 -> 44.833254 | D94: kg/hr | E94: =C94*Units!D498 -> 18.241606 | F94: MT/hr | G94: =E94/1000 -> 0.018241606 | H94: MT/hr | I94: =SUM(G94:G101) -> 0.86745181 | J94: VFAS
A95: total propionate | B95: kg/hr | C95: =Inputs!F$13*ExpBase!E682/1000 -> 143.84121 | D95: kg/hr | E95: =C95*Units!D499 -> 70.932397 | F95: MT/hr | G95: =E95/1000 -> 0.070932397
A96: total butyrate | B96: kg/hr | C96: =Inputs!F$13*ExpBase!E683/1000 -> 198.49181 | D96: kg/hr | E96: =C96*Units!D500 -> 109.48726 | F96: MT/hr | G96: =E96/1000 -> 0.10948726
A97: total isobutyrate | B97: kg/hr | C97: =Inputs!F$13*ExpBase!E684/1000 -> 0 | D97: kg/hr | E97: =C97*Units!D501 -> 0 | F97: MT/hr | G97: =E97/1000 -> 0
A98: total valerate | B98: kg/hr | C98: =Inputs!F$13*ExpBase!E685/1000 -> 313.8984 | D98: kg/hr | E98: =C98*Units!D502 -> 186.42374 | F98: MT/hr | G98: =E98/1000 -> 0.18642374
A99: total isovalerate | B99: kg/hr | C99: =Inputs!F$13*ExpBase!E686/1000 -> 27.358782 | D99: kg/hr | E99: =C99*Units!D503 -> 16.248335 | F99: MT/hr | G99: =E99/1000 -> 0.016248335
A100: total caproate | B100: kg/hr | C100: =Inputs!F$13*ExpBase!E687/1000 -> 708.52004 | D100: kg/hr | E100: =C100*Units!D504 -> 443.42341 | F100: MT/hr | G100: =E100/1000 -> 0.44342341
A101: total heptanoate | B101: kg/hr | C101: =Inputs!F$13*ExpBase!E688/1000 -> 34.867103 | D101: kg/hr | E101: =C101*Units!D505 -> 22.695064 | F101: MT/hr | G101: =E101/1000 -> 0.022695064
A102: Lactate | H102: MT/hr | I102: =I89*0.04 -> 0.033586224 | J102: LACTATE
H103: MT/hr | I103: =SUM(I87:I89)-SUM(I94,I102)-I90 -> 0.10470023 | J103: BIOSOLID WASTE
H104: MT/hr | I104: =SUM(I94,I102) -> 0.90103804 | J104: CONTINUES
A107: ELECTRODIALYSIS
A108: Parameter | B108: Unit | C108: Value | D108: Unit | E108: Carbon | F108: Unit | G108: Carbon Flow Rate | H108: Unit | I108: Total Carbon Flow | J108: TYPE
A109: IN | H109: MT/hr | I109: =I104 -> 0.90103804 | J109: FEED
A110: OUT
...

Sheet CostCalc
A1: CALCULATIONS - CAPEX
A6: Transportation
A7: Parameter | B7: Size Required
B8: Size | C8: Unit | D8: Cost | E8: Unit
A10: Manure | B10: =Inputs!F13*(Inputs!F15)/Units!C15 -> 22.5 | C10: m3/hr
B11: =B10*Units!C5 -> 85.1625 | C11: yd3/hr
A12: Food Waste | B12: =Inputs!F13*(Inputs!F14)/Units!C15 -> 2.5 | C12: m3/hr
B13: =B12*Units!C5 -> 9.4625 | C13: yd3/hr
A14: Total | B14: =SUM(B10,B12) -> 25 | C14: m3/hr
B15: =B14*Units!C$5 -> 94.625 | C15: yd3/hr
B16: =B15*Units!C$55 -> 2271 | C16: yd3/day
A17: Distance | B17: 242 | C17: mi/round trip
A18: Truck Speed | B18: =Inputs!F8 -> 60 | C18: mi/hr
A19: Time | B19: =B17/B18 -> 4.0333333 | C19: hr/trip
A20: Trips | B20: =8/B19 -> 1.9834711 | C20: trip/day
A21: Truck Size | B21: 40 | C21: yd3/trip
B22: =B21*B20 -> 79.338843 | C22: yd3/day
A23: Number of Trucks | B23: =ROUNDUP((B16/B22)*1.5,0) -> 43 | C23: truck
A26: Cheese Whey | B26: 25.78 | C26: m3/hr
A27: Total | B27: =B26 -> 25.78 | C27: m3/hr
B28: =B27*Units!C$5 -> 97.5773 | C28: yd3/hr
B29: =B28*Units!C$55 -> 2341.8552 | C29: yd3/day
A30: Distance | B30: 190 | C30: mi/round trip
A31: Truck Speed | B31: 60 | C31: mi/hr
A32: Time | B32: =B30/B31 -> 3.1666667 | C32: hr/trip
A33: Trips | B33: =8/B32 -> 2.5263158 | C33: trip/day
A34: Truck Size | B34: 40 | C34: yd3/trip
B35: =B34*B33 -> 101.05263 | C35: yd3/day
A36: Number of Trucks | B36: =ROUNDUP((B29/B35)*1.5,0) -> 35 | C36: truck
A38: Ocean Water | B38: =ExpBase!Q102 -> 33.955948 | C38: m3/hr
A39: Total | B39: =B38 -> 33.955948 | C39: m3/hr
B40: =B39*Units!C$5 -> 128.52326 | C40: yd3/hr
B41: =B40*Units!C$55 -> 3084.5584 | C41: yd3/day
A42: Distance | B42: 170 | C42: mi/round trip
A43: Truck Speed | B43: 60 | C43: mi/hr
A44: Time | B44: =B42/B43 -> 2.8333333 | C44: hr/trip
A45: Trips | B45: =8/B44 -> 2.8235294 | C45: trip/day
A46: Truck Size | B46: 40 | C46: yd3/trip
B47: =B46*B45 -> 112.94118 | C47: yd3/day
A48: Number of Trucks | B48: =ROUNDUP((B41/B47)*1.5,0) -> 41 | C48: truck
A50: Hydraulic Truck Dump w/ Scale | B50: =SUM(B38,B26,B10) -> 82.235948 | C50: m3/hr
B51: =B50*Units!C15*Units!C46 -> 37301.593 | C51: lb/hr
A53: Cumulative Miles
A54: Ocean Water | B54: =(B42*B45)*2/Units!C$55*Inputs!F$3/Inputs!F$7 -> 711111.11 | C54: gal/yr
A55: Cheese Whey | B55: =(B30*B33)/Units!C$55*Inputs!F$3/Inputs!F$7 -> 355555.56 | C55: gal/yr
A56: Waste | B56: =(B17*B20)/Units!C$55*Inputs!F$3/Inputs!F$7 -> 355555.56 | C56: gal/yr
A59: Inoculum Development
A60: Parameter | B60: Size Required | F60: Researched Value
B61: Size | C61: Unit | D61: Number | E61: Material | F61: Value | G61: Size | H61: Unit
A63: Incubator | B63: 178 | C63: L | F63: =Inputs!F857 -> 4430 | G63: 178 | H63: L
A69: Ocean Water Processing
A70: Parameter | B70: Size Required | F70: Researched Value
B71: Size | C71: Unit | D71: Number | E71: Material | F71: Value | G71: Size | H71: Unit
A73: Flow Rate - Ocean Water | B73: =ExpBase!Q102 -> 33.955948 | C73: m3/hr
B74: =B73*Units!C15 -> 33955.948 | C74: kg/hr
A76: ED Tank Membrane
A77: LD Tank Volume | B77: =B73*Inputs!F86 -> 203.73569 | C77: m3
A78: Total Membrane SA | B78: =B77*Inputs!F103 -> 101867.85 | C78: m2
A79: Number of Membranes | B79: =ROUNDUP(B78/Inputs!F99,0) -> 101868 | C79: #
A80: Membrane Stacks | B80: =ROUNDUP(B79/Inputs!D106,-1) -> 33960 | C80: #
A81: Membrane Thickness | B81: 127 | C81: um
B82: =B81*Units!C80 -> 0.000127 | C82: m
A83: Separation Between | B83: =Inputs!F105 -> 0.001 | C83: m
A84: Total Length | B84: =(B83+B82)*B79 -> 114.80524 | C84: m
A85: Plan View Area | B85: =B73/B84 -> 0.29577003 | C85: m2
A87: Cation Exchange Membrane | B87: =B80*Inputs!F107 -> 33960 | C87: #
A88: Anion Exchange Membrane | B88: =B80*Inputs!F108 -> 33960 | C88: #
A89: Bipolar Exchange Membrane | B89: =B80*Inputs!F109 -> 67920 | C89: #
A90: Membrane Pairs | B90: =SUM(B87:B89)/3 -> 45280 | C90: #
A92: CEM Surface Area | B92: =B87*Inputs!F$99 -> 33960 | C92: m2
A93: AEM Surface Area | B93: =B88*Inputs!F$99 -> 33960 | C93: m2
A94: BPEM Surface Area | B94: =B89*Inputs!F$99 -> 67920 | C94: m2
A96: Maximum Applied Voltage | B96: =B90*Inputs!F90 -> 90560
A97: Maximum Applied Current | B97: =B90*Inputs!D91 -> 27168
A99: Electrodialysis Units | B99: =ROUNDUP(B80/Inputs!F104,0) -> 340 | C99: #
A102: Anode | B102: =Inputs!F110*Inputs!D111*B99 -> 122.4 | C102: m3
A103: Cathode | B103: =B102 -> 122.4 | C103: m3
A104: Anode | B104: =B103/G312 -> 86.485557 | C104: ton
A105: Cathode | B105: =B104 -> 86.485557 | C105: ton
A108: Peristaltic Pump
A109: Flow Rate | B109: =B74 -> 33955.948 | C109: L/hr
A110: Number
A114: Electrolyte Tank
A115: Volume | B115: =ExpBase!N102*Inputs!F86 -> 40.747138 | C115: m3 | D115: =IF(B115>Inputs!F$113,ROUNDUP(B115/Inputs!F$113,0),1) -> 41
A116: Diameter | B116: =((4*B115)/(1.2*Units!C$79))^(1/3) -> 3.5097433 | C116: m
A117: Radius | B117: =B116/2 -> 1.7548717 | C117: m
A118: Height | B118: =B116*Inputs!F$114 -> 4.211692 | C118: m
A119: Surface Area | B119: =(2*B117*B118*Units!C$79)+(2*Units!C$79*CostCalc!B$117^2) -> 65.788414 | C119: m2
A120: Thickness | B120: =0.5 -> 0.5 | C120: m
A121: Volume of Concrete Needed | B121: =B119*B120 -> 32.894207 | C121: m3
A123: Liquid Digestate Compartment
A124: Volume | B124: =ExpBase!Q102*Inputs!F86 -> 203.73569 | C124: m3 | D124: =IF(B124>Inputs!F$113,ROUNDUP(B124/Inputs!F$113,0),1) -> 204
A125: Diameter | B125: =((4*B124)/(1.2*Units!C$79))^(1/3) -> 6.0015767 | C125: m
A126: Radius | B126: =B125/2 -> 3.0007883 | C126: m
A127: Height | B127: =B125*Inputs!F$114 -> 7.201892 | C127: m
A128: Surface Area | B128: =(2*B126*B127*Units!C$79)+(2*Units!C$79*CostCalc!B$117^2) -> 155.13764 | C128: m2
A129: Thickness | B129: =0.5 -> 0.5 | C129: m
A130: Volume of Concrete Needed | B130: =B128*B129 -> 77.568822 | C130: m3
A132: Cation Water Compartment
A133: Volume | B133: =ExpBase!N102*Inputs!F86 -> 40.747138 | C133: m3 | D133: =IF(B133>Inputs!F$113,ROUNDUP(B133/Inputs!F$113,0),1) -> 41
...

Sheet Locate
A1: LOCATION ANALYSIS
A4: Parameter | B4: Description | C4: Unit | D4: Value
A5: San Francisco, CA
A6: Food Waste | B6: compost collected | C6: ton/day | D6: 500
C7: kg/d | D7: =D6*Units!C45 -> 453592.5
C8: kg/hr | D8: =D7/Units!C55 -> 18899.688
C9: m3/hr | D9: =D8/Units!C18 -> 17.999702
A10: capita | B10: population of san francisco | C10: # | D10: 808437
A11: fw_cap | B11: food waste per person | C11: m3/hr-cap | D11: =D9/D10 -> 2.2264818e-05
A12: Harris Ranch | B12: 29475 Fresno Coalinga Road, Coalinga CA
A13: Manure | B13: number of cows | C13: # | D13: 250000
B14: Coalinga, CA 93210 | C14: kg/d | D14: =D13*Inputs!F4 -> 13450000
C15: kg/hr | D15: =D14/Units!C55 -> 560416.67
C16: m3/hr | D16: =D15/Units!C18 -> 533.73016
B17: TOTAL | C17: m3/hr | D17: =D9+D16 -> 551.72986
B18: Distance Between FW and Manure | C18: mi | D18: 182
A19: FW/M | B19: Ratio food waste to manure | D19: =D8/D15 -> 0.033724349
A21: Austin, TX
A22: Food Waste | B22: compost collected | C22: ton/yr | D22: 138955
C23: kg/yr | D23: =D22*Units!C45 -> 1.2605789e+08
C24: kg/hr | D24: =D23/(Units!C52*Units!C55) -> 14390.17
C25: m3/hr | D25: =D24/Units!C18 -> 13.704924
A26: capita | B26: population of austin | C26: # | D26: 974447
A27: fw_capita | B27: food waste per person | C27: m3/hr-cap | D27: =D25/D26 -> 1.4064309e-05
A30: Berkeley, CA
A31: Food Waste | B31: compost collected | C31: ton/mon | D31: 1800
C32: kg/mon | D32: =D31*Units!C45 -> 1632933
C33: kg/hr | D33: =D32/(Units!C54*Units!C55) -> 2267.9625
C34: m3/hr | D34: =D33/Units!C18 -> 2.1599643
A35: capita | B35: population of berkeley | C35: # | D35: 118950
A36: fw_cap | B36: food waste per person | C36: m3/hr-cap | D36: =D34/D35 -> 1.815859e-05
A38: Fort Collins, CO
A39: Food Waste | B39: theoretical compost collected | C39: kg/hr | D39: =Inputs!D13*Inputs!D14 -> 15000
C40: m3/hr | D40: =D39/Units!C18 -> 14.285714
A41: capita | B41: population of fort collins area | C41: # | D41: 359000
A42: fw_capita | B42: food waste per person | C42: m3/hr-cap | D42: =D40/D41 -> 3.9793076e-05
A44: AVERAGE
A45: avg_fwc | B45: average food waste production per capita | C45: m3/hr-cap | D45: =AVERAGE(D11,D27,D36,D42) -> 2.3570198e-05
A46: sd_fwc | B46: standard deviation of fw production per cap | C46: m3/hr-cap | D46: =_xlfn.STDEV.P(D11,D27,D36,D42) -> 9.8047591e-06
A47: US_pop | B47: population of the US | C47: cap | D47: =333300000 -> 333300000
A48: US_fw | B48: theoretical food waste in the US | C48: m3/hr | D48: =D45*D47 -> 7855.9471
C49: kg/hr | D49: =D48*1050 -> 8248744.4
A50: US_cow | B50: number of cows in the US | C50: cow | D50: =28200000 -> 28200000
A51: US_poo | B51: amount of cattle manure in the US | C51: kg/d | D51: =Inputs!F4*D50 -> 1517160000
C52: m3/hr | D52: =D51/(Units!C18*Units!C55) -> 60204.762
A53: US_fwm | B53: food waste to cow manure ratio in the US | C53: %/100 | D53: =D48/D52 -> 0.13048714
B55: average FW production in US | C55: ton/yr | D55: =D48*Units!C18/Units!C45*Units!C55*Units!C52 -> 79651892
B56: standard deviation FW production in US | C56: ton/yr | D56: =(D48+(D46*D47))*Units!C18/Units!C45*Units!C55*Units!C52 -> 1.1278558e+08
A57: Total | B57: total flow rate of food waste and cattle manure | C57: m3/hr | D57: =D52+D48 -> 68060.709
C58: kg/hr | D58: =D57*Units!C18 -> 71463744
A60: US_tot_poo | B60: total amount of all manure produced in US | C60: ton/yr | D60: =1560000000 -> 1560000000
C61: kg/hr | D61: =D60*Units!C45/(Units!C52*Units!C55) -> 1.6155349e+08
C62: m3/hr | D62: =D61/Units!C18 -> 153860.47
A63: US_TOTAL | B63: total amount of all manure and foodwaste in US | C63: m3/hr | D63: =D62+D48 -> 161716.42
C64: kg/hr | D64: =D63*Units!C18 -> 1.6980224e+08
B65: percent foodwaste in total | C65: %/100 | D65: =D48/D63 -> 0.048578538
A69: San Francisco, CA | B69: =D9*Inputs!F3 -> 143997.62 | C69: ton/yr | D69: Food Waste
A70: Harris Ranch, CA | B70: =D17*Inputs!F3 -> 4413838.9 | C70: ton/yr | D70: Manure
A71: Austin, TX | B71: =D22 -> 138955 | C71: ton/yr | D71: Food Waste
A72: Berkeley, CA | B72: =D34*Inputs!F3 -> 17279.714 | C72: ton/yr | D72: Food Waste
A73: Fort Collins, CO | B73: =D40*Inputs!F3 -> 114285.71 | C73: ton/yr | D73: Food Waste

Sheet CAPEX
A1: CAPITAL EXPENSE
M3: April 2026 PPI | N3: 402.486
A5: Transportation
A7: Total Capital Investment
A8: Mechanical Equipment List | F8: Researched Values | K8: Scaled Installed in Current Year Factors | O8: Total Cost
A9: Equipment Name | B9: Size | C9: Unit | D9: Number Required | E9: Material | F9: Cost | G9: Size | H9: Unit | I9: Year | J9: Source | K9: Scaling Exponent | L9: Installation Factor | M9: Size Ratio | N9: PPI
N10: 2024
A11: Boats - Ocean Water | B11: 1 | C11: boat | D11: 2 | E11: Oceanographic Research Vessel, 100 ft | F11: 20000000 | G11: 1 | H11: boat | I11: 2024 | K11: 1 | L11: 1 | M11: =B11/G11 -> 1 | N11: =N$3/N$3 -> 1 | O11: =D11*N11*F11*L11*M11^(K11) -> 40000000
A12: Diesel Trucks - Ocean Water | B12: 40 | C12: yd3 | D12: =CostCalc!B48 -> 41 | E12: Peterbilt Front Loader | F12: =Inputs!F$844*G12 -> 355000 | G12: 40 | H12: yd3 | I12: 2024 | K12: 1 | L12: 1 | M12: =B12/G12 -> 1 | N12: =N$3/N$3 -> 1 | O12: =D12*N12*F12*L12*M12^(K12) -> 14555000
A13: Diesel Trucks - Cheese Whey | B13: 40 | C13: yd3 | D13: =CostCalc!B36 -> 35 | E13: Peterbilt Front Loader | F13: =Inputs!F$844*G13 -> 355000 | G13: 40 | H13: yd3 | I13: 2024 | K13: 1 | L13: 1 | M13: =B13/G13 -> 1 | N13: =N$3/N$3 -> 1 | O13: =D13*N13*F13*L13*M13^(K13) -> 12425000
A14: Diesel Trucks - Organic Waste | B14: =CostCalc!B21 -> 40 | C14: yd3 | D14: =CostCalc!B23 -> 43 | E14: Peterbilt Front Loader | F14: =Inputs!F$844*G14 -> 355000 | G14: 40 | H14: yd3 | I14: 2024 | K14: 1 | L14: 1 | M14: =B14/G14 -> 1 | N14: =N$3/N$3 -> 1 | O14: =D14*N14*F14*L14*M14^(K14) -> 15265000
A15: Hydraulic Truck Dump with Scale | B15: =CostCalc!B51 -> 37301.593 | C15: lb/hr | D15: 2 | F15: 80000 | G15: 367.437 | H15: lb/hr | I15: 1998 | K15: 0.6 | L15: 2.47 | M15: =B15/G15 -> 101.51834 | N15: =N$3/142.2 -> 2.8304219 | O15: =D15*N15*F15*L15*M15^(K15) -> 17889360
A17: Total: | O17: =SUM(O11:O15) -> 1.0013436e+08
A20: Inoculum Development
A22: Total Capital Investment
A23: Mechanical Equipment List | F23: Researched Values | K23: Scaled Installed in Current Year Factors | O23: Total Cost
A24: Equipment Name | B24: Size | C24: Unit | D24: Number Required | E24: Material | F24: Cost | G24: Size | H24: Unit | I24: Year | J24: Source | K24: Scaling Exponent | L24: Installation Factor | M24: Size Ratio | N24: PPI
N25: 2024
A26: Feed Pump - Caprociproducens | C26: kg/hr | E26: 316 Stainless Steel | F26: 11358 | G26: 43149 | H26: kg/hr | I26: 2018 | K26: 0.8 | L26: 2.3 | M26: =B26/G26 -> 0 | N26: =N$3/329.7 -> 1.2207643
A27: Tank Wall - Caprociproducens | C27: m3 | D27: =CostCalc!D$289 -> 4 | E27: Concrete | F27: =Inputs!F$847 -> 188.34 | G27: 0.76 | H27: m3 | I27: 2022 | J27: 2 | K27: 0.7 | L27: 2.6 | M27: =B27/G27 -> 0 | N27: =N$3/432.15 -> 0.93135717
A28: Insulation - Caprociproducens | C28: m2 | D28: =D$179 -> 2 | E28: Unfaced Fiberglass | F28: =Inputs!F$848 -> 8.35 | G28: 0.09 | H28: m2 | I28: 2022 | J28: 3 | K28: 1 | L28: 2.6 | M28: =B28/G28 -> 0 | N28: =N$3/432.15 -> 0.93135717
A29: Gas Cover - Caprociproducens | C29: m3 | D29: 2 | E29: Double Membrane Polyvinylidene Fluoride 1.5 mm, Pressure and Volume Sensor | F29: =Inputs!F$850*CostCalc!G$300 -> 32000.06 | G29: 1000 | H29: m3 | I29: 2023 | K29: 1 | L29: 2.6 | M29: =B29/G29 -> 0 | N29: =N$3/421.24 -> 0.95547906
A30: Agitator - Caprociproducens | C30: hp | D30: =D$180 -> 2 | E30: Stainless Steel, Fixed Propeller, 3 Impellers, 2 Blades, Motor, Gear drive | F30: =Inputs!F$849*G30 -> 600 | G30: 1 | H30: hp | I30: 1998 | J30: 4 | K30: 0.5 | L30: 1.5 | M30: =B30/G30 -> 0 | N30: =N$3/142.2 -> 2.8304219
A31: Feed Pump - Lignocellulose | C31: kg/hr | E31: 316 Stainless Steel | F31: 11358 | G31: 43149 | H31: kg/hr | I31: 2018 | K31: 0.8 | L31: 2.3 | M31: =B31/G31 -> 0 | N31: =N$3/329.7 -> 1.2207643
A32: Tank Wall - Lignocellulose | C32: m3 | D32: =CostCalc!D$289 -> 4 | E32: Concrete | F32: =Inputs!F$847 -> 188.34 | G32: 0.76 | H32: m3 | I32: 2022 | J32: 2 | K32: 0.7 | L32: 2.6 | M32: =B32/G32 -> 0 | N32: =N$3/432.15 -> 0.93135717
A33: Insulation - Lignocellulose | C33: m2 | D33: =D$179 -> 2 | E33: Unfaced Fiberglass | F33: =Inputs!F$848 -> 8.35 | G33: 0.09 | H33: m2 | I33: 2022 | J33: 3 | K33: 1 | L33: 2.6 | M33: =B33/G33 -> 0 | N33: =N$3/432.15 -> 0.93135717
A34: Gas Cover - Lignocellulose | C34: m3 | D34: 2 | E34: Double Membrane Polyvinylidene Fluoride 1.5 mm, Pressure and Volume Sensor | F34: =Inputs!F$850*CostCalc!G$300 -> 32000.06 | G34: 1000 | H34: m3 | I34: 2023 | K34: 1 | L34: 2.6 | M34: =B34/G34 -> 0 | N34: =N$3/421.24 -> 0.95547906
A35: Agitator - Lignocellulose | C35: hp | D35: =D$180 -> 2 | E35: Stainless Steel, Fixed Propeller, 3 Impellers, 2 Blades, Motor, Gear drive | F35: =Inputs!F$849*G35 -> 600 | G35: 1 | H35: hp | I35: 1998 | J35: 4 | K35: 0.5 | L35: 1.5 | M35: =B35/G35 -> 0 | N35: =N$3/142.2 -> 2.8304219
A36: Feed Pump - Cl. Klu | C36: kg/hr | E36: 316 Stainless Steel | F36: 11358 | G36: 43149 | H36: kg/hr | I36: 2018 | K36: 0.8 | L36: 2.3 | M36: =B36/G36 -> 0 | N36: =N$3/329.7 -> 1.2207643
A37: Tank Wall - Cl. Klu | C37: m3 | D37: =CostCalc!D$289 -> 4 | E37: Concrete | F37: =Inputs!F$847 -> 188.34 | G37: 0.76 | H37: m3 | I37: 2022 | J37: 2 | K37: 0.7 | L37: 2.6 | M37: =B37/G37 -> 0 | N37: =N$3/432.15 -> 0.93135717
A38: Insulation - Cl. Klu | C38: m2 | D38: =D$179 -> 2 | E38: Unfaced Fiberglass | F38: =Inputs!F$848 -> 8.35 | G38: 0.09 | H38: m2 | I38: 2022 | J38: 3 | K38: 1 | L38: 2.6 | M38: =B38/G38 -> 0 | N38: =N$3/432.15 -> 0.93135717
A39: Gas Cover - Cl. Klu | C39: m3 | D39: 2 | E39: Double Membrane Polyvinylidene Fluoride 1.5 mm, Pressure and Volume Sensor | F39: =Inputs!F$850*CostCalc!G$300 -> 32000.06 | G39: 1000 | H39: m3 | I39: 2023 | K39: 1 | L39: 2.6 | M39: =B39/G39 -> 0 | N39: =N$3/421.24 -> 0.95547906
A40: Agitator - Cl. Klu | C40: hp | D40: =D$180 -> 2 | E40: Stainless Steel, Fixed Propeller, 3 Impellers, 2 Blades, Motor, Gear drive | F40: =Inputs!F$849*G40 -> 600 | G40: 1 | H40: hp | I40: 1998 | J40: 4 | K40: 0.5 | L40: 1.5 | M40: =B40/G40 -> 0 | N40: =N$3/142.2 -> 2.8304219
A41: Feed Pump - Cl. Lj | C41: kg/hr | E41: 316 Stainless Steel | F41: 11358 | G41: 43149 | H41: kg/hr | I41: 2018 | K41: 0.8 | L41: 2.3 | M41: =B41/G41 -> 0 | N41: =N$3/329.7 -> 1.2207643
A42: Tank Wall - Cl. Lj | C42: m3 | D42: =CostCalc!D$289 -> 4 | E42: Concrete | F42: =Inputs!F$847 -> 188.34 | G42: 0.76 | H42: m3 | I42: 2022 | J42: 2 | K42: 0.7 | L42: 2.6 | M42: =B42/G42 -> 0 | N42: =N$3/432.15 -> 0.93135717
A43: Insulation - Cl. Lj | C43: m2 | D43: =D$179 -> 2 | E43: Unfaced Fiberglass | F43: =Inputs!F$848 -> 8.35 | G43: 0.09 | H43: m2 | I43: 2022 | J43: 3 | K43: 1 | L43: 2.6 | M43: =B43/G43 -> 0 | N43: =N$3/432.15 -> 0.93135717
A44: Gas Cover - Cl. Lj | C44: m3 | D44: 2 | E44: Double Membrane Polyvinylidene Fluoride 1.5 mm, Pressure and Volume Sensor | F44: =Inputs!F$850*CostCalc!G$300 -> 32000.06 | G44: 1000 | H44: m3 | I44: 2023 | K44: 1 | L44: 2.6 | M44: =B44/G44 -> 0 | N44: =N$3/421.24 -> 0.95547906
A45: Agitator - Cl. Lj | C45: hp | D45: =D$180 -> 2 | E45: Stainless Steel, Fixed Propeller, 3 Impellers, 2 Blades, Motor, Gear drive | F45: =Inputs!F$849*G45 -> 600 | G45: 1 | H45: hp | I45: 1998 | J45: 4 | K45: 0.5 | L45: 1.5 | M45: =B45/G45 -> 0 | N45: =N$3/142.2 -> 2.8304219
A46: Feed Pump - E. Coli | C46: kg/hr | E46: 316 Stainless Steel | F46: 11358 | G46: 43149 | H46: kg/hr | I46: 2018 | K46: 0.8 | L46: 2.3 | M46: =B46/G46 -> 0 | N46: =N$3/329.7 -> 1.2207643
A47: Tank Wall - E. Coli | C47: m3 | D47: =CostCalc!D$289 -> 4 | E47: Concrete | F47: =Inputs!F$847 -> 188.34 | G47: 0.76 | H47: m3 | I47: 2022 | J47: 2 | K47: 0.7 | L47: 2.6 | M47: =B47/G47 -> 0 | N47: =N$3/432.15 -> 0.93135717
A48: Insulation - E. Coli | C48: m2 | D48: =D$179 -> 2 | E48: Unfaced Fiberglass | F48: =Inputs!F$848 -> 8.35 | G48: 0.09 | H48: m2 | I48: 2022 | J48: 3 | K48: 1 | L48: 2.6 | M48: =B48/G48 -> 0 | N48: =N$3/432.15 -> 0.93135717
A49: Gas Cover - E. Coli | C49: m3 | D49: 2 | E49: Double Membrane Polyvinylidene Fluoride 1.5 mm, Pressure and Volume Sensor | F49: =Inputs!F$850*CostCalc!G$300 -> 32000.06 | G49: 1000 | H49: m3 | I49: 2023 | K49: 1 | L49: 2.6 | M49: =B49/G49 -> 0 | N49: =N$3/421.24 -> 0.95547906
A50: Agitator - E. Coli | C50: hp | D50: =D$180 -> 2 | E50: Stainless Steel, Fixed Propeller, 3 Impellers, 2 Blades, Motor, Gear drive | F50: =Inputs!F$849*G50 -> 600 | G50: 1 | H50: hp | I50: 1998 | J50: 4 | K50: 0.5 | L50: 1.5 | M50: =B50/G50 -> 0 | N50: =N$3/142.2 -> 2.8304219
A52: Total:
A56: Ocean Water Processing
A58: Total Capital Investment
A59: Mechanical Equipment List | F59: Researched Values | K59: Scaled Installed in Current Year Factors | O59: Total Cost
A60: Equipment Name | B60: Size | C60: Unit | D60: Number Required | E60: Material | F60: Cost | G60: Size | H60: Unit | I60: Year | J60: Source | K60: Scaling Exponent | L60: Installation Factor | M60: Size Ratio | N60: PPI
N61: 2024
A62: Feed Pump | B62: =CostCalc!B74 -> 33955.948 | C62: kg/hr | D62: 2 | E62: 316 Stainless Steel | F62: 11358 | G62: 43149 | H62: kg/hr | I62: 2018 | K62: 0.8 | L62: 2.3 | M62: =B62/G62 -> 0.78694636 | N62: =N$3/329.7 -> 1.2207643 | O62: =D62*N62*F62*L62*M62^(K62) -> 52655.972
A63: Decanter | B63: =CostCalc!B74 -> 33955.948 | C63: kg/hr | D63: 2 | F63: 327680 | G63: 13403 | H63: kg/hr | I63: 2011 | K63: 0.6 | L63: 2.3 | M63: =B63/G63 -> 2.5334588 | N63: =N$3/295.3 -> 1.3629732 | O63: =D63*N63*F63*L63*M63^(K63) -> 3588586.4
A64: Microfiltration | B64: =CostCalc!B73 -> 33.955948 | C64: m3/hr | D64: 2 | E64: Sepro (USA) 0.45 um | F64: =CostCalc!F$378 -> 990 | G64: =CostCalc!G$376 -> 40.5 | H64: m3/hr | I64: 2012 | J64: 11 | K64: 0.8 | L64: 1.7 | M64: =B64/G64 -> 0.83841848 | N64: =N$3/311.7 -> 1.2912608 | O64: =D64*N64*F64*L64*M64^(K64) -> 3774.8245
A65: Anion-Exchange Membrane | B65: =CostCalc!B92 -> 33960 | C65: m2 | D65: 2 | E65: Fumasep FAS-PET-130 | F65: =Inputs!F$854 -> 16 | G65: 1 | H65: m2 | I65: 2024 | K65: 0.5 | L65: 2.3 | M65: =B65/G65 -> 33960 | N65: =N$3/389.544 -> 1.0332235 | O65: =D65*N65*F65*L65*M65^(K65) -> 14013.8
A66: Cation-Exchange Membrane | B66: =CostCalc!B93 -> 33960 | C66: m2 | D66: 2 | E66: Fumasep FKS-PET-130 | F66: =Inputs!F$855 -> 17.5 | G66: 1 | H66: m2 | I66: 2024 | K66: 0.5 | L66: 2.3 | M66: =B66/G66 -> 33960 | N66: =N$3/389.544 -> 1.0332235 | O66: =D66*N66*F66*L66*M66^(K66) -> 15327.594
A67: Bipolar-Exchange Membrane | B67: =CostCalc!B94 -> 67920 | C67: m2 | D67: 2 | E67: Fumasep FBM | F67: =Inputs!F$856 -> 52.5 | G67: 1 | H67: m2 | I67: 2024 | K67: 0.5 | L67: 2.3 | M67: =B67/G67 -> 67920 | N67: =N$3/389.544 -> 1.0332235 | O67: =D67*N67*F67*L67*M67^(K67) -> 65029.473
A68: Electrodes | B68: =SUM(CostCalc!B104:B105) -> 172.97111 | C68: ton | D68: 2 | E68: Graphite | F68: =Inputs!F$853 -> 3000 | G68: 1 | H68: ton | I68: 2023 | K68: 0.5 | L68: 2.3 | M68: =B68/G68 -> 172.97111 | N68: =N$3/421.24 -> 0.95547906 | O68: =D68*N68*F68*L68*M68^(K68) -> 173415.16
A69: Diluate Tank Wall | B69: =CostCalc!B130 -> 77.568822 | C69: m3 | D69: 2 | E69: Concrete | F69: =CostCalc!F$288 -> 188.34 | G69: 0.76 | H69: m3 | I69: 2022 | J69: 6 | K69: 0.7 | L69: 2.6 | M69: =B69/G69 -> 102.06424 | N69: =N$3/432.15 -> 0.93135717 | O69: =D69*N69*F69*L69*M69^(K69) -> 23242.011
A70: Electrolyte Tank Wall | B70: =CostCalc!B121 -> 32.894207 | C70: m3 | D70: 2 | E70: Concrete | F70: =CostCalc!F$504 -> 188.34 | G70: 0.76 | H70: m3 | I70: 2022 | J70: 2 | K70: 0.5 | L70: 2.6 | M70: =B70/G70 -> 43.281852 | N70: =N$3/432.15 -> 0.93135717 | O70: =D70*N70*F70*L70*M70^(K70) -> 6000.882
A71: Concentrate Tank 1 Wall | B71: =CostCalc!B139 -> 32.894207 | C71: m3 | D71: 2 | E71: Concrete | F71: =CostCalc!F$504 -> 188.34 | G71: 0.76 | H71: m3 | I71: 2022 | J71: 2 | K71: 0.5 | L71: 2.6 | M71: =B71/G71 -> 43.281852 | N71: =N$3/432.15 -> 0.93135717 | O71: =D71*N71*F71*L71*M71^(K71) -> 6000.882
A72: Concentrate Tank 2 Wall | B72: =CostCalc!B148 -> 32.894207 | C72: m3 | D72: 2 | E72: Concrete | F72: =CostCalc!F$504 -> 188.34 | G72: 0.76 | H72: m3 | I72: 2022 | J72: 2 | K72: 0.5 | L72: 2.6 | M72: =B72/G72 -> 43.281852 | N72: =N$3/432.15 -> 0.93135717 | O72: =D72*N72*F72*L72*M72^(K72) -> 6000.882
A73: Peristaltic Pump | B73: =CostCalc!B74 -> 33955.948 | C73: L/hr | D73: 8 | E73: Knight Equipment PMP-8120B, 115V Fixed Speed, T-66E Squeeze Tube | F73: =Inputs!F$860*G73 -> 631.9 | G73: 71 | H73: L/hr | I73: 2023 | J73: 14 | K73: 0.5 | L73: 2.3 | M73: =B73/G73 -> 478.25279 | N73: =N$3/421.24 -> 0.95547906 | O73: =D73*N73*F73*L73*M73^(K73) -> 242949.56
A74: Crystallizer | B74: 0 | C74: GPD | D74: 2 | E74: Crystallizer and feed pump | F74: 365400 | G74: 4000 | H74: GPD | I74: 2011 | K74: 0.8 | L74: 1.5 | M74: =B74/G74 -> 0 | N74: =N$3/295.3 -> 1.3629732 | O74: =D74*N74*F74*L74*M74^(K74) -> 0
A75: Heat Exchanger | B75: 0 | C75: MMBTU/hr | D75: 2 | E75: 304 Stainless Steel | F75: =Inputs!F$863*Reserve!G$10 -> 92000 | G75: 9.4 | H75: MMBTU/hr | I75: 2010 | K75: 0.7 | L75: 2.2 | M75: =B75/G75 -> 0 | N75: =N$3/267.6 -> 1.5040583 | O75: =D75*N75*F75*L75*M75^(K75) -> 0
A76: Electrolyte Storage Tank | B76: =B70 -> 32.894207 | C76: m3 | D76: 2 | E76: Sulfuric acid tank | F76: 5760 | G76: 72 | H76: m3 | I76: 1996 | K76: 0.71 | L76: 1.4 | M76: =B76/G76 -> 0.45686399 | N76: =N$3/135.8 -> 2.9638144 | O76: =D76*N76*F76*L76*M76^(K76) -> 27408.183
A77: Acid Storage Tank | B77: =B71 -> 32.894207 | C77: m3 | D77: 2 | E77: Sulfuric acid tank | F77: 5760 | G77: 72 | H77: m3 | I77: 1996 | K77: 0.71 | L77: 1.4 | M77: =B77/G77 -> 0.45686399 | N77: =N$3/135.8 -> 2.9638144 | O77: =D77*N77*F77*L77*M77^(K77) -> 27408.183
A78: Base Storage Tank | B78: =CostCalc!B153 -> 3080.4313 | C78: lb/hr | D78: 2 | E78: Caustic storage tank | F78: 16005 | G78: 262454 | H78: lb/hr | I78: 2007 | K78: 0.65 | L78: 3.01 | M78: =B78/G78 -> 0.011737033 | N78: =N$3/213.2 -> 1.887833 | O78: =D78*N78*F78*L78*M78^(K78) -> 10116.462
A79: Desalinated Water Storage Tank | B79: =CostCalc!B157 -> 149.51981 | C79: GPM | D79: 2 | E79: Clean water tank | F79: 194200 | G79: 1400 | H79: GPM | I79: 2013 | K79: 0.7 | L79: 2.23 | M79: =B79/G79 -> 0.10679986 | N79: =N$3/303.8 -> 1.3248387 | O79: =D79*N79*F79*L79*M79^(K79) -> 239743.36
A81: Total: | O81: =SUM(O62:O79) -> 4501673.6
A85: Cheese Whey Processing
A87: Total Capital Investment
A88: Mechanical Equipment List | F88: Researched Values | K88: Scaled Installed in Current Year Factors | O88: Total Cost
A89: Equipment Name | B89: Size | C89: Unit | D89: Number Required | E89: Material | F89: Cost | G89: Size | H89: Unit | I89: Year | J89: Source | K89: Scaling Exponent | L89: Installation Factor | M89: Size Ratio | N89: PPI
N90: 2024
A91: Feed Pump - CW+H2O | B91: =ExpBase!C143 -> 12071.385 | C91: kg/hr | D91: 2 | E91: 316 Stainless Steel | F91: 11358 | G91: 43149 | H91: kg/hr | I91: 2018 | K91: 0.8 | L91: 2.3 | M91: =B91/G91 -> 0.27976048 | N91: =N$3/329.7 -> 1.2207643 | O91: =D91*N91*F91*L91*M91^(K91) -> 23020.811
A92: Feed Pump - Recycle | B92: =ExpBase!C152 -> 3621.4155 | C92: kg/hr | D92: 2 | E92: 316 Stainless Steel | F92: 11358 | G92: 43149 | H92: kg/hr | I92: 2018 | K92: 0.8 | L92: 2.3 | M92: =B92/G92 -> 0.083928143 | N92: =N$3/329.7 -> 1.2207643 | O92: =D92*N92*F92*L92*M92^(K92) -> 8786.5345
A93: Hydrolysis Tank Wall | B93: =CostCalc!B179*CostCalc!B180 -> 375.13563 | C93: m3 | D93: 2 | E93: Concrete | F93: =Inputs!F$847 -> 188.34 | G93: 0.76 | H93: m3 | I93: 2022 | J93: 2 | K93: 0.7 | L93: 2.6 | M93: =B93/G93 -> 493.59951 | N93: =N$3/432.15 -> 0.93135717 | O93: =N93*F93*L93*M93^(K93) -> 35026.318
A94: Hydrolysis Insulation | B94: =CostCalc!B181/CostCalc!B180 -> 750.27126 | C94: m2 | D94: 2 | E94: Unfaced Fiberglass | F94: =Inputs!F$848 -> 8.35 | G94: 0.09 | H94: m2 | I94: 2022 | J94: 3 | K94: 1 | L94: 2.6 | M94: =B94/G94 -> 8336.3473 | N94: =N$3/432.15 -> 0.93135717 | O94: =N94*F94*L94*M94^(K94) -> 168558.98
A95: Hydrolysis Agitator | B95: =CostCalc!B185 -> 156.47463 | C95: hp | D95: 2 | E95: Stainless Steel, Fixed Propeller, 3 Impellers, 2 Blades, Motor, Gear drive | F95: =Inputs!F$849*G95 -> 600 | G95: 1 | H95: hp | I95: 1998 | J95: 4 | K95: 0.5 | L95: 1.5 | M95: =B95/G95 -> 156.47463 | N95: =N$3/142.2 -> 2.8304219 | O95: =N95*F95*L95*M95^(K95) -> 31865.127
A96: Feed Pump | B96: =CostCalc!B172 -> 15692.8 | C96: kg/hr | D96: 2 | E96: 316 Stainless Steel | F96: 11358 | G96: 43149 | H96: kg/hr | I96: 2018 | K96: 0.8 | L96: 2.3 | M96: =B96/G96 -> 0.36368862 | N96: =N$3/329.7 -> 1.2207643 | O96: =N96*F96*L96*M96^(K96) -> 14198.593
A97: Fermenter Tank Wall | B97: =CostCalc!B181 -> 375.13563 | C97: m3 | D97: 2 | E97: Concrete | F97: =Inputs!F$847 -> 188.34 | G97: 0.76 | H97: m3 | I97: 2022 | J97: 2 | K97: 0.7 | L97: 2.6 | M97: =B97/G97 -> 493.59951 | N97: =N$3/432.15 -> 0.93135717 | O97: =N97*F97*L97*M97^(K97) -> 35026.318
A98: Fermenter Insulation | B98: =CostCalc!B181/CostCalc!B180 -> 750.27126 | C98: m2 | D98: 2 | E98: Unfaced Fiberglass | F98: =Inputs!F$848 -> 8.35 | G98: 0.09 | H98: m2 | I98: 2022 | J98: 3 | K98: 0.9 | L98: 2.6 | M98: =B98/G98 -> 8336.3473 | N98: =N$3/432.15 -> 0.93135717 | O98: =N98*F98*L98*M98^(K98) -> 68336.748
A99: Fermenter Agitator | B99: =CostCalc!B185 -> 156.47463 | C99: hp | D99: 2 | E99: Stainless Steel, Fixed Propeller, 3 Impellers, 2 Blades, Motor, Gear drive | F99: =Inputs!F$849*G99 -> 600 | G99: 1 | H99: hp | I99: 1998 | J99: 4 | K99: 0.5 | L99: 1.5 | M99: =B99/G99 -> 156.47463 | N99: =N$3/142.2 -> 2.8304219 | O99: =N99*F99*L99*M99^(K99) -> 31865.127
A100: Feed Pump | B100: =CostCalc!B172 -> 15692.8 | C100: kg/hr | D100: 2 | E100: 316 Stainless Steel | F100: 11358 | G100: 43149 | H100: kg/hr | I100: 2018 | K100: 0.8 | L100: 2.3 | M100: =B100/G100 -> 0.36368862 | N100: =N$3/329.7 -> 1.2207643 | O100: =N100*F100*L100*M100^(K100) -> 14198.593
A101: Centrifuge Separator | B101: =CostCalc!B172 -> 15692.8 | C101: kg/hr | D101: 2 | F101: 588000 | G101: 156789 | H101: kg/hr | I101: 2011 | K101: 0.5 | L101: 2.3 | M101: =B101/G101 -> 0.10008866 | N101: =N$3/295.3 -> 1.3629732 | O101: =N101*F101*L101*M101^(K101) -> 583156.23
A102: Microfiltration | B102: =CostCalc!B172 -> 15692.8 | C102: m3/hr | D102: 2 | E102: Sepro (USA) 0.45 um | F102: =CostCalc!F$378 -> 990 | G102: =CostCalc!G$376 -> 40.5 | H102: m3/hr | I102: 2012 | J102: 11 | K102: 0.8 | L102: 1.7 | M102: =B102/G102 -> 387.47655 | N102: =N$3/311.7 -> 1.2912608 | O102: =N102*F102*L102*M102^(K102) -> 255678.63
A103: Feed Pump | B103: =ExpBase!C169 -> 15692.901 | C103: kg/hr | D103: 2 | E103: 316 Stainless Steel | F103: 11358 | G103: 43149 | H103: kg/hr | I103: 2018 | K103: 0.8 | L103: 2.3 | M103: =B103/G103 -> 0.36369095 | N103: =N$3/329.7 -> 1.2207643 | O103: =N103*F103*L103*M103^(K103) -> 14198.666
A104: pH Adjustment Tank Wall | B104: =CostCalc!B194 -> 12.321133 | C104: m3 | D104: 2 | E104: Concrete | F104: =Inputs!F$847 -> 188.34 | G104: =G72 -> 0.76 | H104: m3 | I104: 2022 | J104: 6 | K104: 0.7 | L104: 1.8 | M104: =B104/G104 -> 16.212017 | N104: =N$3/432.15 -> 0.93135717 | O104: =N104*F104*L104*M104^(K104) -> 2219.3064
A105: pH Adjustment Insulation | B105: =CostCalc!B194/CostCalc!B193 -> 24.642266 | C105: m2 | D105: 2 | E105: Unfaced Fiberglass | F105: =CostCalc!F$420 -> 8.35 | G105: =ROUNDUP(CostCalc!G$420,2) -> 0.1 | H105: m2 | I105: 2022 | J105: 3 | K105: 0.7 | L105: 1.8 | M105: =B105/G105 -> 246.42266 | N105: =N$3/432.15 -> 0.93135717 | O105: =N105*F105*L105*M105^(K105) -> 661.07646
A106: pH Adjustment Agitator | B106: =CostCalc!B198 -> 156.47563 | C106: hp | D106: 2 | E106: Stainless Steel, Fixed Propeller, 3 Impellers, 2 Blades, Motor, Gear drive | F106: =Inputs!F$849 -> 600 | G106: 1 | H106: hp | I106: 1998 | J106: 4 | K106: 0.5 | L106: 1.5 | M106: =B106/G106 -> 156.47563 | N106: =N$3/142.2 -> 2.8304219 | O106: =N106*F106*L106*M106^(K106) -> 31865.229
A107: Reverse Osmosis Filtration | B107: =CostCalc!B202 -> 34596.93 | C107: lb/hr | D107: 3 | E107: Reverse osmosis unit | F107: 350000 | G107: 197000 | H107: lb/hr | I107: 2012 | K107: 0.7 | L107: 1.15 | M107: =B107/G107 -> 0.17561893 | N107: =N$3/311.7 -> 1.2912608 | O107: =N107*F107*L107*M107^(K107) -> 153808.31
A108: Lactate Storage Tank | B108: =CostCalc!B204 -> 5.978248 | C108: m3 | D108: 2 | E108: Sulfuric acid tank | F108: 5760 | G108: 72 | H108: m3 | I108: 1996 | K108: 0.71 | L108: 1.4 | M108: =B108/G108 -> 0.083031222 | N108: =N$3/135.8 -> 2.9638144 | O108: =N108*F108*L108*M108^(K108) -> 4083.7857
A109: Desalinated Water Tank | B109: =CostCalc!B206 -> 593.9763 | C109: GPM | D109: 2 | E109: Clean water tank | F109: 194200 | G109: 1400 | H109: GPM | I109: 2013 | K109: 0.7 | L109: 1.2 | M109: =B109/G109 -> 0.42426879 | N109: =N$3/303.8 -> 1.3248387 | O109: =N109*F109*L109*M109^(K109) -> 169411.25
A111: Total: | O111: =SUM(O91:O109) -> 1645965.6
A115: Feedstock Preparation
A117: Total Capital Investment
A118: Mechanical Equipment List | F118: Researched Values | K118: Scaled Installed in Current Year Factors | O118: Total Cost
A119: Equipment Name | B119: Size | C119: Unit | D119: Number Required | E119: Material | F119: Cost | G119: Size | H119: Unit | I119: Year | J119: Source | K119: Scaling Exponent | L119: Installation Factor | M119: Size Ratio | N119: PPI
N120: 2024
A121: Sand Removal - Manure | B121: =ROUNDUP(CostCalc!B233,0) -> 11153 | C121: cow | D121: 2 | E121: 20'' by 22' Sand-Manure Separtor, 5 hp electric motor | F121: 33000 | G121: 75 | H121: cow | I121: 2003 | K121: 0.9 | L121: 1.5 | M121: =B121/G121 -> 148.70667 | N121: =N$3/154.9 -> 2.5983602 | O121: =D121*N121*F121*L121*M121^(K121) -> 23197007
A122: Tank Wall - Manure | B122: =CostCalc!B247 -> 4.8842414 | C122: m3 | D122: 2 | E122: Concrete | F122: =Inputs!F$847 -> 188.34 | G122: 0.76 | H122: m3 | I122: 2022 | J122: 6 | K122: 0.7 | L122: 1.8 | M122: =B122/G122 -> 6.4266335 | N122: =N$3/432.15 -> 0.93135717 | O122: =D122*N122*F122*L122*M122^(K122) -> 2322.4683
...

Sheet OPEX
A1: OPERATIONAL EXPENSE
A4: Transportation
A7: Variable Operating Cost
A8: Input | B8: Value Required | C8: Units | D8: Researched Values | H8: Scaled Cost
D9: Cost | E9: Units | F9: Year | G9: Source | H9: PPI 2024 | I9: Total Cost (per year)
A10: Diesel - Waste | B10: =CostCalc!B56 -> 355555.56 | C10: gal/yr | D10: 3.65 | E10: gal | F10: 2024 | H10: =CAPEX!N$3/389.544 -> 1.0332235 | I10: =B10*D10*H10 -> 1340894.4
A11: Diesel - Cheese Whey | B11: =CostCalc!B55 -> 355555.56 | C11: gal/yr | D11: 3.65 | E11: gal | F11: 2024 | H11: =CAPEX!N$3/389.544 -> 1.0332235 | I11: =B11*D11*H11 -> 1340894.4
A12: Diesel - Ocean Water | B12: =CostCalc!B54 -> 711111.11 | C12: gal/yr | D12: 3.65 | E12: gal | F12: 2024 | H12: =CAPEX!N$3/389.544 -> 1.0332235 | I12: =B12*D12*H12 -> 2681788.9
A13: Total: | I13: =SUM(I10:I12) -> 5363577.8
A15: Fixed Operational Cost: Labor
A16: Position | B16: Number Required | C16: Units | D16: 2024 Salary | E16: Total Cost (per year)
A17: Manager | B17: 3 | C17: person | D17: 100000 | E17: =D17*B17 -> 300000
A18: Operator | B18: 5 | C18: person | D18: 75000 | E18: =D18*B18 -> 375000
A19: Driver | B19: 200 | C19: person | D19: 65000 | E19: =D19*B19 -> 13000000
A20: Total: | E20: =SUM(E17:E19) -> 13675000
A24: Inoculum Development
A27: Variable Operating Cost
A28: Input | B28: Value Required | C28: Units | D28: Researched Values | H28: Scaled Cost
D29: Cost | E29: Units | F29: Year | G29: Source | H29: PPI 2024 | I29: Total Cost (per year)
A30: Pump Power - Cumulative | D30: 0.178 | E30: kWh | F30: 2024 | H30: =CAPEX!N$3/389.544 -> 1.0332235
A31: Mixing Power - Cumulative | D31: 0.178 | E31: kWh | F31: 2024 | H31: =CAPEX!N$3/389.544 -> 1.0332235
A32: Heat - Cumulative | D32: 0.178 | E32: kWh | F32: 2024 | H32: =CAPEX!N$3/389.544 -> 1.0332235
A33: Culture Broth - Caprociproducens
A34: Acetate | D34: 430 | E34: MT | F34: 2024 | H34: =CAPEX!N$3/389.544 -> 1.0332235
A35: Yeast Extract | D35: =2330/5 -> 466 | E35: kg (5 kg) | F35: 2024 | H35: =CAPEX!N$3/389.544 -> 1.0332235
A36: Trace Minerals - KH2PO4 | D36: =1815.37/25 -> 72.6148 | E36: kg (25 kg) | F36: 2024 | H36: =CAPEX!N$3/389.544 -> 1.0332235
A37: Trace Minerals - MgSO4 | D37: 318.5 | E37: kg | F37: 2024 | H37: =CAPEX!N$3/389.544 -> 1.0332235
A38: Trace Minerals - NaHCO3 | D38: 35.65 | E38: lb | F38: 2024 | H38: =CAPEX!N$3/389.544 -> 1.0332235
A39: Phosphate Buffer | D39: =130/2.5 -> 52 | E39: L (2.5 L) | F39: 2024 | H39: =CAPEX!N$3/389.544 -> 1.0332235
A40: Culture Broth - Lignocellulose
A41: Cellulose | D41: =595.65/10000 -> 0.059565 | E41: g (10 kg) | F41: 2024 | H41: =CAPEX!N$3/389.544 -> 1.0332235
A42: Yeast Extract | D42: =2330/5 -> 466 | E42: kg (5 kg) | F42: 2024 | H42: =CAPEX!N$3/389.544 -> 1.0332235
A43: Phosphate Buffer | D43: =130/2.5 -> 52 | E43: L (2.5 L) | F43: 2024 | H43: =CAPEX!N$3/389.544 -> 1.0332235
A44: Culture Broth - Clostridium
A45: Glucose | D45: 106 | E45: kg | H45: =CAPEX!N$3/389.544 -> 1.0332235
A46: Yeast Extract | D46: =2330/5 -> 466 | E46: kg (5kg) | F46: 2024 | H46: =CAPEX!N$3/389.544 -> 1.0332235
A47: Trace Minerals - KH2PO4 | D47: =1815.37/25 -> 72.6148 | E47: kg (25 kg) | F47: 2024 | H47: =CAPEX!N$3/389.544 -> 1.0332235
A48: Trace Minerals - MgSO4 | D48: 318.5 | E48: kg | F48: 2024 | H48: =CAPEX!N$3/389.544 -> 1.0332235
A49: Trace Minerals - NaCl | D49: =238/5 -> 47.6 | E49: kg (5 kg) | F49: 2024 | H49: =CAPEX!N$3/389.544 -> 1.0332235
A50: Phosphate Buffer | D50: =130/2.5 -> 52 | E50: L (2.5 L) | F50: 2024 | H50: =CAPEX!N$3/389.544 -> 1.0332235
I51: =B51*D51*H51 -> 0
A52: Total: | I52: =SUM(I51) -> 0
A54: Fixed Operational Cost: Labor
A55: Position | B55: Number Required | C55: Units | D55: 2024 Salary | E55: Total Cost (per year)
A56: PhD | B56: 1 | C56: person | D56: 150000 | E56: =D56*B56 -> 150000
A57: MS / PE | B57: 1 | C57: person | D57: 100000 | E57: =D57*B57 -> 100000
A58: BS | B58: 3 | C58: person | D58: 85000 | E58: =D58*B58 -> 255000
A59: Operator | B59: 5 | C59: person | D59: 70000 | E59: =D59*B59 -> 350000
A60: Total: | E60: =SUM(E56:E59) -> 855000
A63: Ocean Water Processing
A66: Variable Operating Cost
A67: Input | B67: Value Required | C67: Units | D67: Researched Values | H67: Scaled Cost
D68: Cost | E68: Units | F68: Year | G68: Source | H68: PPI 2024 | I68: Total Cost (per year)
A69: Power - Feed Pump | B69: =CostCalc!B160*Inputs!F3 -> 15231.789 | C69: kWh/yr | D69: 0.178 | E69: kWh | F69: 2024 | H69: =CAPEX!N$3/389.544 -> 1.0332235 | I69: =B69*D69*H69 -> 2801.3359
A70: Power - Acid Pump | B70: =CostCalc!B161*Inputs!F$3 -> 1781.5209 | C70: kWh/yr | D70: 0.178 | E70: kWh | F70: 2024 | H70: =CAPEX!N$3/389.544 -> 1.0332235 | I70: =B70*D70*H70 -> 327.64623
A71: Power - Base Pump | B71: =CostCalc!B162*Inputs!F$3 -> 1781.5209 | C71: kWh/yr | D71: 0.178 | E71: kWh | F71: 2024 | H71: =CAPEX!N$3/389.544 -> 1.0332235 | I71: =B71*D71*H71 -> 327.64623
A72: Power - Electrolyte Pump | B72: =CostCalc!B163*Inputs!F$3 -> 1781.5209 | C72: kWh/yr | D72: 0.178 | E72: kWh | F72: 2024 | H72: =CAPEX!N$3/389.544 -> 1.0332235 | I72: =B72*D72*H72 -> 327.64623
A73: Heat - Crystallizer | B73: 0 | C73: kWh/yr | D73: 0.178 | E73: kWh | F73: 2024 | H73: =CAPEX!N$3/389.544 -> 1.0332235 | I73: =B73*D73*H73 -> 0
A74: Power - Applied Voltage/Current | B74: =CostCalc!B164*Inputs!F3 -> 434688 | C74: kWh/yr | D74: 0.178 | E74: kWh | F74: 2024 | H74: =CAPEX!N$3/389.544 -> 1.0332235 | I74: =B74*D74*H74 -> 79945.112
A76: Total: | I76: =SUM(I69:I74) -> 83729.386
A78: Fixed Operational Cost: Labor
A79: Position | B79: Number Required | C79: Units | D79: 2024 Salary | E79: Total Cost (per year)
A80: PhD | B80: 1 | C80: person | D80: 150000 | E80: =D80*B80 -> 150000
A81: MS / PE | B81: 1 | C81: person | D81: 100000 | E81: =D81*B81 -> 100000
A82: BS | B82: 3 | C82: person | D82: 85000 | E82: =D82*B82 -> 255000
A83: Operator | B83: 5 | C83: person | D83: 70000 | E83: =D83*B83 -> 350000
A84: Total: | E84: =SUM(E80:E83) -> 855000
A89: Cheese Whey Processing
A92: Variable Operating Cost
A93: Input | B93: Value Required | C93: Units | D93: Researched Values | H93: Scaled Cost
D94: Cost | E94: Units | F94: Year | G94: Source | H94: PPI 2024 | I94: Total Cost (per year)
A95: Power - Feed Pump | B95: =CostCalc!B213*Inputs!F3 -> 13902.085 | C95: kWh/yr | D95: 0.178 | E95: kWh | F95: 2024 | H95: =CAPEX!N$3/389.544 -> 1.0332235 | I95: =B95*D95*H95 -> 2556.785
A96: Lactase Enzyme | B96: =CostCalc!B210*Inputs!F3 -> 4.7078401e+11 | C96: U/yr | D96: =(177/1500) -> 0.118 | E96: U (1500 U) | F96: 2024 | H96: 1 | I96: =(B96*D96*H96)^0.55 -> 812057.98
A97: Power - Recycle Pump | B97: =CostCalc!B214*Inputs!F3 -> 3208.1735 | C97: kWh/yr | D97: 0.178 | E97: kWh | F97: 2024 | H97: =CAPEX!N$3/389.544 -> 1.0332235 | I97: =B97*D97*H97 -> 590.02731
A98: Heat - Hydrolysis | B98: =CostCalc!B220*Inputs!F3 -> 5109.227 | C98: kWh/yr | D98: 0.178 | E98: kWh | F98: 2024 | H98: =CAPEX!N$3/389.544 -> 1.0332235 | I98: =B98*D98*H98 -> 939.65724
A99: Power - Mixing | B99: =CostCalc!B185*Units!C$65/Units!C$84*Inputs!F$3 -> 933465.02 | C99: kWh/yr | D99: 0.178 | E99: kWh | F99: 2024 | H99: =CAPEX!N$3/389.544 -> 1.0332235 | I99: =B99*D99*H99 -> 171677.08
A100: Power - Feed Pump | B100: =CostCalc!B215*Inputs!F3 -> 2519.4973 | C100: kWh/yr | D100: 0.178 | E100: kWh | F100: 2024 | H100: =CAPEX!N$3/389.544 -> 1.0332235 | I100: =B100*D100*H100 -> 463.37027
A101: Heat - Fermentation | B101: =CostCalc!B222*Inputs!F3 -> 145.97792 | C101: kWh/yr | D101: 0.178 | E101: kWh | F101: 2024 | H101: =CAPEX!N$3/389.544 -> 1.0332235 | I101: =B101*D101*H101 -> 26.84735
A102: Power - Mixing | B102: =CostCalc!B185*Units!C$65/Units!C$84*Inputs!F$3 -> 933465.02 | C102: kWh/yr | D102: 0.178 | E102: kWh | F102: 2024 | H102: =CAPEX!N$3/389.544 -> 1.0332235 | I102: =B102*D102*H102 -> 171677.08
A103: Power - pH Mixing | B103: =CostCalc!B198*Units!C$65/Units!C$84*Inputs!F$3 -> 933471.01 | C103: kWh/yr | D103: 0.178 | E103: kWh | F103: 2024 | H103: =CAPEX!N$3/389.544 -> 1.0332235 | I103: =B103*D103*H103 -> 171678.18
A104: Power - Reverse Osmosis | B104: =CostCalc!B216*Inputs!F3 -> 1813.4019 | C104: kWh/yr | D104: 0.178 | E104: kWh | F104: 2024 | H104: =CAPEX!N$3/389.544 -> 1.0332235 | I104: =B104*D104*H104 -> 333.50959
A105: Total: | I105: =SUM(I95:I104) -> 1332000.5
A107: Fixed Operational Cost: Labor
A108: Position | B108: Number Required | C108: Units | D108: 2024 Salary | E108: Total Cost (per year)
A109: PhD | B109: 1 | C109: person | D109: 150000 | E109: =D109*B109 -> 150000
A110: MS / PE | B110: 1 | C110: person | D110: 100000 | E110: =D110*B110 -> 100000
A111: BS | B111: 3 | C111: person | D111: 85000 | E111: =D111*B111 -> 255000
A112: Operator | B112: 5 | C112: person | D112: 70000 | E112: =D112*B112 -> 350000
A113: Total: | E113: =SUM(E109:E112) -> 855000
A118: Feedstock Preparation
A121: Variable Operating Cost
A122: Input | B122: Value Required | C122: Units | D122: Researched Values | H122: Scaled Cost
D123: Cost | E123: Units | F123: Year | G123: Source | H123: PPI 2024 | I123: Total Cost (per year)
A124: Power - Sand Removal | B124: =CostCalc!B276 -> 202364.68 | C124: kWh/yr | D124: 0.178 | E124: kWh | F124: 2024 | H124: =CAPEX!N$3/389.544 -> 1.0332235 | I124: =B124*D124*H124 -> 37217.653
A125: Power - Water Pump | B125: =CostCalc!B277*Inputs!F3 -> 209.60834 | C125: kWh/yr | D125: 0.178 | E125: kWh | F125: 2024 | H125: =CAPEX!N$3/389.544 -> 1.0332235 | I125: =B125*D125*H125 -> 38.549861
A126: Power - Manure Pump | B126: =CostCalc!B278*Inputs!F3 -> 106.92574 | C126: kWh/yr | D126: 0.178 | E126: kWh | F126: 2024 | H126: =CAPEX!N$3/389.544 -> 1.0332235 | I126: =B126*D126*H126 -> 19.665116
A127: Power - Food Waste Pump | B127: =CostCalc!B279*Inputs!F3 -> 76.154864 | C127: kWh/yr | D127: 0.178 | E127: kWh | F127: 2024 | H127: =CAPEX!N$3/389.544 -> 1.0332235 | I127: =B127*D127*H127 -> 14.005929
A128: Power - Manure Grinder | B128: =CostCalc!B280*Inputs!F3 -> 11931.2 | C128: kWh/yr | D128: 0.178 | E128: kWh | F128: 2024 | H128: =CAPEX!N$3/389.544 -> 1.0332235 | I128: =B128*D128*H128 -> 2194.312
A129: Power - Food Waste Grinder | B129: =CostCalc!B281*Inputs!F3 -> 5965.6 | C129: kWh/yr | D129: 0.178 | E129: kWh | F129: 2024 | H129: =CAPEX!N$3/389.544 -> 1.0332235 | I129: =B129*D129*H129 -> 1097.156
A130: Total: | I130: =SUM(I124:I129) -> 40581.342
...

Sheet Figures
A1: Transportation
B3: Capital Costs | C3: Operational Costs
A4: Boats - Ocean Water | B4: =CAPEX!O11 -> 40000000
A5: Diesel Trucks - Ocean Water | B5: =CAPEX!O12 -> 14555000
A6: Diesel Trucks - Cheese Whey | B6: =CAPEX!O13 -> 12425000
A7: Diesel Trucks - Organic Waste | B7: =CAPEX!O14 -> 15265000
A8: Hydraulic Truck Dump with Scale | B8: =CAPEX!O15 -> 17889360
A9: Diesel - Waste | C9: =OPEX!I10 -> 1340894.4
A10: Diesel - Lactate Concentrate | C10: =OPEX!I11 -> 1340894.4
A11: Diesel - Ocean Water | C11: =OPEX!I12 -> 2681788.9
A12: Labor | C12: =OPEX!E20 -> 13675000
A32: Ocean Water Processing
A34: Equipment Name | B34: Capital Costs | C34: Operational Costs
A35: Feed Pump | B35: =CAPEX!O62 -> 52655.972
A36: Decanter | B36: =CAPEX!O63 -> 3588586.4
A37: Microfiltration | B37: =CAPEX!O64 -> 3774.8245
A38: Anion-Exchange Membrane | B38: =CAPEX!O65 -> 14013.8
A39: Cation-Exchange Membrane | B39: =CAPEX!O66 -> 15327.594
A40: Bipolar-Exchange Membranes | B40: =CAPEX!O67 -> 65029.473
A41: Electrodes | B41: =CAPEX!O68 -> 173415.16
A42: Diluate Tanks | B42: =CAPEX!O69 -> 23242.011
A43: Electrolyte Tank Wall | B43: =CAPEX!O70 -> 6000.882
A44: Concentrate Tank 1 Wall | B44: =CAPEX!O71 -> 6000.882
A45: Concentrate Tank 2 Wall | B45: =CAPEX!O72 -> 6000.882
A46: Peristaltic Pump | B46: =CAPEX!O73 -> 242949.56
... A52: Desalinated Water Storage Tank | B52: =CAPEX!O79 -> 239743.36
A53: Power - Feed Pump | C53: =OPEX!I69 -> 2801.3359
A54: Power - Acid Pump | C54: =OPEX!I70 -> 327.64623
A55: Power - Base Pump | C55: =OPEX!I71 -> 327.64623
A56: Power - Electrolyte Pump | C56: =OPEX!I72 -> 327.64623
A57: Heat - Crystallizer | C57: =OPEX!I73 -> 0
A58: Power - Applied Voltage | C58: =OPEX!I74 -> 79945.112
A59: Labor | C59: =OPEX!E84 -> 855000
A63: Cheese Whey Processing
B65: Capital Costs | C65: Operational Costs
A66: Feed Pump - CW+H2O | B66: =CAPEX!O91 -> 23020.811
A67: Feed Pump - Recycle | B67: =CAPEX!O92 -> 8786.5345
A68: Hydrolysis Tank Wall | B68: =CAPEX!O93 -> 35026.318
A69: Hydrolysis Insulation | B69: =CAPEX!O94 -> 168558.98
A70: Hydrolysis Agitator | B70: =CAPEX!O95 -> 31865.127
A71: Feed Pump | B71: =CAPEX!O96 -> 14198.593
A72: Fermenter Tank Wall | B72: =CAPEX!O97 -> 35026.318
A73: Fermenter Insulation | B73: =CAPEX!O98 -> 68336.748
A74: Fermenter Agitator | B74: =CAPEX!O99 -> 31865.127
A75: Feed Pump | B75: =CAPEX!O100 -> 14198.593
A76: Decanter | B76: =CAPEX!O101 -> 583156.23
A77: Microfiltration | B77: =CAPEX!O102 -> 255678.63
... A84: Purified Water Tank | B84: =CAPEX!O109 -> 169411.25
A85: Power - Feed Pump | C85: =OPEX!I95 -> 2556.785
A86: Beta-Galactosidase | C86: =OPEX!I96 -> 812057.98
A87: Power - Recycle Pump | C87: =OPEX!I97 -> 590.02731
A88: Heat - Hydrolysis | C88: =OPEX!I98 -> 939.65724
A89: Hydrolysis Mixing | C89: =OPEX!I99 -> 171677.08
A90: Power - Feed Pump | C90: =OPEX!I100 -> 463.37027
A91: Heat - Fermentation | C91: =OPEX!I101 -> 26.84735
A92: Fermentation Mixing | C92: =OPEX!I102 -> 171677.08
A93: pH Mixing | C93: =OPEX!I103 -> 171678.18
A94: Power - Reverse Osmosis | C94: =OPEX!I104 -> 333.50959
A95: Labor | C95: =OPEX!E113 -> 855000
A104: Manure Treatment
B106: Capital Costs - Digestion | C106: Capital Cost - Treatment | D106: Operational Costs - Digestion | E106: Operational Costs - Treatment
A107: Sand Removal | B107: =CAPEX!O121 -> 23197007
A108: Tank Wall - Manure | B108: =CAPEX!O122 -> 2322.4683
A109: Insulation - Manure | B109: =CAPEX!O123 -> 576.50486
A110: Agitator - Manure | B110: =CAPEX!O124 -> 1733320
A111: Feed Pump - Manure | B111: =CAPEX!$O$128 -> 3921621.2
A112: Feed Pump - Water | B112: =CAPEX!O130 -> 135958.67
A113: Manure Slurry Pump Grinder | B113: =CAPEX!O131 -> 9382.8609
A114: Feed Pump | B114: =CAPEX!O176 -> 45288.607
A115: Syngas Makeup Compressor | B115: =CAPEX!O177 -> 112340.64
A116: Syngas Recycle Compressor | B116: =CAPEX!O178 -> 2539.7796
A117: Digester Tank Wall | B117: =CAPEX!O179 -> 2132518.4
A118: Digester Insulation | B118: =CAPEX!O180 -> 2217819.5
A119: Digester Gas Cover | B119: =CAPEX!O181 -> 16000.982
A120: Agitator | B120: =CAPEX!O182 -> 4402632.7
A121: Electrodes | B121: =CAPEX!O183 -> 11155251
A122: Feed Pump | C122: =CAPEX!O193 -> 45288.607
A123: Centrifuge | C123: =CAPEX!O194 -> 25022970
A124: Biosolids Drier | C124: =CAPEX!O195 -> 2426574.1
A125: Microfiltration | C125: =CAPEX!O196 -> 3760.7794
A126: Feed Pump | C126: =CAPEX!O206 -> 52460.054
A127: Air Compressor | C127: =CAPEX!O207 -> 18031375
A128: Caustic Pump | C128: =CAPEX!O208 -> 5712.3662
A129: Absorber Pre-Cooler | C129: =CAPEX!O209 -> 1798744.3
A130: Absorber Column | C130: =CAPEX!O210 -> 4984205.4
A131: Flash Drum | C131: =CAPEX!O211 -> 13341.265
A132: Solvent Circulation Pump | C132: =CAPEX!O212 -> 1665832.2
A133: Lean-rich Heat Exchanger | C133: =CAPEX!O213 -> 1149690
A134: Stripper Column | C134: =CAPEX!O214 -> 2441918
A135: Stripper Reboiler | C135: =CAPEX!O215 -> 986332.07
A136: Stripper OH Condenser | C136: =CAPEX!O216 -> 5447232.3
A137: Stripper Acculumator | C137: =CAPEX!O217 -> 1801803.5
... A141: Crystallizer | C141: =CAPEX!O221 -> 30709654
A142: Power - Grit Removal | D142: =OPEX!I124 -> 37217.653
A143: Power - Water Pump | D143: =OPEX!I125 -> 38.549861
A144: Power - Manure Pump | D144: =OPEX!I126 -> 19.665116
A145: Power - Manure Grinder | D145: =OPEX!$I$128 -> 2194.312
A146: Heat | D146: =OPEX!I180 -> 721.74663
A147: Power - Mixing | D147: =OPEX!I181 -> 625213.14
A148: Power - Feed Pump | D148: =OPEX!I182 -> 2900.0393
...

Sheet A_DCFROR
B2: Economic Inputs | G2: Net Present Values
H3: Portion of MFSP | I3: Expenses | J3: Fraction of Cost
B4: Capital and Operational Costs | G4: Operating Costs | H4: =$D$41*J4 -> 0.85774367 | I4: =D92 -> 6.4211628e+08 | J4: =I4/$I$8 -> 0.71478639
B5: Operational cost | D5: =OPEX!$B$684 -> 69797966 | G5: Equipment and Facilities | H5: =$D$41*J5 -> 0.24812157 | I5: =D93 -> 1.8574652e+08 | J5: =I5/$I$8 -> 0.20676798
B6: Equipment and facilities capital cost | D6: =CAPEX!$B$560 -> 3.8826614e+08 | G6: Taxes | H6: =$D$41*J6 -> 0 | I6: =D91 -> 0 | J6: =I6/$I$8 -> 0
B7: Land capital cost | D7: =D6*0.15 -> 58239921 | G7: Land | H7: =$D$41*J7 -> 0.094134753 | I7: =D89 -> 70470304 | J7: =I7/$I$8 -> 0.078445627
B8: Working capital | D8: =D6*0.05 -> 19413307 | G8: Total | H8: =SUM(H4:H7) -> 1.2 | I8: =SUM(I4:I7) -> 8.983331e+08 | J8: =SUM(J4:J7) -> 1
B10: Loan | G10: Mass Allocation
B11: Equity | D11: 0.4 | G11: Total Product | H11: =SUM(D29:D32) -> 6877297.3 | I11: kg/hr
B12: Loan interest | D12: 0.08 | G12: =B29 -> >90% Ammonia Sulfate | H12: =D29/H$11 -> 0.061950413
B13: Loan term | D13: 10 | G13: =B30 -> >90% Magnesium Sulfate | H13: =D30/H$11 -> 0.026679039
B14: Annual loan payment | D14: =-PMT(D12,D13,D6*(1-D11)) -> 34717862 | G14: =B31 -> Jet Fuel | H14: =D31/H$11 -> 0.89361163
G15: =B32 -> Naphtha | H15: =D32/H$11 -> 0.017758914
B16: Depreciation
B17: MACRS | C17: Years | D17: 7
B19: Construction Period
B20: Construciton period (years) | D20: 3
C21: % yr -2 | D21: 0.1
C22: % yr -1 | D22: 0.5
C23: % yr 0 | D23: 0.4
B25: Productivity
B26: Start up time | C26: Years | D26: 0.5
B27: Start up production | C27: % of full production | D27: 0.5
B29: >90% Ammonia Sulfate | C29: kg/yr | D29: =SUM(ExpBase!$D$623:$D$635)*Inputs!$F$3 -> 426051.41
B30: >90% Magnesium Sulfate | C30: kg/yr | D30: =SUM(ExpBase!$C$623:$C$635)*Inputs!$F$3 -> 183479.68
B31: Jet Fuel | C31: kg/yr | D31: =ExpBase!$C$1151*Inputs!$F$3/1.02 -> 6145632.9
B32: Naphtha | C32: kg/yr | D32: =ExpBase!$C$1150*Inputs!$F$3/1.02 -> 122133.33
B33: Waste Collection | C33: kg/yr | D33: =(ExpBase!$G$126+Inputs!$F$13)*Inputs!$F$3 -> 2.2414277e+08
B35: Internal Rate of Return and Tax Rate
B36: Internal rate of return | D36: 0.1
B37: Tax rate | D37: 0.35
B39: Results
B41: >90% Ammonia Sulfate | C41: per kg | D41: 1.2
B42: >90% Magnesium Sulfate | C42: per kg | D42: 2
B43: MSP Jet Fuel | C43: per kg | D43: 7.33
B44: Naphtha | C44: per kg | D44: 0.85
B45: Waste Collection | C45: per kg | D45: 0.05
B47: Net Present Value | D47: =D86-SUM(E87:G87) -> -6.1829465e+08
B49: Cash flow analysis
B51: Year | E51: -2 | F51: -1 | G51: 0 | H51: 1 | I51: 2 | J51: 3 | K51: 4 | L51: 5 | M51: 6 | N51: 7 | O51: 8 | P51: 9 | Q51: 10 | R51: 11 | S51: 12 | T51: 13 | U51: 14 | V51: 15 | W51: 16 | X51: 17 | Y51: 18 | Z51: 19 | AA51: 20 | AB51: 21 | AC51: 22 | AD51: 23 | AE51: 24 | AF51: 25 | AG51: 26 | AH51: 27 | AI51: 28 | AJ51: 29 | AK51: 30
B52: Equipment and facilities capital | E52: =($D$6*D21*$D$11) -> 15530645 | F52: =($D$6*D22*$D$11) -> 77653227 | G52: =$D$6*D23*$D$11 -> 62122582
B53: Land capital | E53: =D7 -> 58239921
B54: Working capital | G54: =D8 -> 19413307
B56: Loan Payment | E56: =E57 -> 1863677.5 | F56: =F57 -> 11182065 | G56: =G57 -> 18636775 | H56: =D14 -> 34717862 | I56: =IF($D$13>H51,$D$14,0) -> 34717862 | J56: =IF($D$13>I51,$D$14,0) -> 34717862 | K56: =IF($D$13>J51,$D$14,0) -> 34717862 | L56: =IF($D$13>K51,$D$14,0) -> 34717862 | M56: =IF($D$13>L51,$D$14,0) -> 34717862 | N56: =IF($D$13>M51,$D$14,0) -> 34717862 | O56: =IF($D$13>N51,$D$14,0) -> 34717862 | P56: =IF($D$13>O51,$D$14,0) -> 34717862 | ... AK56: =IF($D$13>AJ51,$D$14,0) -> 0
C57: Loan interest payment | E57: =E58*$D$12 -> 1863677.5 | F57: =+F58*$D$12 -> 11182065 | G57: =+G58*$D$12 -> 18636775 | H57: =D6*(1-D11)*D12 -> 18636775 | I57: =+H58*$D$12 -> 17350288 | J57: =+I58*$D$12 -> 15960882 | K57: =+J58*$D$12 -> 14460323 | L57: =+K58*$D$12 -> 12839720 | M57: =+L58*$D$12 -> 11089469 | N57: =+M58*$D$12 -> 9199197.1 | O57: =+N58*$D$12 -> 7157703.9 | P57: =+O58*$D$12 -> 4952891.2 | ... AK57: =+AJ58*$D$12 -> 5.8360379e-08
C58: Loan principle | E58: =$D$6*(1-$D$11)*$D$21 -> 23295968 | F58: =$D$6*(1-$D$11)*$D$22+E58 -> 1.3977581e+08 | G58: =$D$6*(1-$D$11)*$D$23+F58 -> 2.3295968e+08 | H58: =D6*(1-D11)-H56+H57 -> 2.1687859e+08 | I58: =+H58-I56+I57 -> 1.9951102e+08 | J58: =+I58-J56+J57 -> 1.8075404e+08 | K58: =+J58-K56+K57 -> 1.604965e+08 | L58: =+K58-L56+L57 -> 1.3861836e+08 | M58: =+L58-M56+M57 -> 1.1498996e+08 | N58: =+M58-N56+N57 -> 89471298 | O58: =+N58-O56+O57 -> 61911140 | P58: =+O58-P56+P57 -> 32146169 | ... AK58: =+AJ58-AK56+AK57 -> 7.8786511e-07
C60: Total Loan Payent | E60: =E56 -> 1863677.5 | F60: =F56 -> 11182065 | G60: =G56 -> 18636775 | H60: =H56+H59 -> 34717862 | I60: =I56+I59 -> 34717862 | J60: =J56+J59 -> 34717862 | K60: =K56+K59 -> 34717862 | L60: =L56+L59 -> 34717862 | M60: =M56+M59 -> 34717862 | N60: =N56+N59 -> 34717862 | O60: =O56+O59 -> 34717862 | ... R60: =R56+R59 -> 0
B61: Product sales
C62: =B29 -> >90% Ammonia Sulfate | H62: =($D29*$D41)*(1-$D$26)+($D29*$D41)*$D$26*$D$27 -> 383446.27 | I62: =+$D29*$D41 -> 511261.7 | J62: =+$D29*$D41 -> 511261.7 | K62: =+$D29*$D41 -> 511261.7 | L62: =+$D29*$D41 -> 511261.7 | M62: =+$D29*$D41 -> 511261.7 | N62: =+$D29*$D41 -> 511261.7 | O62: =+$D29*$D41 -> 511261.7 | P62: =+$D29*$D41 -> 511261.7 | ... AK62: =+$D29*$D41 -> 511261.7
C63: =B30 -> >90% Magnesium Sulfate | H63: =($D30*$D42)*(1-$D$26)+($D30*$D42)*$D$26*$D$27 -> 275219.52 | I63: =+$D30*$D42 -> 366959.36 | J63: =+$D30*$D42 -> 366959.36 | K63: =+$D30*$D42 -> 366959.36 | L63: =+$D30*$D42 -> 366959.36 | M63: =+$D30*$D42 -> 366959.36 | N63: =+$D30*$D42 -> 366959.36 | O63: =+$D30*$D42 -> 366959.36 | P63: =+$D30*$D42 -> 366959.36 | ... AK63: =+$D30*$D42 -> 366959.36
C64: Jet Fuel | H64: =($D31*$D43)*(1-$D$26)+($D31*$D43)*$D$26*$D$27 -> 33785617 | I64: =+$D31*$D43 -> 45047489 | J64: =+$D31*$D43 -> 45047489 | K64: =+$D31*$D43 -> 45047489 | L64: =+$D31*$D43 -> 45047489 | M64: =+$D31*$D43 -> 45047489 | N64: =+$D31*$D43 -> 45047489 | O64: =+$D31*$D43 -> 45047489 | P64: =+$D31*$D43 -> 45047489 | ... AK64: =+$D31*$D43 -> 45047489
C65: Naphtha | H65: =($D32*$D44)*(1-$D$26)+($D32*$D44)*$D$26*$D$27 -> 77859.998 | I65: =+$D32*$D44 -> 103813.33 | J65: =+$D32*$D44 -> 103813.33 | K65: =+$D32*$D44 -> 103813.33 | L65: =+$D32*$D44 -> 103813.33 | M65: =+$D32*$D44 -> 103813.33 | N65: =+$D32*$D44 -> 103813.33 | O65: =+$D32*$D44 -> 103813.33 | P65: =+$D32*$D44 -> 103813.33 | ... AK65: =+$D32*$D44 -> 103813.33
C66: =B33 -> Waste Collection | H66: =($D33*$D45)*(1-$D$26)+($D33*$D45)*$D$26*$D$27 -> 8405353.9 | I66: =+$D33*$D45 -> 11207138 | J66: =+$D33*$D45 -> 11207138 | K66: =+$D33*$D45 -> 11207138 | L66: =+$D33*$D45 -> 11207138 | M66: =+$D33*$D45 -> 11207138 | N66: =+$D33*$D45 -> 11207138 | O66: =+$D33*$D45 -> 11207138 | P66: =+$D33*$D45 -> 11207138 | ... AK66: =+$D33*$D45 -> 11207138
B68: Total Sales | H68: =SUM(H62:H67) -> 42927497 | I68: =SUM(I62:I67) -> 57236662 | J68: =SUM(J62:J67) -> 57236662 | K68: =SUM(K62:K67) -> 57236662 | L68: =SUM(L62:L67) -> 57236662 | M68: =SUM(M62:M67) -> 57236662 | N68: =SUM(N62:N67) -> 57236662 | O68: =SUM(O62:O67) -> 57236662 | ... AK68: =SUM(AK62:AK67) -> 57236662
B70: Annual costs
C71: Facility | H71: =+D5*(1-$D$26)+D5*$D$26*$D$27 -> 52348474 | I71: =+$D$5 -> 69797966 | J71: =+$D$5 -> 69797966 | K71: =+$D$5 -> 69797966 | L71: =+$D$5 -> 69797966 | M71: =+$D$5 -> 69797966 | N71: =+$D$5 -> 69797966 | O71: =+$D$5 -> 69797966 | P71: =+$D$5 -> 69797966 | ... AK71: =+$D$5 -> 69797966
B73: Total Production Cost | H73: =SUM(H71:H72) -> 52348474 | I73: =SUM(I71:I72) -> 69797966 | J73: =SUM(J71:J72) -> 69797966 | K73: =SUM(K71:K72) -> 69797966 | L73: =SUM(L71:L72) -> 69797966 | M73: =SUM(M71:M72) -> 69797966 | N73: =SUM(N71:N72) -> 69797966 | O73: =SUM(O71:O72) -> 69797966 | ... AK73: =SUM(AK71:AK72) -> 69797966
B75: Depreciation
H76: 0.1429 | I76: 0.2449 | J76: 0.1749 | K76: 0.1249 | L76: 0.0893 | M76: 0.0892 | N76: 0.0893 | O76: 0.0446 | P76: 0 | Q76: 0 | R76: 0 | S76: 0 | T76: 0 | U76: 0 | V76: 0 | W76: 0 | X76: 0 | Y76: 0 | Z76: 0 | AA76: 0 | AB76: 0 | AC76: 0 | AD76: 0 | AE76: 0 | AF76: 0 | AG76: 0 | AH76: 0 | AI76: 0 | AJ76: 0 | AK76: 0
H77: =H$76*$D$6 -> 55483231 | I77: =I$76*$D$6 -> 95086377 | J77: =J$76*$D$6 -> 67907747 | K77: =K$76*$D$6 -> 48494440 | L77: =L$76*$D$6 -> 34672166 | M77: =M$76*$D$6 -> 34633339 | N77: =N$76*$D$6 -> 34672166 | O77: =O$76*$D$6 -> 17316670 | ... AK77: =AK$76*$D$6 -> 0
B79: Net revenue | H79: =+H68-H60-H73-H77 -> -99622071 | I79: =+I68-I60-I73-I77 -> -1.4236554e+08 | J79: =+J68-J60-J73-J77 -> -1.1518691e+08 | K79: =+K68-K60-K73-K77 -> -95773606 | L79: =+L68-L60-L73-L77 -> -81951332 | M79: =+M68-M60-M73-M77 -> -81912505 | N79: =+N68-N60-N73-N77 -> -81951332 | O79: =+O68-O60-O73-O77 -> -64595836 | ... AK79: =+AK68-AK60-AK73-AK77 -> -12561304
B80: Losses forward | H80: 0 | I80: =IF(H81<0,H81,0) -> -99622071 | J80: =IF(I81<0,I81,0) -> -2.4198761e+08 | K80: =IF(J81<0,J81,0) -> -3.5717453e+08 | L80: =IF(K81<0,K81,0) -> -4.5294813e+08 | M80: =IF(L81<0,L81,0) -> -5.3489947e+08 | N80: =IF(M81<0,M81,0) -> -6.1681197e+08 | O80: =IF(N81<0,N81,0) -> -6.987633e+08 | P80: =IF(O81<0,O81,0) -> -7.6335914e+08 | ... AK80: =IF(AJ81<0,AJ81,0) -> -1.0965822e+09
B81: Taxable income | H81: =+H80+H79 -> -99622071 | I81: =+I80+I79 -> -2.4198761e+08 | J81: =+J80+J79 -> -3.5717453e+08 | K81: =+K80+K79 -> -4.5294813e+08 | L81: =+L80+L79 -> -5.3489947e+08 | M81: =+M80+M79 -> -6.1681197e+08 | N81: =+N80+N79 -> -6.987633e+08 | O81: =+O80+O79 -> -7.6335914e+08 | ... AK81: =+AK80+AK79 -> -1.1091435e+09
B82: Income Tax | H82: =IF(H81*($D$37)<0,0,H81*$D$37) -> 0 | I82: =IF(I81*($D$37)<0,0,I81*$D$37) -> 0 | J82: =IF(J81*($D$37)<0,0,J81*$D$37) -> 0 | K82: =IF(K81*($D$37)<0,0,K81*$D$37) -> 0 | L82: =IF(L81*($D$37)<0,0,L81*$D$37) -> 0 | M82: =IF(M81*($D$37)<0,0,M81*$D$37) -> 0 | N82: =IF(N81*($D$37)<0,0,N81*$D$37) -> 0 | O82: =IF(O81*($D$37)<0,0,O81*$D$37) -> 0 | ... AK82: =IF(AK81*($D$37)<0,0,AK81*$D$37) -> 0
B84: Annual Cash Income | H84: =+H68-H60-H73-H82 -> -44138840 | I84: =+I68-I60-I73-I82 -> -47279166 | J84: =+J68-J60-J73-J82 -> -47279166 | K84: =+K68-K60-K73-K82 -> -47279166 | L84: =+L68-L60-L73-L82 -> -47279166 | M84: =+M68-M60-M73-M82 -> -47279166 | N84: =+N68-N60-N73-N82 -> -47279166 | O84: =+O68-O60-O73-O82 -> -47279166 | ... Y84: =+Y68-Y60-Y73-Y82 -> -12561304 | Z84: =+Z68-Z56-Z73-Z82 -> -12561304 | AA84: =+AA68-AA56-AA73-AA82 -> -12561304 | AB84: =+AB68-AB56-AB73-AB82 -> -12561304 | AC84: =+AC68-AC56-AC73-AC82 -> -12561304 | AD84: =+AD68-AD56-AD73-AD82 -> -12561304 | AE84: =+AE68-AE56-AE73-AE82 -> -12561304 | AF84: =+AF68-AF56-AF73-AF82 -> -12561304 | AG84: =+AG68-AG56-AG73-AG82 -> -12561304 | ... AK84: =+AK68-AK56-AK73-AK82 -> -12561304
B85: Discount Factor | E85: =1/(1+$D$36)^E51 -> 1.21 | F85: =1/(1+$D$36)^F51 -> 1.1 | G85: =1/(1+$D$36)^G51 -> 1 | H85: =1/(1+$D$36)^H51 -> 0.90909091 | I85: =1/(1+$D$36)^I51 -> 0.82644628 | J85: =1/(1+$D$36)^J51 -> 0.7513148 | K85: =1/(1+$D$36)^K51 -> 0.68301346 | L85: =1/(1+$D$36)^L51 -> 0.62092132 | ... AK85: =1/(1+$D$36)^AK51 -> 0.057308553
B86: Anuual Present Value | D86: =SUM(H86:AK86) -> -3.2888573e+08 | H86: =+H85*H84 -> -40126218 | I86: =+I85*I84 -> -39073691 | J86: =+J85*J84 -> -35521537 | K86: =+K85*K84 -> -32292306 | L86: =+L85*L84 -> -29356642 | M86: =+M85*M84 -> -26687857 | N86: =+N85*N84 -> -24261688 | O86: =+O85*O84 -> -22056080 | ... AK86: =+AK85*AK84 -> -719870.13
B87: Total Capital Investment + Interest | E87: =+SUM(E52,E57,E53)*E85 -> 91517435 | F87: =+(F52+F57)*F85 -> 97718821 | G87: =+(G52+G57+G54)*G85 -> 1.0017266e+08
B89: NPV Land | D89: =E89 -> 70470304 | E89: =E53*E85 -> 70470304
B90: NPV Total Product Sales | D90: =SUM(H90:AK90) -> 5.2655679e+08 | H90: =H85*H68 -> 39024997 | I90: =I85*I68 -> 47303027 | J90: =J85*J68 -> 43002751 | K90: =K85*K68 -> 39093410 | L90: =L85*L68 -> 35539464 | M90: =M85*M68 -> 32308604 | N90: =N85*N68 -> 29371458 | O90: =O85*O68 -> 26701325 | ... AK90: =AK85*AK68 -> 3280150.3
B91: NPV Tax | D91: =SUM(H91:AK91) -> 0 | H91: =+H85*H82 -> 0 | I91: =+I85*I82 -> 0 | J91: =+J85*J82 -> 0 | K91: =+K85*K82 -> 0 | L91: =+L85*L82 -> 0 | M91: =+M85*M82 -> 0 | N91: =+N85*N82 -> 0 | O91: =+O85*O82 -> 0 | ... AK91: =+AK85*AK82 -> 0
B92: NPV Operating Costs | D92: =SUM(H92:AK92) -> 6.4211628e+08 | H92: =H85*H71 -> 47589522 | I92: =I85*I71 -> 57684269 | J92: =J85*J71 -> 52440245 | K92: =K85*K71 -> 47672950 | L92: =L85*L71 -> 43339045 | M92: =M85*M71 -> 39399132 | N92: =N85*N71 -> 35817393 | O92: =O85*O71 -> 32561266 | ... AK92: =AK85*AK71 -> 4000020.4
B93: NPV Equip and Facilities Capital Costs | D93: =SUM(E93:G93) -> 1.8574652e+08 | E93: =E52*E85 -> 18792081 | F93: =F52*F85 -> 85418550 | G93: =G52*G85+G54*G85 -> 81535889
B94: NPV Coproduct Sales | D94: =SUM(H94:AK94) -> 1.1213602e+08 | H94: =SUM(H62,H63,H65,H66)*H85 -> 8310799.7 | I94: =SUM(I62,I63,I65,I66)*I85 -> 10073697 | J94: =SUM(J62,J63,J65,J66)*J85 -> 9157906 | K94: =SUM(K62,K63,K65,K66)*K85 -> 8325369.1 | L94: =SUM(L62,L63,L65,L66)*L85 -> 7568517.3 | M94: =SUM(M62,M63,M65,M66)*M85 -> 6880470.3 | N94: =SUM(N62,N63,N65,N66)*N85 -> 6254973 | O94: =SUM(O62,O63,O65,O66)*O85 -> 5686339.1 | ... AK94: =SUM(AK62,AK63,AK65,AK66)*AK85 -> 698543.86
B96: NPV Naphtha Sales | D96: =SUM(H96:AK96) -> 4703424.4 | E96: =D96/D94 -> 0.04194392 | H96: =H62*H85 -> 348587.52 | I96: =I62*I85 -> 422530.33 | J96: =J62*J85 -> 384118.48 | K96: =K62*K85 -> 349198.62 | L96: =L62*L85 -> 317453.29 | M96: =M62*M85 -> 288593.9 | N96: =N62*N85 -> 262358.09 | O96: =O62*O85 -> 238507.35 | ... AK96: =AK62*AK85 -> 29299.668
B97: NPV Waste Collection Sales | D97: =SUM(H97:AK97) -> 1.0310166e+08 | E97: =D97/D94 -> 0.91943388 | H97: =H66*H85 -> 7641230.8 | I97: =I66*I85 -> 9262097.9 | J97: =J66*J85 -> 8420089 | K97: =K66*K85 -> 7654626.4 | L97: =L66*L85 -> 6958751.3 | M97: =M66*M85 -> 6326137.5 | N97: =N66*N85 -> 5751034.1 | O97: =O66*O85 -> 5228212.8 | ... AK97: =AK66*AK85 -> 642264.89
B99: Total Net Present Value | D99: =D86-SUM(E87:G87) -> -6.1829465e+08
B102: DCFROR GRAPH
B104: Year | C104: =E51 -> -2 | D104: =F51 -> -1 | E104: =G51 -> 0 | F104: =H51 -> 1 | G104: =I51 -> 2 | H104: =J51 -> 3 | I104: =K51 -> 4 | J104: =L51 -> 5 | ... AI104: =AK51 -> 30
B105: Capital Investment | C105: =SUM(E52:E54)/(10^6) -> 73.770566 | D105: =SUM(F52:F54)/(10^6) -> 77.653227 | E105: =SUM(G52:G54)/(10^6) -> 81.535889
B106: Tax | F106: =H82/(10^6) -> 0 | G106: =I82/(10^6) -> 0 | H106: =J82/(10^6) -> 0 | I106: =K82/(10^6) -> 0 | J106: =L82/(10^6) -> 0 | K106: =M82/(10^6) -> 0 | L106: =N82/(10^6) -> 0 | M106: =O82/(10^6) -> 0 | ... Q106: =S82/(10^6) -> 0 | R106: =T82/(10^6)*-1 -> 0 | S106: =U82/(10^6)*-1 -> 0 | T106: =V82/(10^6)*-1 -> 0 | U106: =W82/(10^6)*-1 -> 0 | V106: =X82/(10^6)*-1 -> 0 | W106: =Y82/(10^6)*-1 -> 0 | X106: =Z82/(10^6)*-1 -> 0 | Y106: =AA82/(10^6)*-1 -> 0 | ... AI106: =AK82/(10^6)*-1 -> 0
B107: Depreciation | E107: =(H77*-1)/10^6 -> -55.483231 | F107: =(I77*-1)/10^6 -> -95.086377 | G107: =(J77*-1)/10^6 -> -67.907747 | H107: =(K77*-1)/10^6 -> -48.49444 | I107: =(L77*-1)/10^6 -> -34.672166 | J107: =(M77*-1)/10^6 -> -34.633339 | K107: =(N77*-1)/10^6 -> -34.672166 | L107: =(O77*-1)/10^6 -> -17.31667 | ... AI107: =(AL77*-1)/10^6 -> 0
B108: Loan Payment | C108: =(E57*-1)/(10^6) -> -1.8636775 | D108: =(F57*-1)/(10^6) -> -11.182065 | E108: =(G57*-1)/(10^6) -> -18.636775 | F108: =(H57*-1)/(10^6) -> -18.636775 | G108: =(I57*-1)/(10^6) -> -17.350288 | H108: =(J57*-1)/(10^6) -> -15.960882 | I108: =(K57*-1)/(10^6) -> -14.460323 | J108: =(L57*-1)/(10^6) -> -12.83972 | ... AI108: =(AK57*-1)/(10^6) -> -5.8360379e-14
B109: Operational Expenses | F109: =(H71*-1)/10^6 -> -52.348474 | G109: =(I71*-1)/10^6 -> -69.797966 | H109: =(J71*-1)/10^6 -> -69.797966 | I109: =(K71*-1)/10^6 -> -69.797966 | J109: =(L71*-1)/10^6 -> -69.797966 | K109: =(M71*-1)/10^6 -> -69.797966 | L109: =(N71*-1)/10^6 -> -69.797966 | M109: =(O71*-1)/10^6 -> -69.797966 | ... AI109: =(AK71*-1)/10^6 -> -69.797966
B110: Revenue | F110: =H86/(10^6) -> -40.126218 | G110: =I86/(10^6) -> -39.073691 | H110: =J86/(10^6) -> -35.521537 | I110: =K86/(10^6) -> -32.292306 | J110: =L86/(10^6) -> -29.356642 | K110: =M86/(10^6) -> -26.687857 | L110: =N86/(10^6) -> -24.261688 | M110: =O86/(10^6) -> -22.05608 | ... AI110: =AK86/(10^6) -> -0.71987013
B111: Net Present Value | F111: =(H86-SUM($E$87:$G$87))/(10^6) -> -329.53514 | G111: =(SUM($H$86:I86)-SUM($E$87:$G$87))/(10^6) -> -368.60883 | H111: =(SUM($H$86:J86)-SUM($E$87:$G$87))/(10^6) -> -404.13037 | I111: =(SUM($H$86:K86)-SUM($E$87:$G$87))/(10^6) -> -436.42267 | J111: =(SUM($H$86:L86)-SUM($E$87:$G$87))/(10^6) -> -465.77931 | K111: =(SUM($H$86:M86)-SUM($E$87:$G$87))/(10^6) -> -492.46717 | L111: =(SUM($H$86:N86)-SUM($E$87:$G$87))/(10^6) -> -516.72886 | M111: =(SUM($H$86:O86)-SUM($E$87:$G$87))/(10^6) -> -538.78494 | N111: =(SUM($H$86:P86)-SUM($E$87:$G$87))/(10^6) -> -558.83592 | ... AI111: =(SUM($H$86:AK86)-SUM($E$87:$G$87))/(10^6) -> -618.29465
B115: MINIMUM SELLING PRICE AS NET PRESENT VALUE
B117: OUTPUTS
B118: Parameter | C118: Unit | D118: Baseline Value
B119: NPV Tax | C119: $ | D119: =D91 -> 0
B120: NPV Operational Cost | C120: $ | D120: =D92 -> 6.4211628e+08
B121: NPV Capital Cost | C121: $ | D121: =D93 -> 1.8574652e+08
B122: NPV Coproduct Sales | C122: $ | D122: =D94 -> 1.1213602e+08
B123: Minimum Selling Price | C123: $/kg | D123: =D43 -> 7.33
B125: Results Analysis
B126: SUM(Tax, OPEX, CAPEX) | C126: $ | D126: =SUM(D119:D121) -> 8.278628e+08
B127: NPV Tax | C127: % | D127: =D119/D$126*(1+D$130) -> 0
B128: NPV Operational Cost | C128: % | D128: =D120/D$126*(1+D$130) -> 0.88069241
B129: NPV Capital Cost | C129: % | D129: =D121/D$126*(1+D$130) -> 0.25476001
B130: NPV Coproduct Sales | C130: % | D130: =D122/D126 -> 0.13545242
...

Sheet B_DCFROR
B2: Economic Inputs | G2: NET PRESENT VALUES
H3: Portion of MFSP | I3: Expenses | J3: Fraction of Cost
B4: Capital and Operational Costs | G4: Operating Costs | H4: =$D$41*J4 -> 0.17315874 | I4: =D92 -> 1.298982e+09 | J4: =I4/$I$8 -> 0.4556809
B5: Operational cost | D5: =SUM(OPEX!$B$694:$B$711) -> 1.4119919e+08 | G5: Equipment and Facilities | H5: =$D$41*J5 -> 0.13340044 | I5: =D93 -> 1.0007278e+09 | J5: =I5/$I$8 -> 0.35105378
B6: Equipment and facilities capital cost | D6: =SUM(CAPEX!$B$578:$B$592) -> 2.0918223e+09 | G6: Taxes | H6: =$D$41*J6 -> 0.022830081 | I6: =D91 -> 1.7126403e+08 | J6: =I6/$I$8 -> 0.060079161
B7: Land capital cost | D7: =D6*0.15 -> 3.1377334e+08 | G7: Land | H7: =$D$41*J7 -> 0.050610742 | I7: =D89 -> 3.7966574e+08 | J7: =I7/$I$8 -> 0.13318616
B8: Working capital | D8: =D6*0.05 -> 1.0459111e+08 | G8: Total | H8: =SUM(H4:H7) -> 0.38 | I8: =SUM(I4:I7) -> 2.8506395e+09 | J8: =SUM(J4:J7) -> 1
B10: Loan
B11: Equity | D11: 0.4
B12: Loan interest | D12: 0.08
B13: Loan term | D13: 10
B14: Annual loan payment | D14: =-PMT(D12,D13,D6*(1-D11)) -> 1.8704592e+08 | G14: Mass Allocation
G15: Total Product | H15: =SUM(D29:D32) -> 2601831.8 | I15: kg/hr
B16: Depreciation | G16: =B29 -> >90% Ammonia Sulfate | H16: =D29/H$15 -> 0.16375056
B17: MACRS | C17: Years | D17: 7 | G17: =B30 -> >90% Magnesium Sulfate | H17: =D30/H$15 -> 0.070519424
G18: =B31 -> Pentyl Caproate | H18: =D31/H$15 -> 0.19550254
B19: Construction Period | G19: =B32 -> Other Pure Esters | H19: =D32/H$15 -> 0.57022748
B20: Construciton period (years) | D20: 3
C21: % yr -2 | D21: 0.1
C22: % yr -1 | D22: 0.5
C23: % yr 0 | D23: 0.4
B25: Productivity
B26: Start up time | C26: Years | D26: 0.5
B27: Start up production | C27: % of full production | D27: 0.5
B29: >90% Ammonia Sulfate | C29: kg/yr | D29: =A_DCFROR!D29 -> 426051.41
B30: >90% Magnesium Sulfate | C30: kg/yr | D30: =A_DCFROR!D30 -> 183479.68
B31: Pentyl Caproate | C31: kg/yr | D31: =ExpBase!$B$2000*Inputs!$F$3 -> 508664.73
B32: Other Pure Esters | C32: kg/yr | D32: =(ExpBase!$B$2009-ExpBase!$B$2000)*Inputs!F3 -> 1483636
B33: Waste Collection | C33: kg/yr | D33: =A_DCFROR!D33 -> 2.2414277e+08
B35: Internal Rate of Return and Tax Rate
B36: Internal rate of return | D36: 0.1
B37: Tax rate | D37: 0.35
B39: Results
B41: >90% Ammonia Sulfate | C41: per kg | D41: 0.38
B42: >90% Magnesium Sulfate | C42: per kg | D42: 1.5
B43: MSP Pentyl Caproate | C43: per kg | D43: 756.75
B44: Other Pure Esters | C44: per kg | D44: 15
B45: Waste Collection | C45: per kg | D45: 0.01
B47: Net Present Value | D47: =D86-SUM(E87:G87) -> -4.081692e+08
B49: Cash flow analysis
B51: Year | E51: -2 | F51: -1 | G51: 0 | H51: 1 | I51: 2 | J51: 3 | K51: 4 | L51: 5 | M51: 6 | N51: 7 | O51: 8 | P51: 9 | Q51: 10 | R51: 11 | S51: 12 | T51: 13 | U51: 14 | V51: 15 | W51: 16 | X51: 17 | Y51: 18 | Z51: 19 | AA51: 20 | AB51: 21 | AC51: 22 | AD51: 23 | AE51: 24 | AF51: 25 | AG51: 26 | AH51: 27 | AI51: 28 | AJ51: 29 | AK51: 30
B52: Equipment and facilities capital | E52: =($D$6*D21*$D$11) -> 83672891 | F52: =($D$6*D22*$D$11) -> 4.1836445e+08 | G52: =$D$6*D23*$D$11 -> 3.3469156e+08
B53: Land capital | E53: =D7 -> 3.1377334e+08
B54: Working capital | G54: =D8 -> 1.0459111e+08
B56: Loan Payment | E56: =E57 -> 10040747 | F56: =F57 -> 60244481 | G56: =G57 -> 1.0040747e+08 | H56: =D14 -> 1.8704592e+08 | I56: =IF($D$13>H51,$D$14,0) -> 1.8704592e+08 | J56: =IF($D$13>I51,$D$14,0) -> 1.8704592e+08 | K56: =IF($D$13>J51,$D$14,0) -> 1.8704592e+08 | L56: =IF($D$13>K51,$D$14,0) -> 1.8704592e+08 | M56: =IF($D$13>L51,$D$14,0) -> 1.8704592e+08 | N56: =IF($D$13>M51,$D$14,0) -> 1.8704592e+08 | O56: =IF($D$13>N51,$D$14,0) -> 1.8704592e+08 | P56: =IF($D$13>O51,$D$14,0) -> 1.8704592e+08 | ... AK56: =IF($D$13>AJ51,$D$14,0) -> 0
C57: Loan interest payment | E57: =E58*$D$12 -> 10040747 | F57: =+F58*$D$12 -> 60244481 | G57: =+G58*$D$12 -> 1.0040747e+08 | H57: =D6*(1-D11)*D12 -> 1.0040747e+08 | I57: =+H58*$D$12 -> 93476393 | J57: =+I58*$D$12 -> 85990830 | K57: =+J58*$D$12 -> 77906423 | L57: =+K58*$D$12 -> 69175263 | M57: =+L58*$D$12 -> 59745610 | N57: =+M58*$D$12 -> 49561586 | O57: =+N58*$D$12 -> 38562839 | P57: =+O58*$D$12 -> 26684192 | ... AK57: =+AJ58*$D$12 -> -8.0386196e-08
C58: Loan principle | E58: =$D$6*(1-$D$11)*$D$21 -> 1.2550934e+08 | F58: =$D$6*(1-$D$11)*$D$22+E58 -> 7.5305602e+08 | G58: =$D$6*(1-$D$11)*$D$23+F58 -> 1.2550934e+09 | H58: =D6*(1-D11)-H56+H57 -> 1.1684549e+09 | I58: =+H58-I56+I57 -> 1.0748854e+09 | J58: =+I58-J56+J57 -> 9.7383029e+08 | K58: =+J58-K56+K57 -> 8.6469079e+08 | L58: =+K58-L56+L57 -> 7.4682013e+08 | M58: =+L58-M56+M57 -> 6.1951982e+08 | N58: =+M58-N56+N57 -> 4.8203548e+08 | O58: =+N58-O56+O57 -> 3.335524e+08 | P58: =+O58-P56+P57 -> 1.7319067e+08 | ... AK58: =+AJ58-AK56+AK57 -> -1.0852137e-06
C60: Total Loan Payent | E60: =E56 -> 10040747 | F60: =F56 -> 60244481 | G60: =G56 -> 1.0040747e+08 | H60: =H56+H59 -> 1.8704592e+08 | I60: =I56+I59 -> 1.8704592e+08 | J60: =J56+J59 -> 1.8704592e+08 | K60: =K56+K59 -> 1.8704592e+08 | L60: =L56+L59 -> 1.8704592e+08 | M60: =M56+M59 -> 1.8704592e+08 | N60: =N56+N59 -> 1.8704592e+08 | O60: =O56+O59 -> 1.8704592e+08 | ... R60: =R56+R59 -> 0
B61: Product sales
C62: =B29 -> >90% Ammonia Sulfate | H62: =($D29*$D41)*(1-$D$26)+($D29*$D41)*$D$26*$D$27 -> 121424.65 | I62: =+$D29*$D41 -> 161899.54 | J62: =+$D29*$D41 -> 161899.54 | K62: =+$D29*$D41 -> 161899.54 | L62: =+$D29*$D41 -> 161899.54 | M62: =+$D29*$D41 -> 161899.54 | N62: =+$D29*$D41 -> 161899.54 | O62: =+$D29*$D41 -> 161899.54 | P62: =+$D29*$D41 -> 161899.54 | ... AK62: =+$D29*$D41 -> 161899.54
C63: =B30 -> >90% Magnesium Sulfate | H63: =($D30*$D42)*(1-$D$26)+($D30*$D42)*$D$26*$D$27 -> 206414.64 | I63: =+$D30*$D42 -> 275219.52 | J63: =+$D30*$D42 -> 275219.52 | K63: =+$D30*$D42 -> 275219.52 | L63: =+$D30*$D42 -> 275219.52 | M63: =+$D30*$D42 -> 275219.52 | N63: =+$D30*$D42 -> 275219.52 | O63: =+$D30*$D42 -> 275219.52 | P63: =+$D30*$D42 -> 275219.52 | ... AK63: =+$D30*$D42 -> 275219.52
C64: =B43 -> MSP Pentyl Caproate | H64: =($D31*$D43)*(1-$D$26)+($D31*$D43)*$D$26*$D$27 -> 2.8869902e+08 | I64: =+$D31*$D43 -> 3.8493203e+08 | J64: =+$D31*$D43 -> 3.8493203e+08 | K64: =+$D31*$D43 -> 3.8493203e+08 | L64: =+$D31*$D43 -> 3.8493203e+08 | M64: =+$D31*$D43 -> 3.8493203e+08 | N64: =+$D31*$D43 -> 3.8493203e+08 | O64: =+$D31*$D43 -> 3.8493203e+08 | P64: =+$D31*$D43 -> 3.8493203e+08 | ... AK64: =+$D31*$D43 -> 3.8493203e+08
C65: =B44 -> Other Pure Esters | H65: =($D32*$D44)*(1-$D$26)+($D32*$D44)*$D$26*$D$27 -> 16690905 | I65: =+$D32*$D44 -> 22254540 | J65: =+$D32*$D44 -> 22254540 | K65: =+$D32*$D44 -> 22254540 | L65: =+$D32*$D44 -> 22254540 | M65: =+$D32*$D44 -> 22254540 | N65: =+$D32*$D44 -> 22254540 | O65: =+$D32*$D44 -> 22254540 | P65: =+$D32*$D44 -> 22254540 | ... AK65: =+$D32*$D44 -> 22254540
C66: =B33 -> Waste Collection | H66: =($D33*$D45)*(1-$D$26)+($D33*$D45)*$D$26*$D$27 -> 1681070.8 | I66: =+$D33*$D45 -> 2241427.7 | J66: =+$D33*$D45 -> 2241427.7 | K66: =+$D33*$D45 -> 2241427.7 | L66: =+$D33*$D45 -> 2241427.7 | M66: =+$D33*$D45 -> 2241427.7 | N66: =+$D33*$D45 -> 2241427.7 | O66: =+$D33*$D45 -> 2241427.7 | P66: =+$D33*$D45 -> 2241427.7 | ... AK66: =+$D33*$D45 -> 2241427.7
B68: Total Sales | H68: =SUM(H62:H67) -> 3.0739884e+08 | I68: =SUM(I62:I67) -> 4.0986512e+08 | J68: =SUM(J62:J67) -> 4.0986512e+08 | K68: =SUM(K62:K67) -> 4.0986512e+08 | L68: =SUM(L62:L67) -> 4.0986512e+08 | M68: =SUM(M62:M67) -> 4.0986512e+08 | N68: =SUM(N62:N67) -> 4.0986512e+08 | O68: =SUM(O62:O67) -> 4.0986512e+08 | ... AK68: =SUM(AK62:AK67) -> 4.0986512e+08
B70: Annual costs
C71: Facility | H71: =+D5*(1-$D$26)+D5*$D$26*$D$27 -> 1.0589939e+08 | I71: =+$D$5 -> 1.4119919e+08 | J71: =+$D$5 -> 1.4119919e+08 | K71: =+$D$5 -> 1.4119919e+08 | L71: =+$D$5 -> 1.4119919e+08 | M71: =+$D$5 -> 1.4119919e+08 | N71: =+$D$5 -> 1.4119919e+08 | O71: =+$D$5 -> 1.4119919e+08 | P71: =+$D$5 -> 1.4119919e+08 | ... AK71: =+$D$5 -> 1.4119919e+08
B73: Total Production Cost | H73: =SUM(H71:H72) -> 1.0589939e+08 | I73: =SUM(I71:I72) -> 1.4119919e+08 | J73: =SUM(J71:J72) -> 1.4119919e+08 | K73: =SUM(K71:K72) -> 1.4119919e+08 | L73: =SUM(L71:L72) -> 1.4119919e+08 | M73: =SUM(M71:M72) -> 1.4119919e+08 | N73: =SUM(N71:N72) -> 1.4119919e+08 | O73: =SUM(O71:O72) -> 1.4119919e+08 | ... AK73: =SUM(AK71:AK72) -> 1.4119919e+08
B75: Depreciation
H76: 0.1429 | I76: 0.2449 | J76: 0.1749 | K76: 0.1249 | L76: 0.0893 | M76: 0.0892 | N76: 0.0893 | O76: 0.0446 | P76: 0 | Q76: 0 | R76: 0 | S76: 0 | T76: 0 | U76: 0 | V76: 0 | W76: 0 | X76: 0 | Y76: 0 | Z76: 0 | AA76: 0 | AB76: 0 | AC76: 0 | AD76: 0 | AE76: 0 | AF76: 0 | AG76: 0 | AH76: 0 | AI76: 0 | AJ76: 0 | AK76: 0
H77: =H$76*$D$6 -> 2.989214e+08 | I77: =I$76*$D$6 -> 5.1228727e+08 | J77: =J$76*$D$6 -> 3.6585972e+08 | K77: =K$76*$D$6 -> 2.612686e+08 | L77: =L$76*$D$6 -> 1.8679973e+08 | M77: =M$76*$D$6 -> 1.8659055e+08 | N77: =N$76*$D$6 -> 1.8679973e+08 | O77: =O$76*$D$6 -> 93295273 | ... AK77: =AK$76*$D$6 -> 0
B79: Net revenue | H79: =+H68-H60-H73-H77 -> -2.8446788e+08 | I79: =+I68-I60-I73-I77 -> -4.3066727e+08 | J79: =+J68-J60-J73-J77 -> -2.8423971e+08 | K79: =+K68-K60-K73-K77 -> -1.796486e+08 | L79: =+L68-L60-L73-L77 -> -1.0517972e+08 | M79: =+M68-M60-M73-M77 -> -1.0497054e+08 | N79: =+N68-N60-N73-N77 -> -1.0517972e+08 | O79: =+O68-O60-O73-O77 -> -11675269 | ... AK79: =+AK68-AK60-AK73-AK77 -> 2.6866593e+08
B80: Losses forward | H80: 0 | I80: =IF(H81<0,H81,0) -> -2.8446788e+08 | J80: =IF(I81<0,I81,0) -> -7.1513515e+08 | K80: =IF(J81<0,J81,0) -> -9.9937486e+08 | L80: =IF(K81<0,K81,0) -> -1.1790235e+09 | M80: =IF(L81<0,L81,0) -> -1.2842032e+09 | N80: =IF(M81<0,M81,0) -> -1.3891737e+09 | O80: =IF(N81<0,N81,0) -> -1.4943535e+09 | P80: =IF(O81<0,O81,0) -> -1.5060287e+09 | ... AK80: =IF(AJ81<0,AJ81,0) -> 0
B81: Taxable income | H81: =+H80+H79 -> -2.8446788e+08 | I81: =+I80+I79 -> -7.1513515e+08 | J81: =+J80+J79 -> -9.9937486e+08 | K81: =+K80+K79 -> -1.1790235e+09 | L81: =+L80+L79 -> -1.2842032e+09 | M81: =+M80+M79 -> -1.3891737e+09 | N81: =+N80+N79 -> -1.4943535e+09 | O81: =+O80+O79 -> -1.5060287e+09 | ... AK81: =+AK80+AK79 -> 2.6866593e+08
B82: Income Tax | H82: =IF(H81*($D$37)<0,0,H81*$D$37) -> 0 | I82: =IF(I81*($D$37)<0,0,I81*$D$37) -> 0 | J82: =IF(J81*($D$37)<0,0,J81*$D$37) -> 0 | K82: =IF(K81*($D$37)<0,0,K81*$D$37) -> 0 | L82: =IF(L81*($D$37)<0,0,L81*$D$37) -> 0 | M82: =IF(M81*($D$37)<0,0,M81*$D$37) -> 0 | N82: =IF(N81*($D$37)<0,0,N81*$D$37) -> 0 | O82: =IF(O81*($D$37)<0,0,O81*$D$37) -> 0 | ... AK82: =IF(AK81*($D$37)<0,0,AK81*$D$37) -> 94033074
B84: Annual Cash Income | H84: =+H68-H60-H73-H82 -> 14453523 | I84: =+I68-I60-I73-I82 -> 81620004 | J84: =+J68-J60-J73-J82 -> 81620004 | K84: =+K68-K60-K73-K82 -> 81620004 | L84: =+L68-L60-L73-L82 -> 81620004 | M84: =+M68-M60-M73-M82 -> 81620004 | N84: =+N68-N60-N73-N82 -> 81620004 | O84: =+O68-O60-O73-O82 -> 81620004 | ... Y84: =+Y68-Y60-Y73-Y82 -> 1.7463285e+08 | Z84: =+Z68-Z56-Z73-Z82 -> 1.7463285e+08 | AA84: =+AA68-AA56-AA73-AA82 -> 1.7463285e+08 | AB84: =+AB68-AB56-AB73-AB82 -> 1.7463285e+08 | AC84: =+AC68-AC56-AC73-AC82 -> 1.7463285e+08 | AD84: =+AD68-AD56-AD73-AD82 -> 1.7463285e+08 | AE84: =+AE68-AE56-AE73-AE82 -> 1.7463285e+08 | AF84: =+AF68-AF56-AF73-AF82 -> 1.7463285e+08 | AG84: =+AG68-AG56-AG73-AG82 -> 1.7463285e+08 | ... AK84: =+AK68-AK56-AK73-AK82 -> 1.7463285e+08
B85: Discount Factor | E85: =1/(1+$D$36)^E51 -> 1.21 | F85: =1/(1+$D$36)^F51 -> 1.1 | G85: =1/(1+$D$36)^G51 -> 1 | H85: =1/(1+$D$36)^H51 -> 0.90909091 | I85: =1/(1+$D$36)^I51 -> 0.82644628 | J85: =1/(1+$D$36)^J51 -> 0.7513148 | K85: =1/(1+$D$36)^K51 -> 0.68301346 | L85: =1/(1+$D$36)^L51 -> 0.62092132 | ... AK85: =1/(1+$D$36)^AK51 -> 0.057308553
B86: Anuual Present Value | D86: =SUM(H86:AK86) -> 1.15105e+09 | H86: =+H85*H84 -> 13139566 | I86: =+I85*I84 -> 67454549 | J86: =+J85*J84 -> 61322317 | K86: =+K85*K84 -> 55747561 | L86: =+L85*L84 -> 50679601 | M86: =+M85*M84 -> 46072365 | N86: =+N85*N84 -> 41883968 | O86: =+O85*O84 -> 38076334 | ... AK86: =+AK85*AK84 -> 10007956
B87: Total Capital Investment + Interest | E87: =+SUM(E52,E57,E53)*E85 -> 4.9305924e+08 | F87: =+(F52+F57)*F85 -> 5.2646983e+08 | G87: =+(G52+G57+G54)*G85 -> 5.3969015e+08
B89: NPV Land | D89: =E89 -> 3.7966574e+08 | E89: =E53*E85 -> 3.7966574e+08
B90: NPV Total Product Sales | D90: =SUM(H90:AK90) -> 3.7706123e+09 | H90: =H85*H68 -> 2.7945349e+08 | I90: =I85*I68 -> 3.387315e+08 | J90: =J85*J68 -> 3.0793773e+08 | K90: =K85*K68 -> 2.7994339e+08 | L90: =L85*L68 -> 2.5449399e+08 | M90: =M85*M68 -> 2.3135817e+08 | N90: =N85*N68 -> 2.1032561e+08 | O90: =O85*O68 -> 1.912051e+08 | ... AK90: =AK85*AK68 -> 23488777
B91: NPV Tax | D91: =SUM(H91:AK91) -> 1.7126403e+08 | H91: =+H85*H82 -> 0 | I91: =+I85*I82 -> 0 | J91: =+J85*J82 -> 0 | K91: =+K85*K82 -> 0 | L91: =+L85*L82 -> 0 | M91: =+M85*M82 -> 0 | N91: =+N85*N82 -> 0 | O91: =+O85*O82 -> 0 | ... AK91: =+AK85*AK82 -> 5388899.4
B92: NPV Operating Costs | D92: =SUM(H92:AK92) -> 1.298982e+09 | H92: =H85*H71 -> 96272177 | I92: =I85*I71 -> 1.1669355e+08 | J92: =J85*J71 -> 1.0608504e+08 | K92: =K85*K71 -> 96440949 | L92: =L85*L71 -> 87673590 | M92: =M85*M71 -> 79703263 | N92: =N85*N71 -> 72457512 | O92: =O85*O71 -> 65870466 | ... AK92: =AK85*AK71 -> 8091921.5
B93: NPV Equip and Facilities Capital Costs | D93: =SUM(E93:G93) -> 1.0007278e+09 | E93: =E52*E85 -> 1.012442e+08 | F93: =F52*F85 -> 4.602009e+08 | G93: =G52*G85+G54*G85 -> 4.3928268e+08
B94: NPV Coproduct Sales | D94: =SUM(H94:AK94) -> 2.2937547e+08 | H94: =SUM(H62,H63,H65,H66)*H85 -> 16999832 | I94: =SUM(I62,I63,I65,I66)*I85 -> 20605857 | J94: =SUM(J62,J63,J65,J66)*J85 -> 18732597 | K94: =SUM(K62,K63,K65,K66)*K85 -> 17029634 | L94: =SUM(L62,L63,L65,L66)*L85 -> 15481485 | M94: =SUM(M62,M63,M65,M66)*M85 -> 14074078 | N94: =SUM(N62,N63,N65,N66)*N85 -> 12794616 | O94: =SUM(O62,O63,O65,O66)*O85 -> 11631469 | ... AK94: =SUM(AK62,AK63,AK65,AK66)*AK85 -> 1428879.1
B96: NPV Naphtha Sales | D96: =SUM(H96:AK96) -> 1489417.7 | E96: =D96/D94 -> 0.0064933611 | H96: =H62*H85 -> 110386.05 | I96: =I62*I85 -> 133801.27 | J96: =J62*J85 -> 121637.52 | K96: =K62*K85 -> 110579.56 | L96: =L62*L85 -> 100526.87 | M96: =M62*M85 -> 91388.068 | N96: =N62*N85 -> 83080.062 | O96: =O62*O85 -> 75527.329 | ... AK96: =AK62*AK85 -> 9278.2283
B97: NPV Waste Collection Sales | D97: =SUM(H97:AK97) -> 20620332 | E97: =D97/D94 -> 0.089897722 | H97: =H66*H85 -> 1528246.2 | I97: =I66*I85 -> 1852419.6 | J97: =J66*J85 -> 1684017.8 | K97: =K66*K85 -> 1530925.3 | L97: =L66*L85 -> 1391750.3 | M97: =M66*M85 -> 1265227.5 | N97: =N66*N85 -> 1150206.8 | O97: =O66*O85 -> 1045642.6 | ... AK97: =AK66*AK85 -> 128452.98
B99: Total Net Present Value | D99: =D86-SUM(E87:G87) -> -4.081692e+08
B103: DCFROR GRAPH
B104: Year | C104: =E51 -> -2 | D104: =F51 -> -1 | E104: =G51 -> 0 | F104: =H51 -> 1 | G104: =I51 -> 2 | H104: =J51 -> 3 | I104: =K51 -> 4 | J104: =L51 -> 5 | ... AI104: =AK51 -> 30
B105: Capital Investment | C105: =SUM(E52:E54)/(10^6) -> 397.44623 | D105: =SUM(F52:F54)/(10^6) -> 418.36445 | E105: =SUM(G52:G54)/(10^6) -> 439.28268
B106: Tax | F106: =H82/(10^6) -> 0 | G106: =I82/(10^6) -> 0 | H106: =J82/(10^6) -> 0 | I106: =K82/(10^6) -> 0 | J106: =L82/(10^6) -> 0 | K106: =M82/(10^6) -> 0 | L106: =N82/(10^6) -> 0 | M106: =O82/(10^6) -> 0 | ... Q106: =S82/(10^6) -> 0 | R106: =T82/(10^6)*-1 -> 0 | S106: =U82/(10^6)*-1 -> 0 | T106: =V82/(10^6)*-1 -> -0.18932225 | U106: =W82/(10^6)*-1 -> -94.033074 | V106: =X82/(10^6)*-1 -> -94.033074 | W106: =Y82/(10^6)*-1 -> -94.033074 | X106: =Z82/(10^6)*-1 -> -94.033074 | Y106: =AA82/(10^6)*-1 -> -94.033074 | ... AI106: =AK82/(10^6)*-1 -> -94.033074
B107: Depreciation | E107: =(H77*-1)/10^6 -> -298.9214 | F107: =(I77*-1)/10^6 -> -512.28727 | G107: =(J77*-1)/10^6 -> -365.85972 | H107: =(K77*-1)/10^6 -> -261.2686 | I107: =(L77*-1)/10^6 -> -186.79973 | J107: =(M77*-1)/10^6 -> -186.59055 | K107: =(N77*-1)/10^6 -> -186.79973 | L107: =(O77*-1)/10^6 -> -93.295273 | ... AI107: =(AL77*-1)/10^6 -> 0
B108: Loan Payment | C108: =(E57*-1)/(10^6) -> -10.040747 | D108: =(F57*-1)/(10^6) -> -60.244481 | E108: =(G57*-1)/(10^6) -> -100.40747 | F108: =(H57*-1)/(10^6) -> -100.40747 | G108: =(I57*-1)/(10^6) -> -93.476393 | H108: =(J57*-1)/(10^6) -> -85.99083 | I108: =(K57*-1)/(10^6) -> -77.906423 | J108: =(L57*-1)/(10^6) -> -69.175263 | ... AI108: =(AK57*-1)/(10^6) -> 8.0386196e-14
B109: Operational Expenses | F109: =(H71*-1)/10^6 -> -105.89939 | G109: =(I71*-1)/10^6 -> -141.19919 | H109: =(J71*-1)/10^6 -> -141.19919 | I109: =(K71*-1)/10^6 -> -141.19919 | J109: =(L71*-1)/10^6 -> -141.19919 | K109: =(M71*-1)/10^6 -> -141.19919 | L109: =(N71*-1)/10^6 -> -141.19919 | M109: =(O71*-1)/10^6 -> -141.19919 | ... AI109: =(AK71*-1)/10^6 -> -141.19919
B110: Revenue | F110: =H86/(10^6) -> 13.139566 | G110: =I86/(10^6) -> 67.454549 | H110: =J86/(10^6) -> 61.322317 | I110: =K86/(10^6) -> 55.747561 | J110: =L86/(10^6) -> 50.679601 | K110: =M86/(10^6) -> 46.072365 | L110: =N86/(10^6) -> 41.883968 | M110: =O86/(10^6) -> 38.076334 | ... AI110: =AK86/(10^6) -> 10.007956
B111: Net Present Value | F111: =(H86-SUM($E$87:$G$87))/(10^6) -> -1546.0797 | G111: =(SUM($H$86:I86)-SUM($E$87:$G$87))/(10^6) -> -1478.6251 | H111: =(SUM($H$86:J86)-SUM($E$87:$G$87))/(10^6) -> -1417.3028 | I111: =(SUM($H$86:K86)-SUM($E$87:$G$87))/(10^6) -> -1361.5552 | J111: =(SUM($H$86:L86)-SUM($E$87:$G$87))/(10^6) -> -1310.8756 | K111: =(SUM($H$86:M86)-SUM($E$87:$G$87))/(10^6) -> -1264.8033 | L111: =(SUM($H$86:N86)-SUM($E$87:$G$87))/(10^6) -> -1222.9193 | M111: =(SUM($H$86:O86)-SUM($E$87:$G$87))/(10^6) -> -1184.843 | N111: =(SUM($H$86:P86)-SUM($E$87:$G$87))/(10^6) -> -1150.2281 | ... AI111: =(SUM($H$86:AK86)-SUM($E$87:$G$87))/(10^6) -> -408.1692
B115: MINIMUM SELLING PRICE AS NET PRESENT VALUE
B117: OUTPUTS
B118: Parameter | C118: Unit | D118: Baseline Value
B119: NPV Tax | C119: $ | D119: =D91 -> 1.7126403e+08
B120: NPV Operational Cost | C120: $ | D120: =D92 -> 1.298982e+09
B121: NPV Capital Cost | C121: $ | D121: =D93 -> 1.0007278e+09
B122: NPV Coproduct Sales | C122: $ | D122: =D94 -> 2.2937547e+08
B123: Minimum Selling Price | C123: $/kg | D123: =D43 -> 756.75
B125: Results Analysis
B126: SUM(Tax, OPEX, CAPEX) | C126: $ | D126: =SUM(D119:D121) -> 2.4709738e+09
B127: NPV Tax | C127: % | D127: =D119/D$126*(1+D$130) -> 0.075744277
B128: NPV Operational Cost | C128: % | D128: =D120/D$126*(1+D$130) -> 0.57449571
B129: NPV Capital Cost | C129: % | D129: =D121/D$126*(1+D$130) -> 0.44258798
...

Sheet AB_DCFROR
B2: Economic Inputs | G2: NET PRESENT VALUES
H3: Portion of MFSP | I3: Expenses | J3: Fraction of Cost
B4: Capital and Operational Costs | G4: Operating Costs | H4: =$D$43*J4 -> 0.24414907 | I4: =D99 -> 1.9410983e+09 | J4: =I4/$I$8 -> 0.54255348
B5: Operational cost | D5: =A_DCFROR!D5+B_DCFROR!D5 -> 2.1099716e+08 | G5: Equipment and Facilities | H5: =$D$43*J5 -> 0.14923335 | I5: =D100 -> 1.1864743e+09 | J5: =I5/$I$8 -> 0.33162966
B6: Equipment and facilities capital cost | D6: =A_DCFROR!D6+B_DCFROR!D6 -> 2.4800884e+09 | G6: Taxes | H6: =$D$43*J6 -> 0 | I6: =D98 -> 0 | J6: =I6/$I$8 -> 0
B7: Land capital cost | D7: =D6*0.15 -> 3.7201326e+08 | G7: Land | H7: =$D$43*J7 -> 0.056617585 | I7: =D96 -> 4.5013605e+08 | J7: =I7/$I$8 -> 0.12581686
B8: Working capital | D8: =D6*0.05 -> 1.2400442e+08 | G8: Total | H8: =SUM(H4:H7) -> 0.45 | I8: =SUM(I4:I7) -> 3.5777086e+09 | J8: =SUM(J4:J7) -> 1
B10: Loan | G10: Mass Allocation
B11: Equity | D11: 0.4 | G11: Total Product | H11: =SUM(D29:D32) -> 7486828.4 | I11: kg/hr
B12: Loan interest | D12: 0.08 | G12: =B29 -> >90% Ammonia Sulfate | H12: =D29/H$11 -> 0.11381359
B13: Loan term | D13: 10 | G13: =B30 -> >90% Magnesium Sulfate | H13: =D30/H$11 -> 0.049013994
B14: Annual loan payment | D14: =-PMT(D12,D13,D6*(1-D11)) -> 2.2176378e+08 | G14: =B31 -> Jet Fuel (Hydrocarbon C8-C16) | H14: =D31/H$11 -> 0.82085932
G15: =B32 -> Naphtha (Hydrocarbon <C8) | H15: =D32/H$11 -> 0.016313093
B16: Depreciation
B17: MACRS | C17: Years | D17: 7
B19: Construction Period
B20: Construciton period (years) | D20: 3
C21: % yr -2 | D21: 0.1
C22: % yr -1 | D22: 0.5
C23: % yr 0 | D23: 0.4
B25: Productivity
B26: Start up time | C26: Years | D26: 0.5
B27: Start up production | C27: % of full production | D27: 0.5
B29: >90% Ammonia Sulfate | C29: kg/yr | D29: =SUM(A_DCFROR!D29+B_DCFROR!D29) -> 852102.83
B30: >90% Magnesium Sulfate | C30: kg/yr | D30: =SUM(A_DCFROR!D30,B_DCFROR!D30) -> 366959.36
B31: Jet Fuel (Hydrocarbon C8-C16) | C31: kg/yr | D31: =ExpBase!$C$1151*Inputs!$F$3/1.02 -> 6145632.9
B32: Naphtha (Hydrocarbon <C8) | C32: kg/yr | D32: =ExpBase!$C$1150*Inputs!$F$3/1.02 -> 122133.33
B33: Pentyl Caproate | C33: kg/yr | D33: =B_DCFROR!D31 -> 508664.73
B34: Other Pure Esters | C34: kg/yr | D34: =B_DCFROR!D32 -> 1483636
B35: Waste Collection | C35: kg/yr | D35: =(A_DCFROR!D33+B_DCFROR!D33) -> 4.4828554e+08
B37: Internal Rate of Return and Tax Rate
B38: Internal rate of return | D38: 0.1
B39: Tax rate | D39: 0.35
B41: Results
B43: >90% Ammonia Sulfate | C43: per kg | D43: 0.45
B44: >90% Magnesium Sulfate | C44: per kg | D44: 1.8
B45: MSP Jet Fuel | C45: per kg | D45: 0.8
B46: Naphtha | C46: per kg | D46: 0.65
B47: Pentyl Caproate | C47: per kg | D47: 180
B48: Other Pure Esters | C48: per kg | D48: 145
B49: Waste Collection | C49: per kg | D49: -0.03
B51: Net Present Value | D51: =D93-SUM(E94:G94) -> -2.3991169e+09
B53: Cash flow analysis
B55: Year | E55: -2 | F55: -1 | G55: 0 | H55: 1 | I55: 2 | J55: 3 | K55: 4 | L55: 5 | M55: 6 | N55: 7 | O55: 8 | P55: 9 | Q55: 10 | R55: 11 | S55: 12 | T55: 13 | U55: 14 | V55: 15 | W55: 16 | X55: 17 | Y55: 18 | Z55: 19 | AA55: 20 | AB55: 21 | AC55: 22 | AD55: 23 | AE55: 24 | AF55: 25 | AG55: 26 | AH55: 27 | AI55: 28 | AJ55: 29 | AK55: 30
B56: Equipment and facilities capital | E56: =($D$6*D21*$D$11) -> 99203536 | F56: =($D$6*D22*$D$11) -> 4.9601768e+08 | G56: =$D$6*D23*$D$11 -> 3.9681415e+08
B57: Land capital | E57: =D7 -> 3.7201326e+08
B58: Working capital | G58: =D8 -> 1.2400442e+08
B60: Loan Payment | E60: =E61 -> 11904424 | F60: =F61 -> 71426546 | G60: =G61 -> 1.1904424e+08 | H60: =D14 -> 2.2176378e+08 | I60: =IF($D$13>H55,$D$14,0) -> 2.2176378e+08 | J60: =IF($D$13>I55,$D$14,0) -> 2.2176378e+08 | K60: =IF($D$13>J55,$D$14,0) -> 2.2176378e+08 | L60: =IF($D$13>K55,$D$14,0) -> 2.2176378e+08 | M60: =IF($D$13>L55,$D$14,0) -> 2.2176378e+08 | N60: =IF($D$13>M55,$D$14,0) -> 2.2176378e+08 | O60: =IF($D$13>N55,$D$14,0) -> 2.2176378e+08 | P60: =IF($D$13>O55,$D$14,0) -> 2.2176378e+08 | ... AK60: =IF($D$13>AJ55,$D$14,0) -> 0
C61: Loan interest payment | E61: =E62*$D$12 -> 11904424 | F61: =+F62*$D$12 -> 71426546 | G61: =+G62*$D$12 -> 1.1904424e+08 | H61: =D6*(1-D11)*D12 -> 1.1904424e+08 | I61: =+H62*$D$12 -> 1.1082668e+08 | J61: =+I62*$D$12 -> 1.0195171e+08 | K61: =+J62*$D$12 -> 92366746 | L61: =+K62*$D$12 -> 82014983 | M61: =+L62*$D$12 -> 70835079 | N61: =+M62*$D$12 -> 58760783 | O61: =+N62*$D$12 -> 45720542 | P61: =+O62*$D$12 -> 31637083 | ... AK61: =+AJ62*$D$12 -> 1.4726751e-07
C62: Loan principle | E62: =$D$6*(1-$D$11)*$D$21 -> 1.488053e+08 | F62: =$D$6*(1-$D$11)*$D$22+E62 -> 8.9283183e+08 | G62: =$D$6*(1-$D$11)*$D$23+F62 -> 1.488053e+09 | H62: =D6*(1-D11)-H60+H61 -> 1.3853335e+09 | I62: =+H62-I60+I61 -> 1.2743964e+09 | J62: =+I62-J60+J61 -> 1.1545843e+09 | K62: =+J62-K60+K61 -> 1.0251873e+09 | L62: =+K62-L60+L61 -> 8.8543849e+08 | M62: =+L62-M60+M61 -> 7.3450978e+08 | N62: =+M62-N60+N61 -> 5.7150678e+08 | O62: =+N62-O60+O61 -> 3.9546354e+08 | P62: =+O62-P60+P61 -> 2.0533684e+08 | ... AK62: =+AJ62-AK60+AK61 -> 1.9881114e-06
C64: Total Loan Payent | E64: =E60 -> 11904424 | F64: =F60 -> 71426546 | G64: =G60 -> 1.1904424e+08 | H64: =H60+H63 -> 2.2176378e+08 | I64: =I60+I63 -> 2.2176378e+08 | J64: =J60+J63 -> 2.2176378e+08 | K64: =K60+K63 -> 2.2176378e+08 | L64: =L60+L63 -> 2.2176378e+08 | M64: =M60+M63 -> 2.2176378e+08 | N64: =N60+N63 -> 2.2176378e+08 | O64: =O60+O63 -> 2.2176378e+08 | ... R64: =R60+R63 -> 0
B65: Product sales
C66: =B29 -> >90% Ammonia Sulfate | H66: =($D29*$D43)*(1-$D$26)+($D29*$D43)*$D$26*$D$27 -> 287584.7 | I66: =+$D29*$D43 -> 383446.27 | J66: =+$D29*$D43 -> 383446.27 | K66: =+$D29*$D43 -> 383446.27 | L66: =+$D29*$D43 -> 383446.27 | M66: =+$D29*$D43 -> 383446.27 | N66: =+$D29*$D43 -> 383446.27 | O66: =+$D29*$D43 -> 383446.27 | P66: =+$D29*$D43 -> 383446.27 | ... AK66: =+$D29*$D43 -> 383446.27
C67: =B30 -> >90% Magnesium Sulfate | H67: =($D30*$D44)*(1-$D$26)+($D30*$D44)*$D$26*$D$27 -> 495395.14 | I67: =+$D30*$D44 -> 660526.86 | J67: =+$D30*$D44 -> 660526.86 | K67: =+$D30*$D44 -> 660526.86 | L67: =+$D30*$D44 -> 660526.86 | M67: =+$D30*$D44 -> 660526.86 | N67: =+$D30*$D44 -> 660526.86 | O67: =+$D30*$D44 -> 660526.86 | P67: =+$D30*$D44 -> 660526.86 | ... AK67: =+$D30*$D44 -> 660526.86
C68: Jet Fuel | H68: =($D31*$D45)*(1-$D$26)+($D31*$D45)*$D$26*$D$27 -> 3687379.7 | I68: =+$D31*$D45 -> 4916506.3 | J68: =+$D31*$D45 -> 4916506.3 | K68: =+$D31*$D45 -> 4916506.3 | L68: =+$D31*$D45 -> 4916506.3 | M68: =+$D31*$D45 -> 4916506.3 | N68: =+$D31*$D45 -> 4916506.3 | O68: =+$D31*$D45 -> 4916506.3 | P68: =+$D31*$D45 -> 4916506.3 | ... AK68: =+$D31*$D45 -> 4916506.3
C69: Naphtha | H69: =($D32*$D46)*(1-$D$26)+($D32*$D46)*$D$26*$D$27 -> 59539.998 | I69: =+$D32*$D46 -> 79386.664 | J69: =+$D32*$D46 -> 79386.664 | K69: =+$D32*$D46 -> 79386.664 | L69: =+$D32*$D46 -> 79386.664 | M69: =+$D32*$D46 -> 79386.664 | N69: =+$D32*$D46 -> 79386.664 | O69: =+$D32*$D46 -> 79386.664 | P69: =+$D32*$D46 -> 79386.664 | ... AK69: =+$D32*$D46 -> 79386.664
C70: Pentyl Caproate | H70: =($D33*$D47)*(1-$D$26)+($D33*$D47)*$D$26*$D$27 -> 68669738 | I70: =$D$33*$D$47 -> 91559651 | J70: =$D$33*$D$47 -> 91559651 | K70: =$D$33*$D$47 -> 91559651 | L70: =$D$33*$D$47 -> 91559651 | M70: =$D$33*$D$47 -> 91559651 | N70: =$D$33*$D$47 -> 91559651 | O70: =$D$33*$D$47 -> 91559651 | P70: =$D$33*$D$47 -> 91559651 | ... AK70: =$D$33*$D$47 -> 91559651
C71: Other Esters | H71: =($D34*$D48)*(1-$D$26)+($D34*$D48)*$D$26*$D$27 -> 1.6134542e+08 | I71: =$D$48*$D$34 -> 2.1512722e+08 | J71: =$D$48*$D$34 -> 2.1512722e+08 | K71: =$D$48*$D$34 -> 2.1512722e+08 | L71: =$D$48*$D$34 -> 2.1512722e+08 | M71: =$D$48*$D$34 -> 2.1512722e+08 | N71: =$D$48*$D$34 -> 2.1512722e+08 | O71: =$D$48*$D$34 -> 2.1512722e+08 | P71: =$D$48*$D$34 -> 2.1512722e+08 | ... AK71: =$D$48*$D$34 -> 2.1512722e+08
C72: =B35 -> Waste Collection | H72: =($D35*$D49)*(1-$D$26)+($D35*$D49)*$D$26*$D$27 -> -10086425 | I72: =+$D35*$D49 -> -13448566 | J72: =+$D35*$D49 -> -13448566 | K72: =+$D35*$D49 -> -13448566 | L72: =+$D35*$D49 -> -13448566 | M72: =+$D35*$D49 -> -13448566 | N72: =+$D35*$D49 -> -13448566 | O72: =+$D35*$D49 -> -13448566 | P72: =+$D35*$D49 -> -13448566 | ... AK72: =+$D35*$D49 -> -13448566
B75: Total Sales | H75: =SUM(H66:H74) -> 2.2445863e+08 | I75: =SUM(I66:I74) -> 2.9927817e+08 | J75: =SUM(J66:J74) -> 2.9927817e+08 | K75: =SUM(K66:K74) -> 2.9927817e+08 | L75: =SUM(L66:L74) -> 2.9927817e+08 | M75: =SUM(M66:M74) -> 2.9927817e+08 | N75: =SUM(N66:N74) -> 2.9927817e+08 | O75: =SUM(O66:O74) -> 2.9927817e+08 | ... AK75: =SUM(AK66:AK74) -> 2.9927817e+08
B77: Annual costs
C78: Facility | H78: =+D5*(1-$D$26)+D5*$D$26*$D$27 -> 1.5824787e+08 | I78: =+$D$5 -> 2.1099716e+08 | J78: =+$D$5 -> 2.1099716e+08 | K78: =+$D$5 -> 2.1099716e+08 | L78: =+$D$5 -> 2.1099716e+08 | M78: =+$D$5 -> 2.1099716e+08 | N78: =+$D$5 -> 2.1099716e+08 | O78: =+$D$5 -> 2.1099716e+08 | P78: =+$D$5 -> 2.1099716e+08 | ... AK78: =+$D$5 -> 2.1099716e+08
B80: Total Production Cost | H80: =SUM(H78:H79) -> 1.5824787e+08 | I80: =SUM(I78:I79) -> 2.1099716e+08 | J80: =SUM(J78:J79) -> 2.1099716e+08 | K80: =SUM(K78:K79) -> 2.1099716e+08 | L80: =SUM(L78:L79) -> 2.1099716e+08 | M80: =SUM(M78:M79) -> 2.1099716e+08 | N80: =SUM(N78:N79) -> 2.1099716e+08 | O80: =SUM(O78:O79) -> 2.1099716e+08 | ... AK80: =SUM(AK78:AK79) -> 2.1099716e+08
B82: Depreciation
H83: 0.1429 | I83: 0.2449 | J83: 0.1749 | K83: 0.1249 | L83: 0.0893 | M83: 0.0892 | N83: 0.0893 | O83: 0.0446 | P83: 0 | Q83: 0 | R83: 0 | S83: 0 | T83: 0 | U83: 0 | V83: 0 | W83: 0 | X83: 0 | Y83: 0 | Z83: 0 | AA83: 0 | AB83: 0 | AC83: 0 | AD83: 0 | AE83: 0 | AF83: 0 | AG83: 0 | AH83: 0 | AI83: 0 | AJ83: 0 | AK83: 0
H84: =H$83*$D$6 -> 3.5440463e+08 | I84: =I$83*$D$6 -> 6.0737365e+08 | J84: =J$83*$D$6 -> 4.3376746e+08 | K84: =K$83*$D$6 -> 3.0976304e+08 | L84: =L$83*$D$6 -> 2.2147189e+08 | M84: =M$83*$D$6 -> 2.2122389e+08 | N84: =N$83*$D$6 -> 2.2147189e+08 | O84: =O$83*$D$6 -> 1.1061194e+08 | ... AK84: =AK$83*$D$6 -> 0
B86: Net revenue | H86: =+H75-H64-H80-H84 -> -5.0995766e+08 | I86: =+I75-I64-I80-I84 -> -7.4085642e+08 | J86: =+J75-J64-J80-J84 -> -5.6725023e+08 | K86: =+K75-K64-K80-K84 -> -4.4324581e+08 | L86: =+L75-L64-L80-L84 -> -3.5495467e+08 | M86: =+M75-M64-M80-M84 -> -3.5470666e+08 | N86: =+N75-N64-N80-N84 -> -3.5495467e+08 | O86: =+O75-O64-O80-O84 -> -2.4409471e+08 | ... AK86: =+AK75-AK64-AK80-AK84 -> 88281013
B87: Losses forward | H87: 0 | I87: =IF(H88<0,H88,0) -> -5.0995766e+08 | J87: =IF(I88<0,I88,0) -> -1.2508141e+09 | K87: =IF(J88<0,J88,0) -> -1.8180643e+09 | L87: =IF(K88<0,K88,0) -> -2.2613101e+09 | M87: =IF(L88<0,L88,0) -> -2.6162648e+09 | N87: =IF(M88<0,M88,0) -> -2.9709715e+09 | O87: =IF(N88<0,N88,0) -> -3.3259261e+09 | P87: =IF(O88<0,O88,0) -> -3.5700208e+09 | ... AK87: =IF(AJ88<0,AJ88,0) -> -2.1596471e+09
B88: Taxable income | H88: =+H87+H86 -> -5.0995766e+08 | I88: =+I87+I86 -> -1.2508141e+09 | J88: =+J87+J86 -> -1.8180643e+09 | K88: =+K87+K86 -> -2.2613101e+09 | L88: =+L87+L86 -> -2.6162648e+09 | M88: =+M87+M86 -> -2.9709715e+09 | N88: =+N87+N86 -> -3.3259261e+09 | O88: =+O87+O86 -> -3.5700208e+09 | ... AK88: =+AK87+AK86 -> -2.0713661e+09
B89: Income Tax | H89: =IF(H88*($D$39)<0,0,H88*$D$39) -> 0 | I89: =IF(I88*($D$39)<0,0,I88*$D$39) -> 0 | J89: =IF(J88*($D$39)<0,0,J88*$D$39) -> 0 | K89: =IF(K88*($D$39)<0,0,K88*$D$39) -> 0 | L89: =IF(L88*($D$39)<0,0,L88*$D$39) -> 0 | M89: =IF(M88*($D$39)<0,0,M88*$D$39) -> 0 | N89: =IF(N88*($D$39)<0,0,N88*$D$39) -> 0 | O89: =IF(O88*($D$39)<0,0,O88*$D$39) -> 0 | ... AK89: =IF(AK88*($D$39)<0,0,AK88*$D$39) -> 0
B91: Annual Cash Income | H91: =+H75-H64-H80-H89 -> -1.5555302e+08 | I91: =+I75-I64-I80-I89 -> -1.3348277e+08 | J91: =+J75-J64-J80-J89 -> -1.3348277e+08 | K91: =+K75-K64-K80-K89 -> -1.3348277e+08 | L91: =+L75-L64-L80-L89 -> -1.3348277e+08 | M91: =+M75-M64-M80-M89 -> -1.3348277e+08 | N91: =+N75-N64-N80-N89 -> -1.3348277e+08 | O91: =+O75-O64-O80-O89 -> -1.3348277e+08 | ... Y91: =+Y75-Y64-Y80-Y89 -> 88281013 | Z91: =+Z75-Z60-Z80-Z89 -> 88281013 | AA91: =+AA75-AA60-AA80-AA89 -> 88281013 | AB91: =+AB75-AB60-AB80-AB89 -> 88281013 | AC91: =+AC75-AC60-AC80-AC89 -> 88281013 | AD91: =+AD75-AD60-AD80-AD89 -> 88281013 | AE91: =+AE75-AE60-AE80-AE89 -> 88281013 | AF91: =+AF75-AF60-AF80-AF89 -> 88281013 | AG91: =+AG75-AG60-AG80-AG89 -> 88281013 | ... AK91: =+AK75-AK60-AK80-AK89 -> 88281013
B92: Discount Factor | E92: =1/(1+$D$38)^E55 -> 1.21 | F92: =1/(1+$D$38)^F55 -> 1.1 | G92: =1/(1+$D$38)^G55 -> 1 | H92: =1/(1+$D$38)^H55 -> 0.90909091 | I92: =1/(1+$D$38)^I55 -> 0.82644628 | J92: =1/(1+$D$38)^J55 -> 0.7513148 | K92: =1/(1+$D$38)^K55 -> 0.68301346 | L92: =1/(1+$D$38)^L55 -> 0.62092132 | ... AK92: =1/(1+$D$38)^AK55 -> 0.057308553
B93: Anuual Present Value | D93: =SUM(H93:AK93) -> -5.5048876e+08 | H93: =+H92*H91 -> -1.4141184e+08 | I93: =+I92*I91 -> -1.1031634e+08 | J93: =+J92*J91 -> -1.0028758e+08 | K93: =+K92*K91 -> -91170529 | L93: =+L92*L91 -> -82882299 | M93: =+M92*M91 -> -75347545 | N93: =+N92*N91 -> -68497768 | O93: =+O92*O91 -> -62270698 | ... AK93: =+AK92*AK91 -> 5059257.1
B94: Total Capital Investment + Interest | E94: =+SUM(E56,E61,E57)*E92 -> 5.8457668e+08 | F94: =+(F56+F61)*F92 -> 6.2418865e+08 | G94: =+(G56+G61+G58)*G92 -> 6.3986281e+08
B96: NPV Land | D96: =E96 -> 4.5013605e+08 | E96: =E57*E92 -> 4.5013605e+08
B97: NPV Total Product Sales | D97: =SUM(H97:AK97) -> 2.753252e+09 | H97: =H92*H75 -> 2.040533e+08 | I97: =I92*I75 -> 2.4733733e+08 | J97: =J92*J75 -> 2.2485212e+08 | K97: =K92*K75 -> 2.0441102e+08 | L97: =L92*L75 -> 1.858282e+08 | M97: =M92*M75 -> 1.6893473e+08 | N97: =N92*N75 -> 1.5357702e+08 | O97: =O92*O75 -> 1.3961548e+08 | ... AK97: =AK92*AK75 -> 17151199
B98: NPV Tax | D98: =SUM(H98:AK98) -> 0 | H98: =+H92*H89 -> 0 | I98: =+I92*I89 -> 0 | J98: =+J92*J89 -> 0 | K98: =+K92*K89 -> 0 | L98: =+L92*L89 -> 0 | M98: =+M92*M89 -> 0 | N98: =+N92*N89 -> 0 | O98: =+O92*O89 -> 0 | ... AK98: =+AK92*AK89 -> 0
B99: NPV Operating Costs | D99: =SUM(H99:AK99) -> 1.9410983e+09 | H99: =H92*H78 -> 1.438617e+08 | I99: =I92*I78 -> 1.7437782e+08 | J99: =J92*J78 -> 1.5852529e+08 | K99: =K92*K78 -> 1.441139e+08 | L99: =L92*L78 -> 1.3101263e+08 | M99: =M92*M78 -> 1.191024e+08 | N99: =N92*N78 -> 1.082749e+08 | O99: =O92*O78 -> 98431732 | ... AK99: =AK92*AK78 -> 12091942
B100: NPV Equip and Facilities Capital Costs | D100: =SUM(E100:G100) -> 1.1864743e+09 | E100: =E56*E92 -> 1.2003628e+08 | F100: =F56*F92 -> 5.4561945e+08 | G100: =G56*G92+G58*G92 -> 5.2081857e+08
B101: NPV Coproduct Sales | D101: =SUM(H101:AK101) -> 2.7080219e+09 | H101: =SUM(H66,H67,H69,H70,H71,H72)*H92 -> 2.0070114e+08 | I101: =SUM(I66,I67,I69,I70,I71,I72)*I92 -> 2.432741e+08 | J101: =SUM(J66,J67,J69,J70,J71,J72)*J92 -> 2.2115828e+08 | K101: =SUM(K66,K67,K69,K70,K71,K72)*K92 -> 2.0105298e+08 | L101: =SUM(L66,L67,L69,L70,L71,L72)*L92 -> 1.8277543e+08 | M101: =SUM(M66,M67,M69,M70,M71,M72)*M92 -> 1.6615949e+08 | N101: =SUM(N66,N67,N69,N70,N71,N72)*N92 -> 1.5105408e+08 | O101: =SUM(O66,O67,O69,O70,O71,O72)*O92 -> 1.3732189e+08 | ... AK101: =SUM(AK66,AK67,AK69,AK70,AK71,AK72)*AK92 -> 16869441
B103: NPV Naphtha Sales | D103: =SUM(H103:AK103) -> 3527568.3 | E103: =D103/D101 -> 0.0013026366 | H103: =H66*H92 -> 261440.64 | I103: =I66*I92 -> 316897.75 | J103: =J66*J92 -> 288088.86 | K103: =K66*K92 -> 261898.96 | L103: =L66*L92 -> 238089.97 | M103: =M66*M92 -> 216445.42 | N103: =N66*N92 -> 196768.57 | O103: =O66*O92 -> 178880.52 | ... AK103: =AK66*AK92 -> 21974.751
B104: NPV Waste Collection Sales | D104: =SUM(H104:AK104) -> -1.2372199e+08 | E104: =D104/D101 -> -0.04568722 | H104: =H72*H92 -> -9169476.9 | I104: =I72*I92 -> -11114518 | J104: =J72*J92 -> -10104107 | K104: =K72*K92 -> -9185551.7 | L104: =L72*L92 -> -8350501.5 | M104: =M72*M92 -> -7591365 | N104: =N72*N92 -> -6901240.9 | O104: =O72*O92 -> -6273855.4 | ... AK104: =AK72*AK92 -> -770717.87
B106: Total Net Present Value | D106: =D93-SUM(E94:G94) -> -2.3991169e+09
B109: DCFROR GRAPH
B111: Year | C111: =E55 -> -2 | D111: =F55 -> -1 | E111: =G55 -> 0 | F111: =H55 -> 1 | G111: =I55 -> 2 | H111: =J55 -> 3 | I111: =K55 -> 4 | J111: =L55 -> 5 | ... AI111: =AK55 -> 30
B112: Capital Investment | C112: =SUM(E56:E58)/(10^6) -> 471.2168 | D112: =SUM(F56:F58)/(10^6) -> 496.01768 | E112: =SUM(G56:G58)/(10^6) -> 520.81857
B113: Tax | F113: =H89/(10^6) -> 0 | G113: =I89/(10^6) -> 0 | H113: =J89/(10^6) -> 0 | I113: =K89/(10^6) -> 0 | J113: =L89/(10^6) -> 0 | K113: =M89/(10^6) -> 0 | L113: =N89/(10^6) -> 0 | M113: =O89/(10^6) -> 0 | ... Q113: =S89/(10^6) -> 0 | R113: =T89/(10^6)*-1 -> 0 | S113: =U89/(10^6)*-1 -> 0 | T113: =V89/(10^6)*-1 -> 0 | U113: =W89/(10^6)*-1 -> 0 | V113: =X89/(10^6)*-1 -> 0 | W113: =Y89/(10^6)*-1 -> 0 | X113: =Z89/(10^6)*-1 -> 0 | Y113: =AA89/(10^6)*-1 -> 0 | ... AI113: =AK89/(10^6)*-1 -> 0
B114: Depreciation | E114: =(H84*-1)/10^6 -> -354.40463 | F114: =(I84*-1)/10^6 -> -607.37365 | G114: =(J84*-1)/10^6 -> -433.76746 | H114: =(K84*-1)/10^6 -> -309.76304 | I114: =(L84*-1)/10^6 -> -221.47189 | J114: =(M84*-1)/10^6 -> -221.22389 | K114: =(N84*-1)/10^6 -> -221.47189 | L114: =(O84*-1)/10^6 -> -110.61194 | ... AI114: =(AL84*-1)/10^6 -> 0
B115: Loan Payment | C115: =(E61*-1)/(10^6) -> -11.904424 | D115: =(F61*-1)/(10^6) -> -71.426546 | E115: =(G61*-1)/(10^6) -> -119.04424 | F115: =(H61*-1)/(10^6) -> -119.04424 | G115: =(I61*-1)/(10^6) -> -110.82668 | H115: =(J61*-1)/(10^6) -> -101.95171 | I115: =(K61*-1)/(10^6) -> -92.366746 | J115: =(L61*-1)/(10^6) -> -82.014983 | ... AI115: =(AK61*-1)/(10^6) -> -1.4726751e-13
B116: OPEX | F116: =(H78*-1)/10^6 -> -158.24787 | G116: =(I78*-1)/10^6 -> -210.99716 | H116: =(J78*-1)/10^6 -> -210.99716 | I116: =(K78*-1)/10^6 -> -210.99716 | J116: =(L78*-1)/10^6 -> -210.99716 | K116: =(M78*-1)/10^6 -> -210.99716 | L116: =(N78*-1)/10^6 -> -210.99716 | M116: =(O78*-1)/10^6 -> -210.99716 | ... AI116: =(AK78*-1)/10^6 -> -210.99716
B117: Revenue | F117: =H93/(10^6) -> -141.41184 | G117: =I93/(10^6) -> -110.31634 | H117: =J93/(10^6) -> -100.28758 | I117: =K93/(10^6) -> -91.170529 | J117: =L93/(10^6) -> -82.882299 | K117: =M93/(10^6) -> -75.347545 | L117: =N93/(10^6) -> -68.497768 | M117: =O93/(10^6) -> -62.270698 | ... AI117: =AK93/(10^6) -> 5.0592571
B118: Net Present Value | F118: =(H93-SUM($E$94:$G$94))/(10^6) -> -1990.04 | G118: =(SUM($H$93:I93)-SUM($E$94:$G$94))/(10^6) -> -2100.3563 | H118: =(SUM($H$93:J93)-SUM($E$94:$G$94))/(10^6) -> -2200.6439 | I118: =(SUM($H$93:K93)-SUM($E$94:$G$94))/(10^6) -> -2291.8144 | J118: =(SUM($H$93:L93)-SUM($E$94:$G$94))/(10^6) -> -2374.6967 | K118: =(SUM($H$93:M93)-SUM($E$94:$G$94))/(10^6) -> -2450.0443 | L118: =(SUM($H$93:N93)-SUM($E$94:$G$94))/(10^6) -> -2518.542 | M118: =(SUM($H$93:O93)-SUM($E$94:$G$94))/(10^6) -> -2580.8127 | N118: =(SUM($H$93:P93)-SUM($E$94:$G$94))/(10^6) -> -2637.4225 | ... AI118: =(SUM($H$93:AK93)-SUM($E$94:$G$94))/(10^6) -> -2399.1169
B122: MINIMUM SELLING PRICE AS NET PRESENT VALUE
B124: OUTPUTS
B125: Parameter | C125: Unit | D125: Baseline Value
B126: NPV Tax | C126: $ | D126: =D98 -> 0
B127: NPV Operational Cost | C127: $ | D127: =D99 -> 1.9410983e+09
B128: NPV Capital Cost | C128: $ | D128: =D100 -> 1.1864743e+09
B129: NPV Coproduct Sales | C129: $ | D129: =D101 -> 2.7080219e+09
B130: Minimum Selling Price | C130: $/kg | D130: =D45 -> 0.8
...

Sheet Scale&MVA
A1: ECONOMIES OF SCALE FIGURE
A2: SCALE | B2: Path A - Jet Only | C2: Path AB - Jet & Esters | D2: A | E2: AB
A3: ton/yr
A4: =ROUNDUP(482812,5) -> 482812 | B4: 35.877437 | C4: 95.598886 | D4: =B4 -> 35.877437 | E4: =C4 -> 95.598886
A5: 724218 | B5: 29.470752 | C5: 44.902507 | D5: =B5 -> 29.470752 | E5: =C5 -> 44.902507
A6: 965624 | B6: 26.072423 | C6: 19.916435 | D6: =B6 -> 26.072423 | E6: =C6 -> 19.916435
A7: 1448437 | B7: 22.395543 | C7: -7.6601671 | D7: 24.679666 | E7: =C7 -> -7.6601671
A8: 1931249 | B8: 20.417827 | C8: -23.286908 | D8: =B8 -> 20.417827 | E8: =C8 -> -23.286908
A49: Market Value Analysis Figure
B51: Caproic Acid | C51: Pentanol | D51: Hexanol | E51: Ethyl Caproate | F51: Pentyl Caproate | G51: Hexyl Caproate | H51: Triethanolamine
A52: Kilograms | B52: USD | C52: USD | D52: USD | E52: USD | F52: USD | G52: USD | H52: USD | J52: Market Value: | K52: 1 MT [USD] | L52: 1 kg [USD]
A53: 1 | B53: 205 | C53: 169 | D53: 168 | E53: 171 | F53: 198 | G53: 210 | H53: 220 | J53: Caproic Acid * | K53: =ROUNDUP(B62,2)*1000 -> 8950 | L53: =B53 -> 205
A54: 5 | B54: 55 | C54: 44 | D54: 43 | E54: 48 | F54: 73 | G54: 85 | H54: 70 | J54: Pentanol * | K54: =ROUNDUP(C62,1)*1000 -> 4100 | L54: =C53 -> 169
A55: 10 | B55: 35 | C55: 24 | D55: 23 | E55: 26 | F55: 53 | G55: 65 | H55: 34 | J55: Hexanol | K55: =ROUNDUP(D62,2)*1000 -> 3490 | L55: =D53 -> 168
A56: 50 | B56: 29 | C56: 18 | D56: 17 | E56: 20 | F56: 47 | G56: 59 | H56: 24 | J56: Ethyl Caproate | K56: =ROUNDUP(E62,2)*1000 -> 5010 | L56: =E53 -> 171
A57: 160 | D57: 11 | J57: Pentyl Caproate * | K57: =ROUNDUP(F62,2)*1000 -> 20350 | L57: =F53 -> 198
A58: 170 | C58: 12 | J58: Hexyl Caproate | K58: =ROUNDUP(G62,1)*1000 -> 28600 | L58: =G53 -> 210
A59: 180 | B59: 23 | E59: 14 | F59: 41 | G59: 53 | J59: Triethanolamine | K59: =158.68*(1000)^(-0.469)*1000 -> 6216.1601 | L59: 220
A60: 230 | H60: 16 | J60: Jet Fuel | K60: =88.3/7.46 -> 11.836461 | L60: =2.05/3.79 -> 0.5408971
J61: Diesel Fuel | K61: =180/7.46 -> 24.128686 | L61: =4.5/3.79 -> 1.1873351
A62: 1000 | B62: =134.16*(A62^(-0.392)) -> 8.9458796 | C62: =116.54*A62^(-0.488) -> 4.0038243 | D62: =117.18*A62^(-0.509) -> 3.4821983 | E62: =118.44*A62^(-0.458) -> 5.0060871 | F62: =141.72*A62^(-0.281) -> 20.343756 | G62: =154.2*1000^(-0.244) -> 28.581458

Sheet BM_Flow
A1: STANDARD ANAEROBIC DIGESTION FOR METHANE PRODUCTION
A2: Biogas Production
A3: Parameter | B3: Unit | C3: Value | D3: Unit | E3: Value
A4: Specific Methane Yield of Sewage Sludge | B4: mL CH4 / g VS | C4: 0.07
A5: Specific Methane Yield of Plant Matter | B5: mL CH4 / g VS | C5: 0.3
A6: Specific Methane Yield of Cattle Manure | B6: mL CH4 / g VS | C6: 0.094
A7: Specific Methane Yield of Swine Manure | B7: mL CH4 / g VS | C7: 0.13
A8: Specific Methane Yield of Dairy Manure | B8: mL CH4 / g VS | C8: 0.24
A9: Specific Methane Yield of Co-Digested Food Grease | B9: mL CH4 / g VS | C9: =810.7/1000 -> 0.8107
A10: Specific Methane Yield of Co-Digestated Food Waste 1 | B10: mL CH4 / g VS | C10: =289/1000 -> 0.289
A11: Specific Methane Yield of Co-Digestated Food Waste 2 | B11: mL CH4 / g VS | C11: =241/1000 -> 0.241
A12: Specific Methane Yield of Co-Digestated Food Waste 3 | B12: mL CH4 / g VS | C12: =287.7/1000 -> 0.2877
A13: Specific Methane Yield of Co-Digestated Food Processing Waste 1 | B13: mL CH4 / g VS | C13: =537.8/1000 -> 0.5378
A14: Specific Methane Yield of Co-Digestated Food Processing Waste 2 | B14: mL CH4 / g VS | C14: =237.8/1000 -> 0.2378
A15: Volatile Solids in Manure | B15: g VS/g | C15: =ExpBase!C230 -> 0.20761053
A16: Volatile Solids in Food Waste | B16: g VS/g | C16: =ExpBase!C231 -> 0.3996 | G16: Figure
A17: Total Volatile Solids Influent Flow Rate | B17: g VS /hr | C17: =((Inputs!F13*Inputs!F14*C16)+(Inputs!F13*Inputs!F15*C15))*1000 -> 5670236.8 | H17: L/hr | I17: L/ g VS
A18: Expected Methane Yield Based on Feedstock | B18: L CH4 / g VS | C18: =((AVERAGE(C6,C8)*Inputs!F15*Inputs!F16)+(C7*Inputs!F15*Inputs!F17)+(AVERAGE(C10:C14)*Inputs!F14))/1000 -> 0.000168846 | G18: Total Methane Flow Rate | H18: =C28 -> 957.39681 | I18: =H18/(C$17/1000) -> 0.168846
A19: Total Methane Flow Rate | B19: L CH4 / hr | C19: =C17*C18 -> 957.39681 | G19: Total Carbon Dioxide Flow Rate | H19: =C29 -> 509.58217 | I19: =H19/(C$17/1000) -> 0.089869645
A20: H2S Concentration in Biogas | B20: mg/m3 | C20: 10000 | G20: Total Nitrogen Flow Rate | H20: =C30 -> 77.20942 | I20: =H20/(C$17/1000) -> 0.013616613
A21: Ammonia Concentration in Biogas | B21: mg/m3 | C21: 100 | G21: Hydrogen Sulfide Flow Rate | H21: =C31 -> 17.344942 | I21: =H21/(C$17/1000) -> 0.0030589449
A22: Total Chlorine Concentration in Biogas | B22: mg/m3 | C22: 100
A23: Total Fluorine Concentration in Biogas | B23: mg/m3 | C23: 100 | H23: L/ g VS
A24: Percent Methane in Biogas | B24: %/100 | C24: 0.62 | G24: Methane Yield | H24: 0.168846
A25: Percent Carbon Dioxide in Biogas | B25: %/100 | C25: 0.33 | G25: Carbon Dioxide Yield | H25: 0.089869645
A26: Percent Nitrogen in Biogas | B26: %/100 | C26: 0.05 | G26: Nitrogen Yield | H26: 0.013616613
A27: Total Main Biogas Flow Rate | B27: L/hr | C27: =C17*C18/C24 -> 1544.1884 | D27: m3/hr | E27: =SUM(E28:E30) -> 1734.4942 | F27: ton C/hr | G27: Hydrogen Sulfide Yield | H27: 0.0030589449
A28: Total Methane Flow Rate | B28: L/hr | C28: =C$27*C24 -> 957.39681 | D28: m3/hr | E28: =C28*Units!C29 -> 629.0097 | F28: 0.8783 | G28: Total Flow Rate | H28: =SUM(H18:H21) -> 1561.5333
A29: Total Carbon Dioxide Flow Rate | B29: L/hr | C29: =C$27*C25 -> 509.58217 | D29: m3/hr | E29: =C29*Units!C30 -> 1008.9727
A30: Total Nitrogen Flow Rate | B30: L/hr | C30: =C$27*C26 -> 77.20942 | D30: m3/hr | E30: =C30*Units!C32 -> 96.511775
A31: Hydrogen Sulfide Flow Rate | B31: kg/hr | C31: =E$27*C20*Units!C$80 -> 17.344942 | D31: m3/hr | E31: =C31*Units!C33 -> 23.589121
A32: Ammonia Flow Rate | B32: kg/hr | C32: =E$27*C21*Units!C$80 -> 0.17344942
A33: Total Chlorine Flow Rate | B33: kg/hr | C33: =E$27*C22*Units!C$80 -> 0.17344942
A34: Total Fluorine Flow Rate | B34: kg/hr | C34: =E$27*C23*Units!C$80 -> 0.17344942
A35: TOTAL Biogas Flow Rate | B35: m3/hr | C35: =SUM(E27:E31)^0.95 -> 2322.6766 | D35: =C35*0.15 -> 348.40149 | E35: emissions of stabilized sludge
A38: Methane Production
A39: Parameter | B39: Unit | C39: Value
A40: Researched Water Scrubber Parameters
A41: Electricity Demand | B41: kWh/m3 BG | C41: 0.25
A42: Operation Pressure | B42: bar | C42: 6
A43: Methane Recovery Rate | B43: % | C43: 95
A44: Water Demand | B44: L/d-m3 BG | C44: 3.3
B46: Specific Investment | C46: Upgrading Capacity
B47: euro/m3 capacity | C47: m3/hr raw biogas | D47: euro/m3/hr | E47: USD/m3/hr
B48: 4000 | C48: 250 | D48: =B48/C48 -> 16 | E48: =D48*1.0316 -> 16.5056
B49: 2750 | C49: 750 | D49: =B49/C49 -> 3.6666667 | E49: =D49*1.0316 -> 3.7825333
B50: 1900 | C50: 1250 | D50: =B50/C50 -> 1.52 | E50: =D50*1.0316 -> 1.568032
A52: Equation of Best Fit | B52: =9*10^(-5) -> 9e-05 | C52: x2
B53: -1.005 | C53: x
B54: 2836 | C54: c
A56: Specific Cost Analysis
B57: Specific Upgrading Cost | C57: Cost of kWh | D57: Upgrading Capacity | F57: Specific Cost
A58: Assume | B58: euro cent / kWh | C58: cent/kWh | D58: m3/hr raw biogas | E58: euro/m3/hr | F58: USD/m3/hr
A59: 6 | B59: 1.95 | C59: 18 | D59: 300 | E59: =B59*A$59/D59 -> 0.039 | F59: =E59*1.0316 -> 0.0402324
A60: kWh/m3 biogas | B60: 1.5 | C60: 18 | D60: 700 | E60: =B60*A$59/D60 -> 0.012857143 | F60: =E60*1.0316 -> 0.013263429
B61: 1.2 | C61: 18 | D61: 1200 | E61: =B61*A$59/D61 -> 0.006 | F61: =E61*1.0316 -> 0.0061896
B62: 1.15 | C62: 18 | D62: 1400 | E62: =B62*A$59/D62 -> 0.0049285714 | F62: =E62*1.0316 -> 0.0050843143
E64: Upgrading Capacity | F64: =F57 -> Specific Cost
A65: Equation of Best Fit | B65: 88.556 | C65: A | E65: m3/hr raw biogas | F65: =F58 -> USD/m3/hr
B66: -1.348 | C66: n | E66: 300 | F66: =F59 -> 0.0402324
E67: 700 | F67: =F60 -> 0.013263429
E68: 1200 | F68: =F61 -> 0.0061896
E69: 1400 | F69: =F62 -> 0.0050843143
A72: Liquid Digestate Production
A73: Parameter | B73: Unit | C73: Value | D73: Unit | E73: Value | F73: Unit | G73: Value
A74: Digested Food Waste Total Solids | B74: kg TS/m3 | C74: =ExpBase!C305 -> 340.368
A75: Digested Cattle Manure Total Solids | B75: kg TS/m3 | C75: =ExpBase!C307 -> 140.4228
A76: Digested Pig Manure Total Solids | B76: kg TS/m3 | C76: =ExpBase!C311 -> 140.4228
A77: Total Total Solids in Sludge | B77: kg TS/m3 | C77: =SUM(C74:C76) -> 621.2136
A78: Influent Flow Rate of Sludge | B78: m3/hr | C78: =ExpBase!C261+ExpBase!G261 -> 39.66895
A79: Influent Flow Rate of Total Solids | B79: kg TS / hr | C79: =C78*C77 -> 24642.891
A81: Researched Decanter Centrifuge Performance | B81: Input Digestate | D81: Liquid Output | F81: Solid Output
A82: Total Solids | B82: % | C82: 4.85 | D82: % | E82: 2.31 | F82: % | G82: 27.66
A83: Ash Content | B83: % | C83: 1.46 | D83: % | E83: 0.82 | F83: % | G83: 6.46
A84: Volatile Solids | B84: % | C84: 3.39 | D84: % | E84: 3.39 | F84: % | G84: 21.2
A85: Suspended Solids | B85: mg/L | C85: 35000 | D85: mg/L | E85: 8400 | F85: mg/L
A86: pH | B86: ppm | C86: 7.64 | D86: ppm | E86: 7.94 | F86: ppm | G86: 8.12
A87: Total Nitrogen | B87: kg/mt | C87: 4.08 | D87: kg/mt | E87: 3.49 | F87: kg/mt | G87: 8.15
A88: Ammonium Nitrogen | B88: kg/mt | C88: 2.87 | D88: kg/mt | E88: 2.63 | F88: kg/mt | G88: 4.5
A89: Organic Nitrogen | B89: kg/mt | C89: 1.21 | D89: kg/mt | E89: 0.86 | F89: kg/mt | G89: 3.65
A90: Total Phosphorus | B90: kg/mt | C90: 0.94 | D90: kg/mt | E90: 0.31 | F90: kg/mt | G90: 6.52
A91: Total Sulfur | B91: kg/mt | C91: 0.42 | D91: kg/mt | E91: 0.29 | F91: kg/mt | G91: 1.56
A94: Sodium Hydroxide Addition
A95: Parameter | B95: Unit | C95: Value
A96: NaOH Addition pH 5 to pH 9 | B96: g/L-d | C96: 2.4
A97: NaOH Addition to raise pH by 1 | B97: g/L-d | C97: =C96/(9-5) -> 0.6
A100: Carbon Calculations
B101: Food Waste | C101: Manure
A102: Volatile Solid Flow Rate | B102: =(Inputs!F13*Inputs!F14*C16)*1000 -> 999000 | C102: =(Inputs!F13*Inputs!F15*C15)*1000 -> 4671236.8 | D102: g VS/hr
A103: Methane | B103: =B102*AVERAGE(C10:C14)/1000 -> 318.34134 | C103: =C102*AVERAGE(C6:C8)/1000 -> 722.48463 | D103: L CH4/hr
A104: Biogas | B104: =B103/C24 -> 513.45377 | C104: =C103/C24 -> 1165.2978 | D104: L Biogas/hr
A105: CO2 | B105: =B104*C25 -> 169.43975 | C105: =C104*C25 -> 384.54827 | D105: L CO2/hr
D106: TOTAL
A107: Methane Carbon | B107: =(B103*Units!$C$490)/(Units!$C$37*Units!$C$85) -> 0.085702122 | C107: =(C103*Units!$C$490)/(Units!$C$37*Units!$C$85) -> 0.19450338 | D107: =SUM(B107:C107) -> 0.2802055 | E107: MT/hr
A108: Biogas Carbon | B108: =(B104*Units!$C$490)/(Units!$C$37*Units!$C$85) -> 0.13822923 | C108: =(C104*Units!$C$490)/(Units!$C$37*Units!$C$85) -> 0.31371513 | D108: =SUM(B108:C108) -> 0.45194435 | E108: MT/hr
A109: CO2 Carbon | B109: =(B105*Units!$C$490)/(Units!$C$37*Units!$C$85) -> 0.045615646 | C109: =(C105*Units!$C$490)/(Units!$C$37*Units!$C$85) -> 0.10352599 | D109: =SUM(B109:C109) -> 0.14914164 | E109: MT/hr
A111: Food Waste Biogas | B111: =B108 -> 0.13822923 | C111: MT/hr
A112: Manure Biogas | B112: =C108 -> 0.31371513 | C112: MT/hr
A113: Methane | B113: =D107*0.95 -> 0.26619522 | C113: MT/hr
A114: Off Gas Carbon | B114: =D109+(D107*0.05) -> 0.16315191 | C114: MT/hr

Sheet BM_CAPEX
A1: CAPITAL EXPENSE - BIOMETHANE
A4: Feedstock Transportation
A6: Total Capital Investment
A7: Mechanical Equipment List | F7: Researched Values | K7: Scaled Installed in Current Year Factors | O7: Total Cost
A8: Equipment Name | B8: Size | C8: Unit | D8: Number Required | E8: Material | F8: Cost | G8: Size | H8: Unit | I8: Year | J8: Source | K8: Scaling Exponent | L8: Installation Factor | M8: Size Ratio | N8: PPI 2024
A10: Diesel Trucks | B10: =CAPEX!B14*2 -> 80 | C10: yd3 | D10: =CAPEX!D14 -> 43 | E10: Peterbilt Front Loader | F10: =Inputs!F$844*G10 -> 355000 | G10: 40 | H10: yd3 | I10: 2024 | K10: 1 | L10: 1 | M10: =B10/G10 -> 2 | N10: =CAPEX!N13 -> 1 | O10: =N10*F10*D10*M10 -> 30530000
A11: Hydraulic Truck Dump with Scale | B11: =CAPEX!B15*2 -> 74603.186 | C11: lb/hr | D11: 2 | F11: 80000 | G11: 367.437 | H11: lb/hr | I11: 1998 | K11: 0.6 | L11: 2.47 | M11: =B11/G11 -> 203.03667 | N11: =CAPEX!N15 -> 2.8304219 | O11: =D11*N11*F11*L11*M11^(K11) -> 27115200
A12: Total: | O12: =SUM(O10:O11) -> 57645200
A15: Feedstock Preparation
A17: Mechanical Equipment List | F17: Researched Values | K17: Scaled Installed in Current Year Factors | O17: Total Cost
A18: Equipment Name | B18: Size | C18: Unit | D18: Number Required | E18: Material | F18: Cost | G18: Size | H18: Unit | I18: Year | J18: Source | K18: Scaling Exponent | L18: Installation Factor | M18: Size Ratio | N18: PPI
N19: 2024
A20: Sand Removal - Manure | B20: =CAPEX!B121*2 -> 22306 | C20: cow | D20: 2 | E20: 20'' by 22' Sand-Manure Separtor, 5 hp electric motor | F20: 33000 | G20: 75 | H20: cow | I20: 2003 | K20: 0.9 | L20: 1.5 | M20: =B20/G20 -> 297.41333 | N20: =CAPEX!N121 -> 2.5983602 | O20: =D20*N20*F20*L20*M20^(K20) -> 43287145
A21: Tank Wall - Manure | B21: =CAPEX!B122*2 -> 9.7684828 | C21: m3 | D21: 2 | E21: Concrete | F21: =Inputs!F$847 -> 188.34 | G21: 0.76 | H21: m3 | I21: 2022 | J21: 6 | K21: 0.7 | L21: 1.8 | M21: =B21/G21 -> 12.853267 | N21: =CAPEX!N122 -> 0.93135717 | O21: =D21*N21*F21*L21*M21^(K21) -> 3772.8609
A22: Insulation - Manure | B22: =CAPEX!B123*2 -> 19.536966 | C22: m2 | D22: 2 | E22: Unfaced Fiberglass | F22: =CostCalc!F$714 -> 8.35 | G22: =ROUNDUP(CostCalc!G$714,2) -> 0.1 | H22: m2 | I22: 2022 | J22: 3 | K22: 0.7 | L22: 1.5 | M22: =B22/G22 -> 195.36966 | N22: =CAPEX!N123 -> 0.93135717 | O22: =D22*N22*F22*L22*M22^(K22) -> 936.53491
A23: Agitator - Manure | B23: =CAPEX!B124*2 -> 448.69991 | C23: hp | D23: 2 | E23: 304 Stainless Steel, Fixed Propeller, 3 Impellers, 2 Blades, Motor, Gear drive | F23: 52500 | G23: 30 | H23: hp | I23: 2009 | K23: 1 | L23: 1.5 | M23: =B23/G23 -> 14.956664 | N23: =CAPEX!N124 -> 1.4716124 | O23: =D23*N23*F23*L23*M23^(K23) -> 3466639.9
A24: Tank Wall - Food Waste | B24: =CAPEX!B125*2 -> 3.8338232 | C24: m3 | D24: 2 | E24: Concrete | F24: =Inputs!F$847 -> 188.34 | G24: 0.76 | H24: m3 | I24: 2022 | J24: 6 | K24: 0.7 | L24: 1.8 | M24: =B24/G24 -> 5.0445043 | N24: =CAPEX!N125 -> 0.93135717 | O24: =D24*N24*F24*L24*M24^(K24) -> 1960.353
A25: Insulation - Food Waste | B25: =CAPEX!B126*2 -> 7.6676465 | C25: m2 | D25: 2 | E25: Unfaced Fiberglass | F25: =CostCalc!F$714 -> 8.35 | G25: =ROUNDUP(CostCalc!G$714,2) -> 0.1 | H25: m2 | I25: 2022 | J25: 3 | K25: 0.7 | L25: 1.5 | M25: =B25/G25 -> 76.676465 | N25: =CAPEX!N126 -> 0.93135717 | O25: =D25*N25*F25*L25*M25^(K25) -> 486.61719
A26: Agitator - Food Waste | B26: =CAPEX!B127*2 -> 49.855546 | C26: hp | D26: 2 | E26: 304 Stainless Steel, Fixed Propeller, 3 Impellers, 2 Blades, Motor, Gear drive | F26: 52500 | G26: 30 | H26: hp | I26: 2009 | K26: 1 | L26: 1.5 | M26: =B26/G26 -> 1.6618515 | N26: =CAPEX!N127 -> 1.4716124 | O26: =D26*N26*F26*L26*M26^(K26) -> 385182.22
A27: Feed Pump - Manure | B27: =CAPEX!B128*2 -> 2838.75 | C27: GPM | D27: 2 | E27: Concentrated wastewater pump | F27: 4900 | G27: 7 | H27: GPM | I27: 2013 | K27: 0.8 | L27: 4.31 | M27: =B27/G27 -> 405.53571 | N27: =CAPEX!N128 -> 1.3248387 | O27: =D27*N27*F27*L27*M27^(K27) -> 6827939.1
A28: Feed Pump - Food Waste | B28: =CAPEX!B129*2 -> 315.41667 | C28: GPM | D28: 2 | E28: Concentrated wastewater pump | F28: 4900 | G28: 7 | H28: GPM | I28: 2013 | K28: 0.8 | L28: 4.31 | M28: =B28/G28 -> 45.059524 | N28: =CAPEX!N129 -> 1.3248387 | O28: =D28*N28*F28*L28*M28^(K28) -> 1177323
A29: Feed Pump - Water | B29: =CAPEX!B130*2 -> 788.54167 | C29: GPM | D29: 2 | E29: Clean water pump | F29: 5200 | G29: 140 | H29: GPM | I29: 2013 | K29: 0.8 | L29: 4.31 | M29: =B29/G29 -> 5.6324405 | N29: =CAPEX!N130 -> 1.3248387 | O29: =D29*N29*F29*L29*M29^(K29) -> 236717.8
A30: Manure Slurry Pump Grinder | B30: =CAPEX!B131*2 -> 45000 | C30: kg/hr | D30: 2 | E30: Little Giant Pump | F30: =Inputs!F$845*G30 -> 1170 | G30: =CostCalc!G$237 -> 11700 | H30: kg/hr | I30: 2024 | J30: 1 | K30: 0.8 | L30: 2.3 | M30: =B30/G30 -> 3.8461538 | N30: =CAPEX!N131 -> 1.0332235 | O30: =D30*N30*F30*L30*M30^(K30) -> 16336.51
A31: Food Waste Slurry Pump Grinder | B31: =CAPEX!B132*2 -> 6250 | C31: kg/hr | D31: 2 | E31: Little Giant Pump | F31: =Inputs!F$845*G31 -> 1170 | G31: =CostCalc!G$237 -> 11700 | H31: kg/hr | I31: 2024 | J31: 1 | K31: 0.8 | L31: 2.3 | M31: =B31/G31 -> 0.53418803 | N31: =CAPEX!N132 -> 1.0332235 | O31: =D31*N31*F31*L31*M31^(K31) -> 3367.3889
A33: Total: | O33: =SUM(O20:O31) -> 55407808
A36: Anaerobic Digestion
A38: Total Capital Investment
A39: Mechanical Equipment List | F39: Researched Values | K39: Scaled Installed in Current Year Factors | O39: Total Cost
A40: Equipment Name | B40: Size | C40: Unit | D40: Number Required | E40: Material | F40: Cost | G40: Size | H40: Unit | I40: Year | J40: Source | K40: Scaling Exponent | L40: Installation Factor | M40: Size Ratio | N40: PPI
N41: 2023
A42: Feed Pump | B42: =(CAPEX!B176+CAPEX!B159)*2 -> 62500 | C42: kg/hr | D42: =CAPEX!D176 -> 2 | E42: 316 Stainless Steel | F42: 11358 | G42: 43149 | H42: kg/hr | I42: 2018 | K42: 0.8 | L42: 2.3 | M42: =B42/G42 -> 1.4484693 | N42: =CAPEX!N176 -> 1.2207643 | O42: =N42*L42*F42*D42*(M42)^K42 -> 85786.501
A43: Digester Tank Wall | B43: =(CAPEX!B179+CAPEX!B162)*2 -> 99283.052 | C43: m3 | D43: =CAPEX!D179 -> 2 | E43: Concrete | F43: =CAPEX!F179 -> 188.34 | G43: 0.76 | H43: m3 | I43: 2022 | J43: 2 | K43: 0.7 | L43: 2.6 | M43: =B43/G43 -> 130635.59 | N43: =CAPEX!N179 -> 0.93135717 | O43: =N43*L43*F43*D43*(M43)^K43 -> 3477805.1
A44: Digester Insulation | B44: =(CAPEX!B180+CAPEX!B163)*2 -> 10973.445 | C44: m2 | D44: =CAPEX!D180 -> 2 | E44: Unfaced Fiberglass | F44: =CAPEX!F180 -> 8.35 | G44: 0.09 | H44: m2 | I44: 2022 | J44: 3 | K44: 1 | L44: 2.6 | M44: =B44/G44 -> 121927.17 | N44: =CAPEX!N180 -> 0.93135717 | O44: =N44*D44*L44*F44*(M44^K44) -> 4930677.1
A45: Digester Gas Cover | B45: =(CAPEX!B181+CAPEX!B164)*2 -> 203.28032 | C45: m3 | D45: =CAPEX!D181 -> 2 | E45: Double Membrane Polyvinylidene Fluoride 1.5 mm, Pressure and Volume Sensor | F45: =CAPEX!F181 -> 32000.06 | G45: 1000 | H45: m3 | I45: 2023 | K45: 1 | L45: 2.6 | M45: =B45/G45 -> 0.20328032 | N45: =CAPEX!N181 -> 0.95547906 | O45: =N45*L45*F45*D45*M45^K45 -> 32319.948
A46: Agitator | B46: =(CAPEX!B182+CAPEX!B165)*2 -> 1266.3309 | C46: hp | D46: =CAPEX!D182 -> 2 | E46: Stainless Steel, Fixed Propeller, 3 Impellers, 2 Blades, Motor, Gear drive | F46: =CAPEX!F182 -> 52500 | G46: 30 | H46: hp | I46: 1998 | J46: 4 | K46: 0.5 | L46: 1.5 | M46: =B46/G46 -> 42.211029 | N46: =CAPEX!N182 -> 1.4716124 | O46: =D46*N46*F46*L46*(M46)^K46 -> 1505868.2
A47: Total: | O47: =SUM(O43:O46) -> 9946670.3
A50: Solid-Liquid Separation
A52: Mechanical Equipment List | F52: Researched Values | K52: Scaled Installed in Current Year Factors | O52: Total Cost
A53: Equipment Name | B53: Size | C53: Unit | D53: Number Required | E53: Material | F53: Cost | G53: Size | H53: Unit | I53: Year | J53: Source | K53: Scaling Exponent | L53: Installation Factor | M53: Size Ratio | N53: PPI
N54: 2024
A55: Feed Pump | B55: =CAPEX!B193*2 -> 56250 | C55: kg/hr | D55: 2 | E55: 316 Stainless Steel | F55: 11358 | G55: 43149 | H55: kg/hr | I55: 2018 | K55: 0.8 | L55: 2.3 | M55: =B55/G55 -> 1.3036223 | N55: =CAPEX!N193 -> 1.2207643 | O55: =D55*N55*F55*L55*M55^(K55) -> 78852.045
A56: Centrifuge Separator | B56: =CAPEX!B194*2 -> 56250 | C56: kg/hr | D56: 2 | F56: 8800000 | G56: 98039 | H56: kg/hr | I56: 2000 | K56: 0.6 | L56: 2.3 | M56: =B56/G56 -> 0.57375126 | N56: =CAPEX!N194 -> 1.3076218 | O56: =D56*N56*F56*L56*M56^(K56) -> 37927731
A57: Biosolids Drier | B57: =CAPEX!B195*2 -> 10305 | C57: kg/hr | D57: 2 | E57: Fluidixed bed drier parallel | F57: 555008 | G57: 11526 | H57: kg/hr | I57: 2011 | K57: 0.6 | L57: 2.6 | M57: =B57/G57 -> 0.89406559 | N57: =CAPEX!N195 -> 1.3629732 | O57: =D57*N57*F57*L57*M57^(K57) -> 3677998.5
A58: Total: | O58: =SUM(O55:O57) -> 41684581
A61: Biogas Purification
A63: Total Capital Investment
A64: Mechanical Equipment List | F64: Researched Values | K64: Scaled Installed in Current Year Factors | O64: Total Cost
A65: Equipment Name | B65: Size | C65: Unit | D65: Number Required | E65: Material | F65: Cost | G65: Size | H65: Unit | I65: Year | J65: Source | K65: Scaling Exponent | L65: Installation Factor | M65: Size Ratio | N65: PPI
N66: 2024
A67: Investment Cost | B67: =BM_Flow!C35 -> 2322.6766 | C67: m3/hr | D67: 2 | E67: Accourding to Franhofer IWES, 2012 | F67: =16.5*250 -> 4125 | G67: 250 | H67: m3/hr | I67: 2012 | K67: 0.8 | L67: 2.5 | M67: =B67/G67 -> 9.2907065 | N67: =CAPEX!$N$102 -> 1.2912608 | O67: =D67*N67*F67*L67*M67^(K67) -> 158433.47
A68: Total: | O68: =O67 -> 158433.47
A71: Standard Capital Expense: | O71: =SUM(O68,O58,O47,O33,O12) -> 1.6484269e+08
A73: CAPEX | B73: COST
A74: Transportation | B74: =O12 -> 57645200
A75: Feedstock Preparation | B75: =O33 -> 55407808
A76: Anaerobic Digestion | B76: =O47 -> 9946670.3
A77: Solid-Liquid Separation | B77: =O58 -> 41684581
A78: Bio-Methane Purification | B78: =O68 -> 158433.47
A94: CAPITAL EXPENSE

Sheet BM_OPEX
A1: OPERATIONAL EXPENSE - BIOMETHANE
A5: Feedstock Transportation
A8: Variable Operating Cost
A9: Input | B9: Value Required | C9: Units | D9: Researched Values | H9: Scaled Cost
D10: Cost | E10: Units | F10: Year | G10: Source | H10: PPI 2024 | I10: Total Cost (per year)
A11: Diesel - Waste | B11: =OPEX!B10*2 -> 711111.11 | C11: gal/yr | D11: 3.65 | E11: gal | F11: 2024 | H11: =CAPEX!N$3/389.544 -> 1.0332235 | I11: =B11*D11*H11 -> 2681788.9
A12: Total: | I12: =SUM(I11:I11) -> 2681788.9
A14: Fixed Operational Cost: Labor
A15: Position | B15: Number Required | C15: Units | D15: 2024 Salary | E15: Total Cost (per year)
A16: Manager | B16: =ROUNDUP(OPEX!B17/3,0) -> 1 | C16: person | D16: 100000 | E16: =D16*B16 -> 100000
A17: Operator | B17: =ROUNDUP(OPEX!B18/3,0) -> 2 | C17: person | D17: 75000 | E17: =D17*B17 -> 150000
A18: Driver | B18: =ROUNDUP(OPEX!B19/3,0)*2 -> 134 | C18: person | D18: 65000 | E18: =D18*B18 -> 8710000
A19: Total: | E19: =SUM(E18) -> 8710000
A22: Feedstock Preparation
A25: Variable Operating Cost
A26: Input | B26: Value Required | C26: Units | D26: Researched Values | H26: Scaled Cost
D27: Cost | E27: Units | F27: Year | G27: Source | H27: PPI 2024 | I27: Total Cost (per year)
A28: Power - Sand Removal | B28: =OPEX!B124*2 -> 404729.37 | C28: kWh/yr | D28: 0.178 | E28: kWh | F28: 2024 | H28: =CAPEX!N$3/389.544 -> 1.0332235 | I28: =B28*D28*H28 -> 74435.306
A29: Power - Water Pump | B29: =OPEX!B125*2 -> 419.21667 | C29: kWh/yr | D29: 0.178 | E29: kWh | F29: 2024 | H29: =CAPEX!N$3/389.544 -> 1.0332235 | I29: =B29*D29*H29 -> 77.099721
A30: Power - Manure Pump | B30: =OPEX!B126*2 -> 213.85147 | C30: kWh/yr | D30: 0.178 | E30: kWh | F30: 2024 | H30: =CAPEX!N$3/389.544 -> 1.0332235 | I30: =B30*D30*H30 -> 39.330232
A31: Power - Food Waste Pump | B31: =OPEX!B127*2 -> 152.30973 | C31: kWh/yr | D31: 0.178 | E31: kWh | F31: 2024 | H31: =CAPEX!N$3/389.544 -> 1.0332235 | I31: =B31*D31*H31 -> 28.011857
A32: Power - Manure Grinder | B32: =OPEX!B128*2 -> 23862.4 | C32: kWh/yr | D32: 0.178 | E32: kWh | F32: 2024 | H32: =CAPEX!N$3/389.544 -> 1.0332235 | I32: =B32*D32*H32 -> 4388.6241
A33: Power - Food Waste Grinder | B33: =OPEX!B129*2 -> 11931.2 | C33: kWh/yr | D33: 0.178 | E33: kWh | F33: 2024 | H33: =CAPEX!N$3/389.544 -> 1.0332235 | I33: =B33*D33*H33 -> 2194.312
A34: Total: | I34: =SUM(I28:I33) -> 81162.684
A38: Anaerobic Digestion
M39: NaOH Market Value Analysis
M40: kg NaOH | N40: USD
A41: Variable Operating Cost | M41: 1 | N41: 55
A42: Input | B42: Value Required | C42: Units | D42: Researched Values | H42: Scaled Cost | M42: 25 | N42: =380/25 -> 15.2
D43: Cost | E43: Units | F43: Year | G43: Source | H43: PPI 2024 | I43: Total Cost (per year) | M43: 40 | N43: 12
A44: Heat | B44: =(OPEX!B159+OPEX!B180)*2 -> 8720.8333 | C44: kWh/yr | D44: 0.178 | E44: kWh | F44: 2024 | H44: =CAPEX!N$3/389.544 -> 1.0332235 | I44: =H44*D44*B44 -> 1603.8814
A45: Power - Mixing | B45: =(OPEX!B160+OPEX!B181)*2 -> 7554423.4 | C45: kWh/yr | D45: 0.178 | E45: kWh | F45: 2024 | H45: =CAPEX!N$3/389.544 -> 1.0332235 | I45: =H45*D45*B45 -> 1389362.5
A46: NaOH Addition | B46: =BM_Flow!C97*Inputs!F13*2*Inputs!D170/1000*Inputs!F3 -> 2400000 | C46: kg/yr | D46: 2.48 | E46: kg (2 ton) | F46: 2024 | H46: 1 | I46: =H46*D46*B46 -> 5952000
A47: Power - Digester Pump | B47: =(OPEX!B161+OPEX!B182)*2 -> 35041.05 | C47: kg/yr | D47: 0.178 | E47: kWh | F47: 2024 | H47: =CAPEX!N$3/389.544 -> 1.0332235 | I47: =H47*D47*B47 -> 6444.5317
A48: Total: | I48: =SUM(I44:I47) -> 7349410.9
A50: Fixed Operational Cost: Labor
A51: Position | B51: Number Required | C51: Units | D51: 2024 Salary | E51: Total Cost (per year)
A52: PhD | B52: =ROUNDUP(OPEX!B166/3,0) -> 1 | C52: person | D52: 150000 | E52: =D52*B52 -> 150000
A53: MS / PE | B53: =ROUNDUP(OPEX!B167/3,0) -> 1 | C53: person | D53: 100000 | E53: =D53*B53 -> 100000
A54: BS | B54: =ROUNDUP(OPEX!B168/3,0) -> 2 | C54: person | D54: 85000 | E54: =D54*B54 -> 170000
A55: Operator | B55: =ROUNDUP(OPEX!B169/3,0) -> 2 | C55: person | D55: 70000 | E55: =D55*B55 -> 140000
A56: Total: | E56: =SUM(E52:E55) -> 560000
A60: Solid-Liquid Separation
A63: Variable Operating Cost
A64: Input | B64: Value Required | C64: Units | D64: Researched Values | H64: Scaled Cost
D65: Cost | E65: Units | F65: Year | G65: Source | H65: PPI 2024 | I65: Total Cost (per year)
A66: Power - Centrifuge Decanter | B66: =OPEX!B201*2 -> 763209.39 | C66: kWh/yr | D66: 0.178 | E66: kWh | F66: 2024 | H66: =CAPEX!N$3/389.544 -> 1.0332235 | I66: =H66*D66*B66 -> 140364.72
A67: Power - Feed Pump | B67: =OPEX!B202*2 -> 31536.945 | C67: kWh/yr | D67: 0.178 | E67: kWh | F67: 2024 | H67: =CAPEX!N$3/389.544 -> 1.0332235 | I67: =H67*D67*B67 -> 5800.0786
A68: Waste - Biosolids | B68: =OPEX!B203*2 -> 46314.607 | C68: ton/yr | D68: =3441.6/1000 -> 3.4416 | E68: ton | F68: 2000 | H68: =CAPEX!N$3/307.8 -> 1.3076218 | I68: =H68*D68*B68 -> 208430.15
A69: Total: | I69: =SUM(I66:I68) -> 354594.95
A73: Biogas Purification
A76: Variable Operating Cost
A77: Input | B77: Value Required | C77: Units | D77: Researched Values | H77: Scaled Cost
D78: Cost | E78: Units | F78: Year | G78: Source | H78: PPI 2024 | I78: Total Cost (per year)
A79: Water Demand | B79: =BM_Flow!C44*BM_Flow!E27*1/24*Inputs!F3/1000 -> 1907.9436 | C79: m3/yr | D79: =(6.67+0.067)/2 -> 3.3685 | E79: m3 | F79: 2024 | H79: 1 | I79: =H79*D79*B79 -> 6426.908
A80: Total Energy Demand | B80: =(0.22*BM_Flow!C35/1400*Inputs!F3)*2 -> 5839.8726 | C80: kWh/yr | D80: 0.18 | E80: kWh | F80: 2024 | H80: 1 | I80: =H80*D80*B80 -> 1051.1771 | M80: L | N80: d
A81: Total: | I81: =SUM(I79:I80) -> 7478.0851 | M81: d
A83: Fixed Operational Cost: Labor
A84: Position | B84: Number Required | C84: Units | D84: 2023 Salary | E84: Total Cost (per year)
A85: PhD | B85: 1 | C85: person | D85: 104000 | E85: =D85*B85 -> 104000
A86: MS PE | B86: 1 | C86: person | D86: 97760 | E86: =D86*B86 -> 97760
A87: BS | B87: 2 | C87: person | D87: 81120 | E87: =D87*B87 -> 162240
A88: Operator | B88: 2 | C88: person | D88: 66560 | E88: =D88*B88 -> 133120
A89: Total: | E89: =SUM(E85:E88) -> 497120
A93: Waste Transportation
A96: Variable Operating Cost
A97: Input | B97: Value Required | C97: Units | D97: Researched Values | H97: Scaled Cost
D98: Cost | E98: Units | F98: Year | G98: Source | H98: PPI 2023 | I98: Total Cost (per year)
A99: Tipping Fee | B99: =BM_Flow!C78*0.8*Inputs!F3 -> 253881.28 | C99: ton/yr | D99: 0.3 | E99: ton | F99: 2023 | H99: 1 | I99: =B99*D99*H99 -> 76164.384
A100: Total: | I100: =SUM(I99) -> 76164.384
A103: Overall
A106: Fixed Operating Cost
A107: Input | B107: Value Required | C107: Units | D107: Researched Values | G107: Scaled Cost
D108: Cost | E108: Units | F108: Year | G108: Source | H108: PPI 2024 | I108: Total Cost (per year)
A109: Electricity | D109: 0.178 | E109: kWh | F109: 2024 | H109: =CAPEX!N$3/389.544 -> 1.0332235
A110: Waste Disposal
A111: Chemical Inputs
A112: Labor
A113: Overhead and Benefits | B113: =SUM(E89,E56,E19) -> 9767120 | C113: $/yr | D113: 0.9 | E113: of Employment Cost | I113: =B113*D113 -> 8790408
A114: Plant Maintenance | B114: =BM_CAPEX!O71 -> 1.6484269e+08 | C114: $ | D114: 0.03 | E114: of FCI | I114: =B114*D114 -> 4945280.8
A115: Insurance and Taxes | B115: =B114 -> 1.6484269e+08 | C115: $ | D115: 0.007 | E115: of FCI | I115: =B115*D115 -> 1153898.8
A116: Total: | I116: =SUM(I113:I115) -> 14889588
A119: Standard Operational Expense: | I119: =SUM(I12,E19,I34,I48,E56,I69,I81,E89,I100,I113:I115) -> 35207308
A122: OPEX | B122: COST
A123: Transportation | B123: =I12 -> 2681788.9
A124: Feedstock Preparation | B124: =I34 -> 81162.684
A125: Anaerobic Digestion | B125: =I48 -> 7349410.9
A126: Solid-Liquid Separation | B126: =I69 -> 354594.95
A127: Bio-Methane Purification | B127: =I116 -> 14889588
A128: Labor | B128: =SUM(E19,E56,E89) -> 9767120
A129: Overhead and Benefits | B129: =I113 -> 8790408
A130: Plant Maintenance | B130: =I114 -> 4945280.8
A131: Insurance and Taxes | B131: =I115 -> 1153898.8

Sheet BM_DCFROR
B2: Economic Inputs
B4: Capital and Operational Costs
B5: Operational cost | D5: =BM_OPEX!I119 -> 35207308
B6: Equipment and facilities capital cost | D6: =BM_CAPEX!O71 -> 1.6484269e+08
B7: Land capital cost | D7: =D6*0.15 -> 24726404
B8: Working capital | D8: =D6*0.05 -> 8242134.6
B10: Loan
B11: Equity | D11: 0.4
B12: Loan interest | D12: 0.08
B13: Loan term | D13: 10
B14: Annual loan payment | D14: =-PMT(D12,D13,D6*(1-D11)) -> 14739853
B16: Depreciation
B17: MACRS | C17: Years | D17: 7
B19: Construction Period
B20: Construciton period (years) | D20: 3
C21: % yr -2 | D21: 0.1
C22: % yr -1 | D22: 0.5
C23: % yr 0 | D23: 0.4
B25: Productivity
B26: Start up time | C26: Years | D26: 0.5
B27: Start up production | C27: % of full production | D27: 0.5
B31: Biomethane | C31: m3/yr | D31: =BM_Flow!E28*(BM_Flow!C43/100)*Inputs!F3*2 -> 9560947.5
B32: Fertilizer (?) | C32: kg/yr
B33: Waste Collection | C33: kg/yr | D33: =A_DCFROR!D33*2 -> 4.4828554e+08
B35: Internal Rate of Return and Tax Rate
B36: Internal rate of return | D36: 0.1
B37: Tax rate | D37: 0.35
B39: Results
B43: MSP BioMethane | C43: per m3 | D43: 4.8525 | H43: =D43/9.5 -> 0.51078947 | I43: $/kWh
B45: Waste Collection | C45: per kg | D45: 0.03
B47: Net Present Value | D47: =D86-SUM(E87:G87) -> -7025610.5
B49: Cash flow analysis
B51: Year | E51: -2 | F51: -1 | G51: 0 | H51: 1 | I51: 2 | J51: 3 | K51: 4 | L51: 5 | M51: 6 | N51: 7 | O51: 8 | P51: 9 | Q51: 10 | R51: 11 | S51: 12 | T51: 13 | U51: 14 | V51: 15 | W51: 16 | X51: 17 | Y51: 18 | Z51: 19 | AA51: 20 | AB51: 21 | AC51: 22 | AD51: 23 | AE51: 24 | AF51: 25 | AG51: 26 | AH51: 27 | AI51: 28 | AJ51: 29 | AK51: 30
B52: Equipment and facilities capital | E52: =($D$6*D21*$D$11) -> 6593707.7 | F52: =($D$6*D22*$D$11) -> 32968539 | G52: =$D$6*D23*$D$11 -> 26374831
B53: Land capital | E53: =D7 -> 24726404
B54: Working capital | G54: =D8 -> 8242134.6
B56: Loan Payment | E56: =E57 -> 791244.93 | F56: =F57 -> 4747469.6 | G56: =G57 -> 7912449.3 | H56: =D14 -> 14739853 | I56: =IF($D$13>H51,$D$14,0) -> 14739853 | J56: =IF($D$13>I51,$D$14,0) -> 14739853 | K56: =IF($D$13>J51,$D$14,0) -> 14739853 | L56: =IF($D$13>K51,$D$14,0) -> 14739853 | M56: =IF($D$13>L51,$D$14,0) -> 14739853 | N56: =IF($D$13>M51,$D$14,0) -> 14739853 | O56: =IF($D$13>N51,$D$14,0) -> 14739853 | P56: =IF($D$13>O51,$D$14,0) -> 14739853 | ... AK56: =IF($D$13>AJ51,$D$14,0) -> 0
C57: Loan interest payment | E57: =E58*$D$12 -> 791244.93 | F57: =+F58*$D$12 -> 4747469.6 | G57: =+G58*$D$12 -> 7912449.3 | H57: =D6*(1-D11)*D12 -> 7912449.3 | I57: =+H58*$D$12 -> 7366256.9 | J57: =+I58*$D$12 -> 6776369.2 | K57: =+J58*$D$12 -> 6139290.5 | L57: =+K58*$D$12 -> 5451245.5 | M57: =+L58*$D$12 -> 4708156.8 | N57: =+M58*$D$12 -> 3905621.1 | O57: =+N58*$D$12 -> 3038882.5 | P57: =+O58*$D$12 -> 2102804.9 | ... AK57: =+AJ58*$D$12 -> 2.4839335e-08
C58: Loan principle | E58: =$D$6*(1-$D$11)*$D$21 -> 9890561.6 | F58: =$D$6*(1-$D$11)*$D$22+E58 -> 59343369 | G58: =$D$6*(1-$D$11)*$D$23+F58 -> 98905616 | H58: =D6*(1-D11)-H56+H57 -> 92078212 | I58: =+H58-I56+I57 -> 84704615 | J58: =+I58-J56+J57 -> 76741131 | K58: =+J58-K56+K57 -> 68140568 | L58: =+K58-L56+L57 -> 58851960 | M58: =+L58-M56+M57 -> 48820264 | N58: =+M58-N56+N57 -> 37986032 | O58: =+N58-O56+O57 -> 26285061 | P58: =+O58-P56+P57 -> 13648012 | ... AK58: =+AJ58-AK56+AK57 -> 3.3533102e-07
C60: Total Loan Payent | E60: =E56 -> 791244.93 | F60: =F56 -> 4747469.6 | G60: =G56 -> 7912449.3 | H60: =H56+H59 -> 14739853 | I60: =I56+I59 -> 14739853 | J60: =J56+J59 -> 14739853 | K60: =K56+K59 -> 14739853 | L60: =L56+L59 -> 14739853 | M60: =M56+M59 -> 14739853 | N60: =N56+N59 -> 14739853 | O60: =O56+O59 -> 14739853 | ... R60: =R56+R59 -> 0
B61: Product sales
C62: =B29 -> 0 | H62: =($D29*$D41)*(1-$D$26)+($D29*$D41)*$D$26*$D$27 -> 0 | I62: =+$D29*$D41 -> 0 | J62: =+$D29*$D41 -> 0 | K62: =+$D29*$D41 -> 0 | L62: =+$D29*$D41 -> 0 | M62: =+$D29*$D41 -> 0 | N62: =+$D29*$D41 -> 0 | O62: =+$D29*$D41 -> 0 | P62: =+$D29*$D41 -> 0 | ... AK62: =+$D29*$D41 -> 0
C63: =B30 -> 0 | H63: =($D30*$D42)*(1-$D$26)+($D30*$D42)*$D$26*$D$27 -> 0 | I63: =+$D30*$D42 -> 0 | J63: =+$D30*$D42 -> 0 | K63: =+$D30*$D42 -> 0 | L63: =+$D30*$D42 -> 0 | M63: =+$D30*$D42 -> 0 | N63: =+$D30*$D42 -> 0 | O63: =+$D30*$D42 -> 0 | P63: =+$D30*$D42 -> 0 | ... AK63: =+$D30*$D42 -> 0
C64: Biomethane | H64: =($D31*$D43)*(1-$D$26)+($D31*$D43)*$D$26*$D$27 -> 34795873 | I64: =+$D31*$D43 -> 46394498 | J64: =+$D31*$D43 -> 46394498 | K64: =+$D31*$D43 -> 46394498 | L64: =+$D31*$D43 -> 46394498 | M64: =+$D31*$D43 -> 46394498 | N64: =+$D31*$D43 -> 46394498 | O64: =+$D31*$D43 -> 46394498 | P64: =+$D31*$D43 -> 46394498 | ... AK64: =+$D31*$D43 -> 46394498
C65: Fertilizer | H65: =($D32*$D44)*(1-$D$26)+($D32*$D44)*$D$26*$D$27 -> 0 | I65: =+$D32*$D44 -> 0 | J65: =+$D32*$D44 -> 0 | K65: =+$D32*$D44 -> 0 | L65: =+$D32*$D44 -> 0 | M65: =+$D32*$D44 -> 0 | N65: =+$D32*$D44 -> 0 | O65: =+$D32*$D44 -> 0 | P65: =+$D32*$D44 -> 0 | ... AK65: =+$D32*$D44 -> 0
C66: =B33 -> Waste Collection | H66: =($D33*$D45)*(1-$D$26)+($D33*$D45)*$D$26*$D$27 -> 10086425 | I66: =+$D33*$D45 -> 13448566 | J66: =+$D33*$D45 -> 13448566 | K66: =+$D33*$D45 -> 13448566 | L66: =+$D33*$D45 -> 13448566 | M66: =+$D33*$D45 -> 13448566 | N66: =+$D33*$D45 -> 13448566 | O66: =+$D33*$D45 -> 13448566 | P66: =+$D33*$D45 -> 13448566 | ... AK66: =+$D33*$D45 -> 13448566
B68: Total Sales | H68: =SUM(H62:H67) -> 44882298 | I68: =SUM(I62:I67) -> 59843064 | J68: =SUM(J62:J67) -> 59843064 | K68: =SUM(K62:K67) -> 59843064 | L68: =SUM(L62:L67) -> 59843064 | M68: =SUM(M62:M67) -> 59843064 | N68: =SUM(N62:N67) -> 59843064 | O68: =SUM(O62:O67) -> 59843064 | ... AK68: =SUM(AK62:AK67) -> 59843064
B70: Annual costs
C71: Facility | H71: =+D5*(1-$D$26)+D5*$D$26*$D$27 -> 26405481 | I71: =+$D$5 -> 35207308 | J71: =+$D$5 -> 35207308 | K71: =+$D$5 -> 35207308 | L71: =+$D$5 -> 35207308 | M71: =+$D$5 -> 35207308 | N71: =+$D$5 -> 35207308 | O71: =+$D$5 -> 35207308 | P71: =+$D$5 -> 35207308 | ... AK71: =+$D$5 -> 35207308
B73: Total Production Cost | H73: =SUM(H71:H72) -> 26405481 | I73: =SUM(I71:I72) -> 35207308 | J73: =SUM(J71:J72) -> 35207308 | K73: =SUM(K71:K72) -> 35207308 | L73: =SUM(L71:L72) -> 35207308 | M73: =SUM(M71:M72) -> 35207308 | N73: =SUM(N71:N72) -> 35207308 | O73: =SUM(O71:O72) -> 35207308 | ... AK73: =SUM(AK71:AK72) -> 35207308
B75: Depreciation
H76: 0.1429 | I76: 0.2449 | J76: 0.1749 | K76: 0.1249 | L76: 0.0893 | M76: 0.0892 | N76: 0.0893 | O76: 0.0446 | P76: 0 | Q76: 0 | R76: 0 | S76: 0 | T76: 0 | U76: 0 | V76: 0 | W76: 0 | X76: 0 | Y76: 0 | Z76: 0 | AA76: 0 | AB76: 0 | AC76: 0 | AD76: 0 | AE76: 0 | AF76: 0 | AG76: 0 | AH76: 0 | AI76: 0 | AJ76: 0 | AK76: 0
H77: =H$76*$D$6 -> 23556021 | I77: =I$76*$D$6 -> 40369975 | J77: =J$76*$D$6 -> 28830987 | K77: =K$76*$D$6 -> 20588852 | L77: =L$76*$D$6 -> 14720452 | M77: =M$76*$D$6 -> 14703968 | N77: =N$76*$D$6 -> 14720452 | O77: =O$76*$D$6 -> 7351984.1 | ... AK77: =AK$76*$D$6 -> 0
B79: Net revenue | H79: =+H68-H60-H73-H77 -> -19819057 | I79: =+I68-I60-I73-I77 -> -30474072 | J79: =+J68-J60-J73-J77 -> -18935084 | K79: =+K68-K60-K73-K77 -> -10692949 | L79: =+L68-L60-L73-L77 -> -4824549.4 | M79: =+M68-M60-M73-M77 -> -4808065.2 | N79: =+N68-N60-N73-N77 -> -4824549.4 | O79: =+O68-O60-O73-O77 -> 2543918.9 | ... AK79: =+AK68-AK60-AK73-AK77 -> 24635756
B80: Losses forward | H80: 0 | I80: =IF(H81<0,H81,0) -> -19819057 | J80: =IF(I81<0,I81,0) -> -50293129 | K80: =IF(J81<0,J81,0) -> -69228213 | L80: =IF(K81<0,K81,0) -> -79921162 | M80: =IF(L81<0,L81,0) -> -84745712 | N80: =IF(M81<0,M81,0) -> -89553777 | O80: =IF(N81<0,N81,0) -> -94378326 | P80: =IF(O81<0,O81,0) -> -91834408 | ... AK80: =IF(AJ81<0,AJ81,0) -> 0
B81: Taxable income | H81: =+H80+H79 -> -19819057 | I81: =+I80+I79 -> -50293129 | J81: =+J80+J79 -> -69228213 | K81: =+K80+K79 -> -79921162 | L81: =+L80+L79 -> -84745712 | M81: =+M80+M79 -> -89553777 | N81: =+N80+N79 -> -94378326 | O81: =+O80+O79 -> -91834408 | ... AK81: =+AK80+AK79 -> 24635756
B82: Income Tax | H82: =IF(H81*($D$37)<0,0,H81*$D$37) -> 0 | I82: =IF(I81*($D$37)<0,0,I81*$D$37) -> 0 | J82: =IF(J81*($D$37)<0,0,J81*$D$37) -> 0 | K82: =IF(K81*($D$37)<0,0,K81*$D$37) -> 0 | L82: =IF(L81*($D$37)<0,0,L81*$D$37) -> 0 | M82: =IF(M81*($D$37)<0,0,M81*$D$37) -> 0 | N82: =IF(N81*($D$37)<0,0,N81*$D$37) -> 0 | O82: =IF(O81*($D$37)<0,0,O81*$D$37) -> 0 | ... AK82: =IF(AK81*($D$37)<0,0,AK81*$D$37) -> 8622514.7
B84: Annual Cash Income | H84: =+H68-H60-H73-H82 -> 3736963.9 | I84: =+I68-I60-I73-I82 -> 9895903 | J84: =+J68-J60-J73-J82 -> 9895903 | K84: =+K68-K60-K73-K82 -> 9895903 | L84: =+L68-L60-L73-L82 -> 9895903 | M84: =+M68-M60-M73-M82 -> 9895903 | N84: =+N68-N60-N73-N82 -> 9895903 | O84: =+O68-O60-O73-O82 -> 9895903 | ... Y84: =+Y68-Y60-Y73-Y82 -> 16013242 | Z84: =+Z68-Z56-Z73-Z82 -> 16013242 | AA84: =+AA68-AA56-AA73-AA82 -> 16013242 | AB84: =+AB68-AB56-AB73-AB82 -> 16013242 | AC84: =+AC68-AC56-AC73-AC82 -> 16013242 | AD84: =+AD68-AD56-AD73-AD82 -> 16013242 | AE84: =+AE68-AE56-AE73-AE82 -> 16013242 | AF84: =+AF68-AF56-AF73-AF82 -> 16013242 | AG84: =+AG68-AG56-AG73-AG82 -> 16013242 | ... AK84: =+AK68-AK56-AK73-AK82 -> 16013242
B85: Discount Factor | E85: =1/(1+$D$36)^E51 -> 1.21 | F85: =1/(1+$D$36)^F51 -> 1.1 | G85: =1/(1+$D$36)^G51 -> 1 | H85: =1/(1+$D$36)^H51 -> 0.90909091 | I85: =1/(1+$D$36)^I51 -> 0.82644628 | J85: =1/(1+$D$36)^J51 -> 0.7513148 | K85: =1/(1+$D$36)^K51 -> 0.68301346 | L85: =1/(1+$D$36)^L51 -> 0.62092132 | ... AK85: =1/(1+$D$36)^AK51 -> 0.057308553
B86: Anuual Present Value | D86: =SUM(H86:AK86) -> 1.1584615e+08 | H86: =+H85*H84 -> 3397239.9 | I86: =+I85*I84 -> 8178432.3 | J86: =+J85*J84 -> 7434938.4 | K86: =+K85*K84 -> 6759034.9 | L86: =+L85*L84 -> 6144577.2 | M86: =+M85*M84 -> 5585979.3 | N86: =+N85*N84 -> 5078163 | O86: =+O85*O84 -> 4616511.8 | ... AK86: =+AK85*AK84 -> 917695.71
B87: Total Capital Investment + Interest | E87: =+SUM(E52,E57,E53)*E85 -> 38854741 | F87: =+(F52+F57)*F85 -> 41487609 | G87: =+(G52+G57+G54)*G85 -> 42529415
B89: NPV Land | D89: =E89 -> 29918949 | E89: =E53*E85 -> 29918949
B90: NPV Total Product Sales | D90: =SUM(H90:AK90) -> 5.5053475e+08 | H90: =H85*H68 -> 40802089 | I90: =I85*I68 -> 49457078 | J90: =J85*J68 -> 44960980 | K90: =K85*K68 -> 40873618 | L90: =L85*L68 -> 37157834 | M90: =M85*M68 -> 33779849 | N90: =N85*N68 -> 30708954 | O90: =O85*O68 -> 27917231 | ... AK90: =AK85*AK68 -> 3429519.4
B91: NPV Tax | D91: =SUM(H91:AK91) -> 20223960 | H91: =+H85*H82 -> 0 | I91: =+I85*I82 -> 0 | J91: =+J85*J82 -> 0 | K91: =+K85*K82 -> 0 | L91: =+L85*L82 -> 0 | M91: =+M85*M82 -> 0 | N91: =+N85*N82 -> 0 | O91: =+O85*O82 -> 0 | ... AK91: =+AK85*AK82 -> 494143.84
B92: NPV Operating Costs | D92: =SUM(H92:AK92) -> 3.2389462e+08 | H92: =H85*H71 -> 24004982 | I92: =I85*I71 -> 29096948 | J92: =J85*J71 -> 26451771 | K92: =K85*K71 -> 24047065 | L92: =L85*L71 -> 21860968 | M92: =M85*M71 -> 19873607 | N92: =N85*N71 -> 18066916 | O92: =O85*O71 -> 16424469 | ... AK92: =AK85*AK71 -> 2017679.9
B93: NPV Equip and Facilities Capital Costs | D93: =SUM(E93:G93) -> 78860744 | E93: =E52*E85 -> 7978386.3 | F93: =F52*F85 -> 36265392 | G93: =G52*G85+G54*G85 -> 34616965
B94: NPV Coproduct Sales | D94: =SUM(H94:AK94) -> 1.2372199e+08 | H94: =SUM(H62,H63,H65,H66)*H85 -> 9169476.9 | I94: =SUM(I62,I63,I65,I66)*I85 -> 11114518 | J94: =SUM(J62,J63,J65,J66)*J85 -> 10104107 | K94: =SUM(K62,K63,K65,K66)*K85 -> 9185551.7 | L94: =SUM(L62,L63,L65,L66)*L85 -> 8350501.5 | M94: =SUM(M62,M63,M65,M66)*M85 -> 7591365 | N94: =SUM(N62,N63,N65,N66)*N85 -> 6901240.9 | O94: =SUM(O62,O63,O65,O66)*O85 -> 6273855.4 | ... AK94: =SUM(AK62,AK63,AK65,AK66)*AK85 -> 770717.87
B96: NPV Naphtha Sales | D96: =SUM(H96:AK96) -> 0 | E96: =D96/D94 -> 0 | H96: =H62*H85 -> 0 | I96: =I62*I85 -> 0 | J96: =J62*J85 -> 0 | K96: =K62*K85 -> 0 | L96: =L62*L85 -> 0 | M96: =M62*M85 -> 0 | N96: =N62*N85 -> 0 | O96: =O62*O85 -> 0 | ... AK96: =AK62*AK85 -> 0
B97: NPV Waste Collection Sales | D97: =SUM(H97:AK97) -> 1.2372199e+08 | E97: =D97/D94 -> 1 | H97: =H66*H85 -> 9169476.9 | I97: =I66*I85 -> 11114518 | J97: =J66*J85 -> 10104107 | K97: =K66*K85 -> 9185551.7 | L97: =L66*L85 -> 8350501.5 | M97: =M66*M85 -> 7591365 | N97: =N66*N85 -> 6901240.9 | O97: =O66*O85 -> 6273855.4 | ... AK97: =AK66*AK85 -> 770717.87
B99: Total Net Present Value | D99: =D86-SUM(E87:G87) -> -7025610.5
B102: DCFROR GRAPH
B104: Year | C104: =E51 -> -2 | D104: =F51 -> -1 | E104: =G51 -> 0 | F104: =H51 -> 1 | G104: =I51 -> 2 | H104: =J51 -> 3 | I104: =K51 -> 4 | J104: =L51 -> 5 | ... AI104: =AK51 -> 30
B105: Capital Investment | C105: =SUM(E52:E54)/(10^6) -> 31.320112 | D105: =SUM(F52:F54)/(10^6) -> 32.968539 | E105: =SUM(G52:G54)/(10^6) -> 34.616965
B106: Tax | F106: =H82/(10^6) -> 0 | G106: =I82/(10^6) -> 0 | H106: =J82/(10^6) -> 0 | I106: =K82/(10^6) -> 0 | J106: =L82/(10^6) -> 0 | K106: =M82/(10^6) -> 0 | L106: =N82/(10^6) -> 0 | M106: =O82/(10^6) -> 0 | ... Q106: =S82/(10^6) -> 0 | R106: =T82/(10^6)*-1 -> -0.65263365 | S106: =U82/(10^6)*-1 -> -8.6225147 | T106: =V82/(10^6)*-1 -> -8.6225147 | U106: =W82/(10^6)*-1 -> -8.6225147 | V106: =X82/(10^6)*-1 -> -8.6225147 | W106: =Y82/(10^6)*-1 -> -8.6225147 | X106: =Z82/(10^6)*-1 -> -8.6225147 | Y106: =AA82/(10^6)*-1 -> -8.6225147 | ... AI106: =AK82/(10^6)*-1 -> -8.6225147
B107: Depreciation | E107: =(H77*-1)/10^6 -> -23.556021 | F107: =(I77*-1)/10^6 -> -40.369975 | G107: =(J77*-1)/10^6 -> -28.830987 | H107: =(K77*-1)/10^6 -> -20.588852 | I107: =(L77*-1)/10^6 -> -14.720452 | J107: =(M77*-1)/10^6 -> -14.703968 | K107: =(N77*-1)/10^6 -> -14.720452 | L107: =(O77*-1)/10^6 -> -7.3519841 | ... AI107: =(AL77*-1)/10^6 -> 0
B108: Loan Payment | C108: =(E57*-1)/(10^6) -> -0.79124493 | D108: =(F57*-1)/(10^6) -> -4.7474696 | E108: =(G57*-1)/(10^6) -> -7.9124493 | F108: =(H57*-1)/(10^6) -> -7.9124493 | G108: =(I57*-1)/(10^6) -> -7.3662569 | H108: =(J57*-1)/(10^6) -> -6.7763692 | I108: =(K57*-1)/(10^6) -> -6.1392905 | J108: =(L57*-1)/(10^6) -> -5.4512455 | ... AI108: =(AK57*-1)/(10^6) -> -2.4839335e-14
B109: OPEX | F109: =(H71*-1)/10^6 -> -26.405481 | G109: =(I71*-1)/10^6 -> -35.207308 | H109: =(J71*-1)/10^6 -> -35.207308 | I109: =(K71*-1)/10^6 -> -35.207308 | J109: =(L71*-1)/10^6 -> -35.207308 | K109: =(M71*-1)/10^6 -> -35.207308 | L109: =(N71*-1)/10^6 -> -35.207308 | M109: =(O71*-1)/10^6 -> -35.207308 | ... AI109: =(AK71*-1)/10^6 -> -35.207308
B110: Revenue | F110: =H86/(10^6) -> 3.3972399 | G110: =I86/(10^6) -> 8.1784323 | H110: =J86/(10^6) -> 7.4349384 | I110: =K86/(10^6) -> 6.7590349 | J110: =L86/(10^6) -> 6.1445772 | K110: =M86/(10^6) -> 5.5859793 | L110: =N86/(10^6) -> 5.078163 | M110: =O86/(10^6) -> 4.6165118 | ... AI110: =AK86/(10^6) -> 0.91769571
B111: Net Present Value | F111: =(H86-SUM($E$87:$G$87))/(10^6) -> -119.47453 | G111: =(SUM($H$86:I86)-SUM($E$87:$G$87))/(10^6) -> -111.29609 | H111: =(SUM($H$86:J86)-SUM($E$87:$G$87))/(10^6) -> -103.86115 | I111: =(SUM($H$86:K86)-SUM($E$87:$G$87))/(10^6) -> -97.102119 | J111: =(SUM($H$86:L86)-SUM($E$87:$G$87))/(10^6) -> -90.957542 | K111: =(SUM($H$86:M86)-SUM($E$87:$G$87))/(10^6) -> -85.371563 | L111: =(SUM($H$86:N86)-SUM($E$87:$G$87))/(10^6) -> -80.2934 | M111: =(SUM($H$86:O86)-SUM($E$87:$G$87))/(10^6) -> -75.676888 | N111: =(SUM($H$86:P86)-SUM($E$87:$G$87))/(10^6) -> -71.480059 | ... AI111: =(SUM($H$86:AK86)-SUM($E$87:$G$87))/(10^6) -> -7.0256105
B115: MINIMUM SELLING PRICE AS NET PRESENT VALUE
B117: OUTPUTS
B118: Parameter | C118: Unit | D118: Baseline Value
B119: NPV Tax | C119: $ | D119: =D91 -> 20223960
B120: NPV Operational Cost | C120: $ | D120: =D92 -> 3.2389462e+08
B121: NPV Capital Cost | C121: $ | D121: =D93 -> 78860744
B122: NPV Coproduct Sales | C122: $ | D122: =D94 -> 1.2372199e+08
B123: Minimum Selling Price | C123: $/kg | D123: =D43 -> 4.8525
B125: Results Analysis
B126: SUM(Tax, OPEX, CAPEX) | C126: $ | D126: =SUM(D119:D121) -> 4.2297932e+08
B127: NPV Tax | C127: % | D127: =D119/D$126*(1+D$130) -> 0.061798516
B128: NPV Operational Cost | C128: % | D128: =D120/D$126*(1+D$130) -> 0.98972736
B129: NPV Capital Cost | C129: % | D129: =D121/D$126*(1+D$130) -> 0.2409754
B130: NPV Coproduct Sales | C130: % | D130: =D122/D126 -> 0.29250128
B131: NPV Tax | C131: as MSP | D131: =D127*D$123 -> 0.2998773
B132: NPV Operational Cost | C132: as MSP | D132: =D128*D$123 -> 4.802652
B133: NPV Capital Cost | C133: as MSP | D133: =D129*D$123 -> 1.1693331
B134: NPV Coproduct Sales | C134: as MSP | D134: =D130*D$123 -> 1.4193624
B135: Total MSP | D135: =SUM(D131:D133)-D134 -> 4.8525
C139: Price
B140: Transportation | C140: =((BM_CAPEX!B74/SUM(BM_CAPEX!B$74:B$78))*BM_DCFROR!D$133)+((BM_OPEX!B123/SUM(BM_OPEX!B$123:B$131))*BM_DCFROR!D$132) -> 0.66643946
...

Sheet LCOE&D
A1: Levelized Cost of Energy and Disposal - Excluding Coproducts
A3: Energy Density of Hydrocarbon Mixture
A4: C4 n-Paraffin | B4: =Units!C264/Units!C558*ExpBase!E1156/100 -> 0.0085343369
A5: C5 n-Paraffin | B5: =Units!C265/Units!C559*ExpBase!E1157/100 -> 0.30259053
A6: C6 n-Paraffin | B6: =Units!C266/Units!C560*ExpBase!E1158/100 -> 3.5018938
A7: C7 n-Paraffin | B7: =Units!C267/Units!C561*ExpBase!E1159/100 -> 16.519655
A8: C8 n-Paraffin | B8: =Units!C268/Units!C562*ExpBase!E1160/100 -> 0.94171127
A9: C9 n-Paraffin | B9: =Units!C269/Units!C563*ExpBase!E1161/100 -> 2.3090539
A10: C10 n-Paraffin | B10: =Units!C270/Units!C564*ExpBase!E1162/100 -> 3.8632995
A11: C11 n-Paraffin | B11: =Units!C271/Units!C565*ExpBase!E1163/100 -> 4.4035704
A12: C12 n-Paraffin | B12: =Units!C272/Units!C566*ExpBase!E1164/100 -> 8.2520341
A13: C13 n-Paraffin | B13: =Units!C273/Units!C567*ExpBase!E1165/100 -> 0.48670086
A14: C14 n-Paraffin | B14: =Units!C274/Units!C568*ExpBase!E1166/100 -> 0.0043739753
A15: C6 iso-Paraffin | B15: =Units!C275/Units!C569*ExpBase!E1167/100 -> 0
... A21: C12 iso-Paraffin | B21: =Units!C281/Units!C575*ExpBase!E1173/100 -> 0.01839238
A22: TOTAL | B22: =SUM(B4:B21)*1000000 -> 41256193 | C22: J/kg
A26: Year | D26: -2 | E26: -1 | F26: 0 | G26: 1 | H26: 2 | I26: 3 | J26: 4 | K26: 5 | L26: 6 | M26: 7 | N26: 8 | O26: 9 | P26: 10 | Q26: 11 | R26: 12 | S26: 13 | T26: 14 | U26: 15 | V26: 16 | W26: 17 | X26: 18 | Y26: 19 | Z26: 20 | AA26: 21 | AB26: 22 | AC26: 23 | AD26: 24 | AE26: 25 | AF26: 26 | AG26: 27 | AH26: 28 | AI26: 29 | AJ26: 30
A28: Discount Factor | D28: =1/(1+AB_DCFROR!$D$38)^D26 -> 1.21 | E28: =1/(1+AB_DCFROR!$D$38)^E26 -> 1.1 | F28: =1/(1+AB_DCFROR!$D$38)^F26 -> 1 | G28: =1/(1+AB_DCFROR!$D$38)^G26 -> 0.90909091 | H28: =1/(1+AB_DCFROR!$D$38)^H26 -> 0.82644628 | I28: =1/(1+AB_DCFROR!$D$38)^I26 -> 0.7513148 | J28: =1/(1+AB_DCFROR!$D$38)^J26 -> 0.68301346 | K28: =1/(1+AB_DCFROR!$D$38)^K26 -> 0.62092132 | ... AJ28: =1/(1+AB_DCFROR!$D$38)^AJ26 -> 0.057308553
A30: SUSTAINABLE AVIATION FUEL
A31: Energy Generated | D31: 0 | E31: 0 | F31: 0 | G31: =(H31)*(1-AB_DCFROR!D26)+(J31*AB_DCFROR!D26*AB_DCFROR!D27) -> 52821962 | H31: =$B$22*A_DCFROR!$D$31/3600000 -> 70429283 | I31: =$B$22*A_DCFROR!$D$31/3600000 -> 70429283 | J31: =$B$22*A_DCFROR!$D$31/3600000 -> 70429283 | K31: =$B$22*A_DCFROR!$D$31/3600000 -> 70429283 | L31: =$B$22*A_DCFROR!$D$31/3600000 -> 70429283 | M31: =$B$22*A_DCFROR!$D$31/3600000 -> 70429283 | N31: =$B$22*A_DCFROR!$D$31/3600000 -> 70429283 | O31: =$B$22*A_DCFROR!$D$31/3600000 -> 70429283 | ... AJ31: =$B$22*A_DCFROR!$D$31/3600000 -> 70429283
A32: Discounted Energy | D32: =D31*D28 -> 0 | E32: =E31*E28 -> 0 | F32: =F31*F28 -> 0 | G32: =G31*G28 -> 48019966 | H32: =H31*H28 -> 58206019 | I32: =I31*I28 -> 52914563 | J32: =J31*J28 -> 48104148 | K32: =K31*K28 -> 43731044 | ... AJ32: =AJ31*AJ28 -> 4036200.3
A33: Total Discounted Energy | B33: =SUM(D32:AJ32) -> 6.4792417e+08 | C33: kWh
A36: Waste Collected (kg/yr)
A37: Waste Collected - 0.48 M Scale | G37: =A_DCFROR!$D$33 -> 2.2414277e+08 | H37: =A_DCFROR!$D$33 -> 2.2414277e+08 | I37: =A_DCFROR!$D$33 -> 2.2414277e+08 | J37: =A_DCFROR!$D$33 -> 2.2414277e+08 | K37: =A_DCFROR!$D$33 -> 2.2414277e+08 | L37: =A_DCFROR!$D$33 -> 2.2414277e+08 | M37: =A_DCFROR!$D$33 -> 2.2414277e+08 | N37: =A_DCFROR!$D$33 -> 2.2414277e+08 | ... AJ37: =A_DCFROR!$D$33 -> 2.2414277e+08
A38: Discounted Waste | G38: =G37*G28 -> 2.0376615e+08 | H38: =H37*H28 -> 1.8524196e+08 | I38: =I37*I28 -> 1.6840178e+08 | J38: =J37*J28 -> 1.5309253e+08 | K38: =K37*K28 -> 1.3917503e+08 | L38: =L37*L28 -> 1.2652275e+08 | M38: =M37*M28 -> 1.1502068e+08 | N38: =N37*N28 -> 1.0456426e+08 | ... AJ38: =AJ37*AJ28 -> 12845298
A39: Total Discounted Waste | B39: =SUM(G38:AJ38) -> 2.1129747e+09 | C39: kg
A41: Costs
A42: Discounted Capital Costs | D42: =A_DCFROR!D6*A_DCFROR!D21*D28 -> 46980203 | E42: =A_DCFROR!D6*A_DCFROR!D22*E28 -> 2.1354638e+08 | F42: =A_DCFROR!D6*A_DCFROR!D23*F28 -> 1.5530645e+08
A43: Land Capital - Discounted | D43: =A_DCFROR!D7*D28 -> 70470304
A44: Working Capital - Discounted | F44: =A_DCFROR!D8*F28 -> 19413307
A45: Operational Costs | G45: =A_DCFROR!$D$5*G28 -> 63452696 | H45: =A_DCFROR!$D$5*H28 -> 57684269 | I45: =A_DCFROR!$D$5*I28 -> 52440245 | J45: =A_DCFROR!$D$5*J28 -> 47672950 | K45: =A_DCFROR!$D$5*K28 -> 43339045 | L45: =A_DCFROR!$D$5*L28 -> 39399132 | M45: =A_DCFROR!$D$5*M28 -> 35817393 | N45: =A_DCFROR!$D$5*N28 -> 32561266 | ... AJ45: =A_DCFROR!$D$5*AJ28 -> 4000020.4
A46: Sustainable Aviation Fuel Credit | B46: =1.25/Units!C10 -> 0.41254125 | C46: per kg | G46: =A_DCFROR!$H$64/A_DCFROR!$D$43*$B$46*G28 -> 1728632.1 | H46: =A_DCFROR!$H$64/A_DCFROR!$D$43*$B$46*H28 -> 1571483.7 | I46: =A_DCFROR!$H$64/A_DCFROR!$D$43*$B$46*I28 -> 1428621.6 | J46: =A_DCFROR!$H$64/A_DCFROR!$D$43*$B$46*J28 -> 1298746.9 | K46: =A_DCFROR!$H$64/A_DCFROR!$D$43*$B$46*K28 -> 1180679 | L46: =A_DCFROR!$H$64/A_DCFROR!$D$43*$B$46*L28 -> 1073344.5 | M46: =A_DCFROR!$H$64/A_DCFROR!$D$43*$B$46*M28 -> 975767.77 | N46: =A_DCFROR!$H$64/A_DCFROR!$D$43*$B$46*N28 -> 887061.61 | ... AJ46: =A_DCFROR!$H$64/A_DCFROR!$D$43*$B$46*AJ28 -> 108971.95
A47: Total Discounted Cost | B47: =SUM(D42:AJ46) -> 1.1816213e+09
A49: net Levelized Cost of Energy - SAF | B49: =B47/B33 -> 1.8237031 | C49: USD/kWh
A50: net Levelized Cost of Disposal - SAF | B50: =B47/B39 -> 0.55922171 | C50: USD/kg Waste
A52: BIO-METHANE PRODUCTION | G52: =G53/1000000 -> 71.491985
A53: Energy Generated | B53: 9.97 | C53: kWh/m3 | D53: 0 | E53: 0 | F53: 0 | G53: =(BM_DCFROR!$D$31*$B$53)*BM_DCFROR!D26+(H53*BM_DCFROR!D27*BM_DCFROR!D26) -> 71491985 | H53: =BM_DCFROR!$D$31*$B$53 -> 95322647 | I53: =BM_DCFROR!$D$31*$B$53 -> 95322647 | J53: =BM_DCFROR!$D$31*$B$53 -> 95322647 | K53: =BM_DCFROR!$D$31*$B$53 -> 95322647 | L53: =BM_DCFROR!$D$31*$B$53 -> 95322647 | M53: =BM_DCFROR!$D$31*$B$53 -> 95322647 | N53: =BM_DCFROR!$D$31*$B$53 -> 95322647 | O53: =BM_DCFROR!$D$31*$B$53 -> 95322647 | ... AJ53: =BM_DCFROR!$D$31*$B$53 -> 95322647
A54: Discounted Energy | D54: =D28*D53 -> 0 | E54: =E28*E53 -> 0 | F54: =F28*F53 -> 0 | G54: =G28*G53 -> 64992714 | H54: =H28*H53 -> 78779047 | I54: =I28*I53 -> 71617315 | J54: =J28*J53 -> 65106650 | K54: =K28*K53 -> 59187864 | ... AJ54: =AJ28*AJ53 -> 5462803
A55: Total Discounted Energy | B55: =SUM(D54:AJ54) -> 8.769342e+08 | C55: kWh
A57: Discounted Capital Costs | D57: =BM_DCFROR!D6*BM_DCFROR!D21*D28 -> 19945966 | E57: =BM_DCFROR!D6*BM_DCFROR!D22*E28 -> 90663481 | F57: =BM_DCFROR!D6*BM_DCFROR!D23*F28 -> 65937077
A58: Land Capital - Discounted | D58: =BM_DCFROR!D7*D28 -> 29918949
A59: Working Capital - Discounted | F59: =BM_DCFROR!D8*F28 -> 8242134.6
A60: Operational Costs | G60: =BM_DCFROR!$D$5*G28 -> 32006643 | H60: =BM_DCFROR!$D$5*H28 -> 29096948 | I60: =BM_DCFROR!$D$5*I28 -> 26451771 | J60: =BM_DCFROR!$D$5*J28 -> 24047065 | K60: =BM_DCFROR!$D$5*K28 -> 21860968 | L60: =BM_DCFROR!$D$5*L28 -> 19873607 | M60: =BM_DCFROR!$D$5*M28 -> 18066916 | N60: =BM_DCFROR!$D$5*N28 -> 16424469 | ... AJ60: =BM_DCFROR!$D$5*AJ28 -> 2017679.9
A62: Total Discounted Cost | B62: =SUM(D57:AJ61) -> 5.4660388e+08 | C62: =B62/2 -> 2.7330194e+08
A64: net Levelized Cost of Energy - BM | B64: =B62/B55 -> 0.62331231 | C64: USD/kWh
A65: net Levelized Cost of Disposal - BM | B65: =B62/B39 -> 0.25868927 | C65: USD/kg Waste
A67: PETROCHEMICAL JET FUEL
A68: Price of Jet A Fuel | B68: 6.25 | C68: per gal
A69: Energy Content of Jet Fuel | B69: 36.8 | C69: kWh/gal
A70: Cost of Energy | B70: =B68/B69 -> 0.16983696 | C70: USD/kWH
B72: Pilot Scale
B73: Energy | C73: Disposal | D73: Energy | E73: Disposal
B74: BM | C74: BM | D74: SAF | E74: SAF
A75: Capital Cost | B75: =SUM(D57:F59)/B55 -> 0.2448389 | C75: =SUM(D57:F59)/B39 -> 0.1016139 | D75: =SUM(D42:F44)/B33 -> 0.78051826 | E75: =SUM(D42:F44)/B39 -> 0.23933871
A76: Operation Cost | B76: =SUM(F60:AJ60)/B55 -> 0.37847341 | C76: =SUM(F60:AJ60)/B39 -> 0.15707537 | D76: =SUM(D45:AJ45)/B33 -> 1.0155192 | E76: =SUM(D45:AJ45)/B39 -> 0.31139959
A77: Tax Credits | D77: =-SUM(D46:AJ46)/B33 -> -0.027665635 | E77: =-SUM(D46:AJ46)/B39 -> -0.0084834114
A78: Total Cost | B78: =SUM(B75:B77) -> 0.62331231 | C78: =SUM(C75:C77) -> 0.25868927 | D78: =SUM(D75:D77) -> 1.7683718 | E78: =SUM(E75:E77) -> 0.54225488
B81: Pilot Scale | F81: Commercial Scale
B82: Energy | D82: Disposal | F82: Energy | H82: Disposal
B83: BM | C83: SAF | D83: BM | E83: SAF | F83: BM | G83: SAF | H83: BM | I83: SAF
A84: Capital Cost | B84: 0.20957503 | C84: 0.63976759 | D84: 0.087128718 | E84: 0.19382101 | F84: 0.19354096 | G84: 3.4091098 | H84: 0.080542874 | I84: 1.0255147
A85: Operation Cost | B85: 0.25485856 | C85: 0.61127366 | D85: 0.10595489 | E85: 0.18518862 | F85: 0.21250768 | G85: 1.652407 | H85: 0.088435952 | I85: 0.49707044
A86: Tax Credits | C86: -0.02766563 | E86: -0.0083814504 | G86: -0.027665627 | I86: -0.008322263
A87: Total Cost | B87: 0.4644336 | C87: 1.2233756 | D87: 0.19308361 | E87: 0.37062817 | F87: 0.40604865 | G87: -0.36814405 | H87: 0.16897883 | I87: -0.11074361
A89: Coproducts | F89: 0 | G89: -5.4019952 | H89: 0 | I89: -1.6250065

Sheet LCOE_CP
A1: Net Levelized Cost of Energy and Disposal - Including Coproducts
A3: Energy Density of Hydrocarbon Mixture
A4: C4 n-Paraffin | B4: =Units!C264/Units!C558*ExpBase!E1156/100 -> 0.0085343369
A5: C5 n-Paraffin | B5: =Units!C265/Units!C559*ExpBase!E1157/100 -> 0.30259053
A6: C6 n-Paraffin | B6: =Units!C266/Units!C560*ExpBase!E1158/100 -> 3.5018938
A7: C7 n-Paraffin | B7: =Units!C267/Units!C561*ExpBase!E1159/100 -> 16.519655
A8: C8 n-Paraffin | B8: =Units!C268/Units!C562*ExpBase!E1160/100 -> 0.94171127
A9: C9 n-Paraffin | B9: =Units!C269/Units!C563*ExpBase!E1161/100 -> 2.3090539
A10: C10 n-Paraffin | B10: =Units!C270/Units!C564*ExpBase!E1162/100 -> 3.8632995
A11: C11 n-Paraffin | B11: =Units!C271/Units!C565*ExpBase!E1163/100 -> 4.4035704
A12: C12 n-Paraffin | B12: =Units!C272/Units!C566*ExpBase!E1164/100 -> 8.2520341
A13: C13 n-Paraffin | B13: =Units!C273/Units!C567*ExpBase!E1165/100 -> 0.48670086
A14: C14 n-Paraffin | B14: =Units!C274/Units!C568*ExpBase!E1166/100 -> 0.0043739753
A15: C6 iso-Paraffin | B15: =Units!C275/Units!C569*ExpBase!E1167/100 -> 0
... A21: C12 iso-Paraffin | B21: =Units!C281/Units!C575*ExpBase!E1173/100 -> 0.01839238
A22: TOTAL | B22: =SUM(B4:B21)*1000000 -> 41256193 | C22: J/kg | D22: =B22/1000000 -> 41.256193 | E22: MJ/kg
B23: =B22*A_DCFROR!D31/(365*24*3600) -> 8039872.5 | C23: J/s
B24: =B23*Inputs!F3*1/1000 -> 64318980 | C24: kWh/yr
A26: Year | D26: -2 | E26: -1 | F26: 0 | G26: 1 | H26: 2 | I26: 3 | J26: 4 | K26: 5 | L26: 6 | M26: 7 | N26: 8 | O26: 9 | P26: 10 | Q26: 11 | R26: 12 | S26: 13 | T26: 14 | U26: 15 | V26: 16 | W26: 17 | X26: 18 | Y26: 19 | Z26: 20 | AA26: 21 | AB26: 22 | AC26: 23 | AD26: 24 | AE26: 25 | AF26: 26 | AG26: 27 | AH26: 28 | AI26: 29 | AJ26: 30
A28: Discount Factor | D28: =1/(1+AB_DCFROR!$D$38)^D26 -> 1.21 | E28: =1/(1+AB_DCFROR!$D$38)^E26 -> 1.1 | F28: =1/(1+AB_DCFROR!$D$38)^F26 -> 1 | G28: =1/(1+AB_DCFROR!$D$38)^G26 -> 0.90909091 | H28: =1/(1+AB_DCFROR!$D$38)^H26 -> 0.82644628 | I28: =1/(1+AB_DCFROR!$D$38)^I26 -> 0.7513148 | J28: =1/(1+AB_DCFROR!$D$38)^J26 -> 0.68301346 | K28: =1/(1+AB_DCFROR!$D$38)^K26 -> 0.62092132 | ... AJ28: =1/(1+AB_DCFROR!$D$38)^AJ26 -> 0.057308553
A30: SUSTAINABLE AVIATION FUEL
A31: Energy Generated | D31: 0 | E31: 0 | F31: 0 | G31: =(H31)*(1-AB_DCFROR!D26)+(J31*AB_DCFROR!D26*AB_DCFROR!D27) -> 52821962 | H31: =$B$22*A_DCFROR!$D$31/3600000 -> 70429283 | I31: =$B$22*A_DCFROR!$D$31/3600000 -> 70429283 | J31: =$B$22*A_DCFROR!$D$31/3600000 -> 70429283 | K31: =$B$22*A_DCFROR!$D$31/3600000 -> 70429283 | L31: =$B$22*A_DCFROR!$D$31/3600000 -> 70429283 | M31: =$B$22*A_DCFROR!$D$31/3600000 -> 70429283 | N31: =$B$22*A_DCFROR!$D$31/3600000 -> 70429283 | O31: =$B$22*A_DCFROR!$D$31/3600000 -> 70429283 | ... AJ31: =$B$22*A_DCFROR!$D$31/3600000 -> 70429283
A32: Discounted Energy | D32: =D31*D28 -> 0 | E32: =E31*E28 -> 0 | F32: =F31*F28 -> 0 | G32: =G31*G28 -> 48019966 | H32: =H31*H28 -> 58206019 | I32: =I31*I28 -> 52914563 | J32: =J31*J28 -> 48104148 | K32: =K31*K28 -> 43731044 | ... AJ32: =AJ31*AJ28 -> 4036200.3
A33: Total Discounted Energy | B33: =SUM(D32:AJ32) -> 6.4792417e+08 | C33: kWh
A35: Waste Collected (kg/yr)
A36: Waste Collected - 0.48 M Scale | G36: =A_DCFROR!$D$33 -> 2.2414277e+08 | H36: =A_DCFROR!$D$33 -> 2.2414277e+08 | I36: =A_DCFROR!$D$33 -> 2.2414277e+08 | J36: =A_DCFROR!$D$33 -> 2.2414277e+08 | K36: =A_DCFROR!$D$33 -> 2.2414277e+08 | L36: =A_DCFROR!$D$33 -> 2.2414277e+08 | M36: =A_DCFROR!$D$33 -> 2.2414277e+08 | N36: =A_DCFROR!$D$33 -> 2.2414277e+08 | ... AJ36: =A_DCFROR!$D$33 -> 2.2414277e+08
A37: Discounted Waste | G37: =G36*G28 -> 2.0376615e+08 | H37: =H36*H28 -> 1.8524196e+08 | I37: =I36*I28 -> 1.6840178e+08 | J37: =J36*J28 -> 1.5309253e+08 | K37: =K36*K28 -> 1.3917503e+08 | L37: =L36*L28 -> 1.2652275e+08 | M37: =M36*M28 -> 1.1502068e+08 | N37: =N36*N28 -> 1.0456426e+08 | ... AJ37: =AJ36*AJ28 -> 12845298
A38: Total Discounted Waste | B38: =SUM(G37:AJ37) -> 2.1129747e+09 | C38: kg
A40: Discounted Capital Costs | D40: =(AB_DCFROR!D6)*AB_DCFROR!D21*D28 -> 3.000907e+08 | E40: =(AB_DCFROR!D6)*A_DCFROR!D22*E28 -> 1.3640486e+09 | F40: =AB_DCFROR!D6*AB_DCFROR!D23*F28 -> 9.9203536e+08
A41: Land Capital - Discounted | D41: =AB_DCFROR!D7*D28 -> 4.5013605e+08
A42: Working Capital - Discounted | F42: =AB_DCFROR!D8*F28 -> 1.2400442e+08
A43: Operational Costs | G43: =AB_DCFROR!$D$5*G28 -> 1.918156e+08 | H43: =AB_DCFROR!$D$5*H28 -> 1.7437782e+08 | I43: =AB_DCFROR!$D$5*I28 -> 1.5852529e+08 | J43: =AB_DCFROR!$D$5*J28 -> 1.441139e+08 | K43: =AB_DCFROR!$D$5*K28 -> 1.3101263e+08 | L43: =AB_DCFROR!$D$5*L28 -> 1.191024e+08 | M43: =AB_DCFROR!$D$5*M28 -> 1.082749e+08 | N43: =AB_DCFROR!$D$5*N28 -> 98431732 | ... AJ43: =AB_DCFROR!$D$5*AJ28 -> 12091942
